Workbook

Sheet Cover
B2: MERGER MODEL & ACQUISITION ANALYSIS
B3: Meridian Industrial Supply, Inc. (MIDS) proposed acquisition of Calder Fluid & Flow Systems, Inc. (CFFS)
B4: All figures in $ millions except per-share data. All companies, figures and market data are fictional and were created for this exercise.
B6: TRANSACTION SNAPSHOT
C8: Proposed Structure | E8: 100% stock (switchable to a cash / debt / stock mix)
C9: Exchange Ratio | E9: 1.4000x
C10: Offer Price per Share | E10: =Merger_Model!$E$15 -> 48.3
C11: Premium to Undisturbed Price | E11: =Merger_Model!$E$17 -> 0.27777778
C12: Purchase Equity Value | E12: =Merger_Model!$E$20 -> 2697.84
C13: Purchase Enterprise Value | E13: =Merger_Model!$E$23 -> 2984.2793
C14: Purchase TEV / FY25E EBITDA | E14: =Merger_Model!E27 -> 9.3927607
C15: Run-Rate Cost Synergies by Year 3 | E15: =Synergies!$I$16 -> 95.437822
C16: Combined Year 1 EPS Accretion / (Dilution) | E16: =Merger_Model!$G$135 -> -0.10827477
C17: Combined Year 3 EPS Accretion / (Dilution) | E17: =Merger_Model!$I$135 -> 0.036944412
B20: HOW TO READ THIS MODEL
C22: Colour convention | E22: Blue — hardcoded input or scenario lever. These are the only cells intended to be edited.
E23: Black — a formula calculated on the same tab.
E24: Green — a live link to another tab.
E25: Grey italics — commentary explaining the assumption or methodology (column M on most tabs).
C27: Key levers | E27: Merger_Model E9 — transaction structure: 2 = 100% stock, 1 = cash / debt / stock mix.
E28: Merger_Model E10 / E11 — switch revenue and expense synergies on or off.
E29: Merger_Model E12 — expense synergy realisation factor, the single most important variable in the model.
E30: Merger_Model E14 — exchange ratio, which drives both the price paid and the ownership split.
C32: Acquirer balance sheet (FY30E) | E32: =Acquirer!K147 -> 0
C33: Target balance sheet (FY30E) | E33: =Target!K147 -> 0
C34: Pro-forma opening balance sheet | E34: =Combined_BS!I40 -> 0
C35: Sources less uses of funds | E35: =Merger_Model!E69 -> 0
B37: TAB INDEX
C39: Merger_Model | E39: Deal assumptions, sources & uses, purchase price allocation, combined income statement and cash flow, EPS accretion and sensitivities.
C40: Acquirer | E40: Meridian standalone three-statement operating model, FY24A-FY30E.
C41: Target | E41: Calder standalone three-statement operating model, FY24A-FY30E.
C42: Synergies | E42: Headcount-driven cost synergies, cross-sell revenue synergies, costs to achieve, and the PV of synergies versus the premium paid.
C43: Combined_BS | E43: Purchase-accounting balance sheet combination at the close date.
C44: DCF_IRR | E44: Ten-year unlevered DCF of the target and the acquirer's IRR on the transaction, with sensitivities.
C45: WACC | E45: Peer beta unlevering and re-levering; discount rates for both companies.
C46: Pub_Comps | E46: Trading comparables for the sector.
C47: MA_Comps | E47: Precedent control transactions.
C48: Contrib | E48: Relative contribution analysis and the exchange ratio each metric implies.
C49: Value_Creation | E49: Combined entity valued against larger-cap platform multiples.

Sheet Merger_Model
B2: Merger Model -Meridian Industrial Supply, Inc. (MIDS) / Calder Fluid & Flow Systems, Inc. (CFFS)
B3: ($ in millions, except per-share and per-unit data)
B4: Transaction assumptions, sources & uses, purchase price allocation and the combined income statement, cash flow and credit profile. FY26E is the first full combined year (Combined Year 1).
B5: 1. TRANSACTION ASSUMPTIONS & DEAL SWITCHES | M5: Yellow-shaded cells are the levers a reviewer should drive: deal structure, synergy switches and the realisation factor.
C7: Transaction Close Date | D7: Date | E7: 46022 | F7: (end of FY25E)
C8: Valuation / Analysis Date | D8: Date | E8: 46022
C9: Transaction Type (1 = Cash / Debt / Stock, 2 = 100% Stock) | D9: # | E9: 2 | M9: Master structure switch. 2 = management's proposed all-stock deal. 1 = maximum cash and debt first, with stock plugging the balance.
C10: Include Revenue Synergies? (1 = Yes, 0 = No) | D10: # | E10: 1
C11: Include Expense Synergies? (1 = Yes, 0 = No) | D11: # | E11: 1
C12: Expense Synergy Realisation Factor | D12: % | E12: 1
C14: Exchange Ratio | D14: x | E14: 1.4 | M14: Target holders receive this many Meridian shares per Calder share. Drives both the offer price and the pro-forma ownership split.
C15: Implied Offer Price per Share | D15: $ / sh | E15: =E14*Acquirer!E11 -> 48.3
C16: Target Share Price (Undisturbed) | D16: $ / sh | E16: =Target!$E$11 -> 37.8
C17: Premium Paid | D17: % | E17: =E15/E16-1 -> 0.27777778
C19: Target Diluted Shares @ Offer Price | D19: M sh | E19: =Target!E13+IF(Merger_Model!E15>Target!S16,Target!$R$16-Target!$R$16*Target!$S$16/Merger_Model!E15,0)+Target!R17 -> 55.855901 | M19: Treasury stock method re-run at the OFFER price, not the market price -a higher offer pulls more options into the money and raises the share count being bought.
C20: Purchase Equity Value | D20: $M | E20: =E15*E19 -> 2697.84
C21: (+) Target Total Debt Assumed / Refinanced | D21: $M | E21: =Target!F135 -> 506.7 | M21: Calder's debt is refinanced at close on identical economics, so it is a wash in the accretion analysis but still sits in the purchase enterprise value.
C22: (-) Target Cash Acquired | D22: $M | E22: =-Target!F116 -> -220.26067
C23: Purchase Enterprise Value | D23: $M | E23: =SUM(E20:E22) -> 2984.2793
C25: Purchase TEV / FY25E Revenue | D25: x | E25: =E23/Target!F90 -> 1.1018199
C26: Purchase TEV / FY24A EBITDA | D26: x | E26: =E23/Target!E192 -> 10.558162
C27: Purchase TEV / FY25E EBITDA | D27: x | E27: =E23/Target!F192 -> 9.3927607 | M27: Compare against the trading comps (Pub_Comps) and the precedent transactions (MA_Comps) to judge whether the price is fair.
C28: Purchase Equity Value / FY25E Net Income | D28: x | E28: =E20/Target!F108 -> 15.434651
B30: 2. FINANCING CAPACITY & COST | M30: Sets the ceiling on how much cash and debt the buyer can put into the deal before the stock component has to fill the gap.
C31: Post-Transaction Minimum Cash Balance | D31: $M | E31: 200 | M31: Operating cash the combined business must retain for working-capital seasonality; it cannot be spent on the deal.
C32: Combined Cash at Close (FY25E) | D32: $M | E32: =Acquirer!F116+Target!F116 -> 582.42509
C33: Maximum Cash Available for the Deal | D33: $M | E33: =MAX(E32-E31,0) -> 382.42509
C34: Maximum Combined Debt / EBITDA | D34: x | E34: 4 | M34: Credit-agreement style ceiling. At 4.0x the combined company would sit at the top of the range peers can carry -arguably too far, which is the point of case question 3.
C35: Combined FY25E EBITDA | D35: $M | E35: =Acquirer!F192+Target!F192 -> 953.52712
C36: Existing Combined Debt at Close | D36: $M | E36: =Acquirer!F135+Target!F135 -> 2040.9
C37: Maximum New Debt Available for the Deal | D37: $M | E37: =MAX(E34*E35-E36,0) -> 1773.2085
C38: New Debt - Premium to Acquirer's Cost of Debt | D38: bps | E38: 200
C39: New Debt - Pre-Tax Interest Rate | D39: % | E39: =Acquirer!E75+Merger_Model!E38/10000 -> 0.0775 | M39: Acquisition debt prices wide of the existing capital structure because it is incremental leverage on a larger, less proven credit.
C40: New Debt - Annual Amortisation | D40: % | E40: 0.01
C41: New Debt - Maturity | D41: # yrs | E41: 5
C42: Foregone Interest Rate on Cash Used | D42: % | E42: 0.035 | M42: Cash spent on the deal stops earning interest -a real, if small, cost of the cash component.
C44: Advisory Fee (% of Purchase Equity Value) | D44: % | E44: 0.01
C45: Debt Issuance Fee (% of New Debt) | D45: % | E45: 0.02
C46: Legal, Accounting & Other Fees | D46: $M | E46: 12
B48: 3. CONSIDERATION MIX & THE ACCRETION TEST
C49: Cash Used | D49: $M | E49: =IF(E9=2,0,MIN(E33,E20)) -> 0
C50: New Debt Issued | D50: $M | E50: =IF(E9=2,0,MIN(E37,MAX(E20-E49,0))) -> 0
C51: Stock Issued | D51: $M | E51: =E20-E49-E50 -> 2697.84 | M51: Under structure 1 the model uses cheap capital first (cash, then debt to the leverage ceiling) and issues stock only for the residual.
C52: Total Consideration | D52: $M | E52: =SUM(E49:E51) -> 2697.84
C53: New Acquirer Shares Issued | D53: M sh | E53: =E51/Acquirer!$E$11 -> 78.198261 | M53: Under 100% stock this reduces exactly to Exchange Ratio x Target Diluted Shares.
C54: Check: Total Consideration less Purchase Equity Value | D54: $M | E54: =ROUND(E52-E20,6) -> 0
C56: Weighted Average Cost of Acquisition Capital (After-Tax) | D56: % | E56: =IFERROR((E49*E42*(1-Acquirer!$E$10)+E50*E39*(1-Acquirer!$E$10)+E51*(Acquirer!G111/Acquirer!$E$11))/E20,0) -> 0.091444436 | M56: Cost of cash = foregone after-tax interest; cost of debt = after-tax coupon; cost of stock = the acquirer's FY26E earnings yield (inverse P/E).
C57: Target's Yield (FY26E Net Income / Purchase Equity Value) | D57: % | E57: =Target!G108/Merger_Model!E20 -> 0.073932951
C58: Quick Test: Accretive or Dilutive Before Synergies? | E58: =IF(E57>E56,"ACCRETIVE -target yield exceeds cost of capital","DILUTIVE -cost of capital exceeds target yield") -> DILUTIVE -cost of capital exceeds target yield | M58: The classic screen: a deal is accretive before synergies when what you buy yields more than what you pay with. Stock is the most expensive currency here because Meridian trades on a low earnings yield relative to Calder's.
B60: 4. SOURCES & USES OF FUNDS
C62: Sources | E62: $M | G62: Uses | K62: $M
C63: Cash on Hand | E63: =E49+E44*E20+E46 -> 38.9784 | G63: Purchase Target Equity | K63: =E20 -> 2697.84 | M63: Cash on hand funds the cash consideration plus all expensed fees. Debt financing fees are capitalised against the new debt and amortised over its life.
C64: New Acquisition Debt Issued | E64: =E50 -> 0 | G64: Repay / Refinance Target Debt | K64: =E21 -> 506.7
C65: New Debt to Refinance Target Debt | E65: =E21 -> 506.7 | G65: Advisory Fees | K65: =E44*E20 -> 26.9784
C66: Acquirer Stock Issued to Target Holders | E66: =E51 -> 2697.84 | G66: Legal, Accounting & Other Fees | K66: =E46 -> 12
C67: Debt Financing Fees (Capitalised) | E67: =E45*(E50+E21) -> 10.134 | G67: Debt Financing Fees | K67: =E45*(E50+E21) -> 10.134
C68: Total Sources | E68: =SUM(E63:E67) -> 3253.6524 | G68: Total Uses | K68: =SUM(K63:K67) -> 3253.6524
C69: Check: Sources less Uses | E69: =ROUND(E68-K68,6) -> 0
B71: 5. PURCHASE PRICE ALLOCATION | M71: Allocates the premium to written-up assets first; whatever is left over becomes goodwill. The write-ups are what create the new D&A that drags on pro-forma EPS.
C73: Goodwill Calculation | E73: $M | G73: Write-Up Assumptions | K73: Value
C74: Purchase Equity Value | E74: =E20 -> 2697.84 | G74: PP&E Write-Up % | K74: 0.15 | M74: PP&E is written up to fair value; distribution centres and fleet carry meaningful appreciation over book.
C75: (-) Target Book Value of Equity at Close | E75: =-Target!F143 -> -1132.5583 | G75: PP&E Write-Up Amount | K75: =K74*Target!F121 -> 42.093885
C76: (+) Write-Off of Target's Existing Goodwill | E76: =Target!F123 -> 470 | G76: Depreciation Period | K76: 15
C77: Total Allocable Purchase Premium | E77: =SUM(E74:E76) -> 2035.2817 | G77: Annual Depreciation on Write-Up | K77: =K75/K76 -> 2.806259
C79: (-) Write-Up of PP&E | E79: =-K79 -> -42.093885 | G79: PP&E Write-Up (to goodwill calc) | K79: =K75 -> 42.093885
C80: (-) Write-Up of Intangible Assets | E80: =-K84 -> -377.6976 | G80: % Allocated to Indefinite-Lived Intangibles | K80: 0.03 | M80: Trade names are indefinite-lived and NOT amortised; customer relationships are amortised over 12 years and are the main purchase-accounting drag on EPS.
C81: (-) Write-Off of Target's Existing Net DTL | E81: =-Target!F137 -> -12.537624 | G81: Indefinite-Lived Intangibles (Trade Names) | K81: =K80*E20 -> 80.9352
C82: (+) New Deferred Tax Liability | E82: =K86 -> 100.74996 | G82: % Allocated to Definite-Lived Intangibles | K82: 0.11 | M82: Asset write-ups are not deductible for tax, so a DTL is booked at the acquirer's tax rate and increases goodwill.
C83: Total Goodwill Created | E83: =E77+SUM(E79:E82) -> 1703.7025 | G83: Definite-Lived Intangibles (Customer Relationships) | K83: =K82*E20 -> 296.7624
G84: Total Intangible Write-Up | K84: =K81+K83 -> 377.6976
C85: Memo: Goodwill % of Purchase Equity Value | D85: % | E85: =E83/E20 -> 0.63150614 | G85: Amortisation Period | K85: 12
G86: New Deferred Tax Liability | K86: =(K75+K84)*Acquirer!$E$10 -> 100.74996
G87: Annual Amortisation of New Intangibles | K87: =K83/K85 -> 24.7302
B88: 6. COMBINED INCOME STATEMENT & EPS ACCRETION / (DILUTION) | G88: Combined Yr 1 | H88: Combined Yr 2 | I88: Combined Yr 3 | J88: Combined Yr 4 | K88: Combined Yr 5 | M88: The deal closes on the last day of FY25E, so FY26E is the first full combined year. Pre-close years are intentionally left blank.
D89: ($ in millions) | E89: =EOMONTH(F89,-12) -> 45657 | F89: =E8 -> 46022 | G89: =EOMONTH(F89,12) -> 46387 | H89: =EOMONTH(G89,12) -> 46752 | I89: =EOMONTH(H89,12) -> 47118 | J89: =EOMONTH(I89,12) -> 47483 | K89: =EOMONTH(J89,12) -> 47848
C90: Revenue:
C91: (+) Acquirer Revenue | D91: $M | G91: =Acquirer!G90 -> 6756.087 | H91: =Acquirer!H90 -> 7060.9885 | I91: =Acquirer!I90 -> 7353.2209 | J91: =Acquirer!J90 -> 7627.6141 | K91: =Acquirer!K90 -> 7879.65
C92: (+) Target Revenue | D92: $M | G92: =Target!G90 -> 2854.0245 | H92: =Target!H90 -> 3000.0668 | I92: =Target!I90 -> 3143.3389 | J92: =Target!J90 -> 3280.8122 | K92: =Target!K90 -> 3408.3886
C93: (+) Revenue Synergies | D93: $M | G93: =Synergies!G26 -> 76.412175 | H93: =Synergies!H26 -> 160.47452 | I93: =Synergies!I26 -> 251.91614 | J93: =Synergies!J26 -> 310.94766 | K93: =Synergies!K26 -> 322.64635
C94: Total Revenue | D94: $M | G94: =SUM(G91:G93) -> 9686.5237 | H94: =SUM(H91:H93) -> 10221.53 | I94: =SUM(I91:I93) -> 10748.476 | J94: =SUM(J91:J93) -> 11219.374 | K94: =SUM(K91:K93) -> 11610.685
C96: (-) Cost of Sales -Acquirer | D96: $M | G96: =Acquirer!G91 -> -4945.4557 | H96: =Acquirer!H91 -> -5154.5216 | I96: =Acquirer!I91 -> -5360.498 | J96: =Acquirer!J91 -> -5552.9031 | K96: =Acquirer!K91 -> -5736.3852
C97: (-) Cost of Sales -Target | D97: $M | G97: =Target!G91 -> -2012.0873 | H97: =Target!H91 -> -2109.047 | I97: =Target!I91 -> -2203.4806 | J97: =Target!J91 -> -2296.5685 | K97: =Target!K91 -> -2385.872
C98: (-) Cost of Revenue Synergies | D98: $M | G98: =Synergies!G27 -> -53.870583 | H98: =Synergies!H27 -> -112.81359 | I98: =Synergies!I27 -> -176.59321 | J98: =Synergies!J27 -> -217.66336 | K98: =Synergies!K27 -> -225.85244
C99: Total Cost of Sales | D99: $M | G99: =SUM(G96:G98) -> -7011.4135 | H99: =SUM(H96:H98) -> -7376.3822 | I99: =SUM(I96:I98) -> -7740.5718 | J99: =SUM(J96:J98) -> -8067.135 | K99: =SUM(K96:K98) -> -8348.1096
C101: Gross Profit | D101: $M | G101: =G94+G99 -> 2675.1101 | H101: =H94+H99 -> 2845.1477 | I101: =I94+I99 -> 3007.9041 | J101: =J94+J99 -> 3152.239 | K101: =K94+K99 -> 3262.5753
C103: Operating Expenses:
C104: (-) SG&A -Acquirer | D104: $M | G104: =Acquirer!G95 -> -1134.635 | H104: =Acquirer!H95 -> -1188.8933 | I104: =Acquirer!I95 -> -1238.8107 | J104: =Acquirer!J95 -> -1286.3178 | K104: =Acquirer!K95 -> -1327.2364
C105: (-) SG&A -Target | D105: $M | G105: =Target!G95 -> -491.90245 | H105: =Target!H95 -> -516.1298 | I105: =Target!I95 -> -539.50559 | J105: =Target!J95 -> -562.11777 | K105: =Target!K95 -> -583.00953
C106: (-) Operating Expenses on Revenue Synergies | D106: $M | G106: =Synergies!G28 -> -13.169942 | H106: =Synergies!H28 -> -27.607945 | I106: =Synergies!I28 -> -43.237515 | J106: =Synergies!J28 -> -53.276199 | K106: =Synergies!K28 -> -55.189099
C107: (+) Expense (Cost) Synergies | D107: $M | G107: =Synergies!G18 -> 57.45949 | H107: =Synergies!H18 -> 81.633045 | I107: =Synergies!I18 -> 95.437822 | J107: =Synergies!J18 -> 98.110081 | K107: =Synergies!K18 -> 100.56283 | M107: Pulled from the Synergies tab after the on/off switch and the realisation factor have been applied.
C108: (-) Depreciation | D108: $M | G108: =Acquirer!G96+Target!G96 -> -124.53001 | H108: =Acquirer!H96+Target!H96 -> -131.12681 | I108: =Acquirer!I96+Target!I96 -> -137.27474 | J108: =Acquirer!J96+Target!J96 -> -142.38396 | K108: =Acquirer!K96+Target!K96 -> -147.38582
C109: (-) Amortisation of Existing Intangibles | D109: $M | G109: =Acquirer!G97+Target!G97 -> -44.538701 | H109: =Acquirer!H97+Target!H97 -> -44.638236 | I109: =Acquirer!I97+Target!I97 -> -44.495281 | J109: =Acquirer!J97+Target!J97 -> -44.084954 | K109: =Acquirer!K97+Target!K97 -> -43.385627
C110: (-) Depreciation of PP&E Write-Up | D110: $M | G110: =-$K$77 -> -2.806259 | H110: =-$K$77 -> -2.806259 | I110: =-$K$77 -> -2.806259 | J110: =-$K$77 -> -2.806259 | K110: =-$K$77 -> -2.806259 | M110: New non-cash D&A created by purchase accounting. Management's 'accretive in year one' claim excludes exactly these two lines.
C111: (-) Amortisation of New Intangibles | D111: $M | G111: =-$K$87 -> -24.7302 | H111: =-$K$87 -> -24.7302 | I111: =-$K$87 -> -24.7302 | J111: =-$K$87 -> -24.7302 | K111: =-$K$87 -> -24.7302
C112: (-) Legacy Merger & Integration Costs | D112: $M | G112: =Acquirer!G98+Target!G98 -> -3 | H112: =Acquirer!H98+Target!H98 -> 0 | I112: =Acquirer!I98+Target!I98 -> 0 | J112: =Acquirer!J98+Target!J98 -> 0 | K112: =Acquirer!K98+Target!K98 -> 0
C113: (-) New Merger & Integration Costs | D113: $M | G113: =-Synergies!G36 -> -63.625215 | H113: =-Synergies!H36 -> -31.812607 | I113: =-Synergies!I36 -> 0 | J113: =-Synergies!J36 -> 0 | K113: =-Synergies!K36 -> 0
C114: (-) Impairment of Assets | D114: $M | G114: =Acquirer!G99+Target!G99 -> 0 | H114: =Acquirer!H99+Target!H99 -> 0 | I114: =Acquirer!I99+Target!I99 -> 0 | J114: =Acquirer!J99+Target!J99 -> 0 | K114: =Acquirer!K99+Target!K99 -> 0
C115: Total Operating Expenses | D115: $M | G115: =SUM(G104:G114) -> -1845.4783 | H115: =SUM(H104:H114) -> -1886.1121 | I115: =SUM(I104:I114) -> -1935.4224 | J115: =SUM(J104:J114) -> -2017.6071 | K115: =SUM(K104:K114) -> -2083.1801
C117: Operating Income (EBIT) | D117: $M | G117: =G101+G115 -> 829.63185 | H117: =H101+H115 -> 959.03555 | I117: =I101+I115 -> 1072.4817 | J117: =J101+J115 -> 1134.6319 | K117: =K101+K115 -> 1179.3952
C118: (-) Interest Expense on Existing Debt | D118: $M | G118: =Acquirer!G103+Target!G103 -> -120.40363 | H118: =Acquirer!H103+Target!H103 -> -109.58487 | I118: =Acquirer!I103+Target!I103 -> -97.855125 | J118: =Acquirer!J103+Target!J103 -> -85.214375 | K118: =Acquirer!K103+Target!K103 -> -71.662625
...

Sheet Acquirer
B2: Acquirer: Meridian Industrial Supply, Inc. (MIDS) — Standalone Operating Model
B3: ($ in Millions Except Per Share and Per Unit Data)
B4: Meridian is a national distributor of maintenance, repair and operating (MRO) supplies, fasteners, power-transmission components and fluid-handling products, serving industrial, energy and institutional end markets through ~230 branches and four regional DCs.
B5: 1. FINANCIAL PROFILE & CURRENT MARKET VALUATION | D5: Units
C7: Company Name: | D7: Name | E7: Meridian Industrial Supply, Inc.
C8: Ticker: | D8: Name | E8: MIDS
C9: Last Fiscal Year: | D9: Date | E9: 45657
C10: Effective Tax Rate: | D10: % | E10: 0.24 | M10: Blended federal + state rate, held flat. Drives the tax provision in every projected year.
C11: Share Price (Undisturbed) | D11: $ as Stated | E11: 34.5 | M11: Unaffected price one day prior to announcement — the basis for the offer premium.
C13: Basic Shares Outstanding | D13: M sh | E13: 116.4 | P13: Treasury Stock Method:
C14: (+) Net Dilution from Options & RSUs | D14: M sh | E14: =T20 -> 2.3057971 | M14: Treasury stock method — schedule in columns P:S. Options are dilutive only when in the money.
C15: Diluted Shares Outstanding | D15: M sh | E15: =SUM(E13:E14) -> 118.7058 | P15: Name: | R15: Units (M) | S15: Strike | T15: Net Dilution
P16: Options | R16: 3.2 | S16: 21.5 | T16: =IF($E$11>S16,R16-R16*S16/$E$11, 0) -> 1.2057971
C17: Current Equity Value (Market Capitalisation) | D17: $M | E17: =E15*E11 -> 4095.35 | P17: RSUs / Restricted Stock | R17: 1.1 | S17: n/a | T17: =R17 -> 1.1
C18: (-) Cash & Cash Equivalents | D18: $M | E18: =-E116 -> -210.04235
C19: (+) Total Debt & Finance Leases | D19: $M | E19: =E135 -> 1650
C20: (+) Operating Lease Liabilities | D20: $M | M20: Deliberately excluded: Rent is part of SG&A, so, lease is excluded. Treated the same way on Pub_Comps and MA_Comps. | P20: Total Net Dilution | R20: =SUM(R16:R17) -> 4.3 | T20: =SUM(T16:T17) -> 2.3057971
C21: (+) Preferred Stock | D21: $M
C22: (+) Noncontrolling Interests | D22: $M
C23: (-) NOLs & Non-Core Assets | D23: $M | M23: Neither company carries material NOLs or non-core assets; set to zero to keep the bridge clean.
C24: Current Enterprise Value (TEV) | D24: $M | E24: =SUM(E17:E23) -> 5535.3077
C26: TEV / FY24A EBITDA | D26: x | E26: =E24/E192 -> 9.4133691
C27: TEV / FY25E EBITDA | D27: x | E27: =E24/F192 -> 8.7059708
C28: Price / FY24A EPS | D28: x | E28: =E11/E111 -> 13.657464
B32: 2. OPERATING DRIVERS & PROJECTION ASSUMPTIONS | G32: Projected: | M32: Every projected line item is driven from this block of drivers.
E33: =Merger_Model!$E$89 -> 45657 | F33: =Merger_Model!$F$89 -> 46022 | G33: =Merger_Model!$G$89 -> 46387 | H33: =Merger_Model!$H$89 -> 46752 | I33: =Merger_Model!$I$89 -> 47118 | J33: =Merger_Model!$J$89 -> 47483 | K33: =Merger_Model!$K$89 -> 47848
C35: Revenue Growth Rates by Segment:
C36: Fasteners & MRO Consumables | D36: % | E36: n/a | F36: 0.03 | G36: 0.035 | H36: 0.033 | I36: 0.03 | J36: 0.028 | K36: 0.025
C37: Power Transmission & Automation | D37: % | E37: n/a | F37: 0.055 | G37: 0.06 | H37: 0.055 | I37: 0.05 | J37: 0.045 | K37: 0.04
C38: Fluid Handling & Process | D38: % | E38: n/a | F38: 0.035 | G38: 0.045 | H38: 0.042 | I38: 0.038 | J38: 0.035 | K38: 0.03
C39: Safety & Facility Solutions | D39: % | E39: n/a | F39: 0.045 | G39: 0.05 | H39: 0.048 | I39: 0.045 | J39: 0.04 | K39: 0.035
C40: Engineered Services & Solutions | D40: % | E40: n/a | F40: 0.065 | G40: 0.07 | H40: 0.065 | I40: 0.06 | J40: 0.05 | K40: 0.045
C42: Cost of Sales % of Revenue | D42: % | E42: =-E91/E90 -> 0.735 | F42: 0.734 | G42: 0.732 | H42: 0.73 | I42: 0.729 | J42: 0.728 | K42: 0.728 | M42: Gross-margin improves due to private-label penetration and also due to normalisation of freight and input costs
C44: Total Employees | D44: # | E44: 14200 | F44: 14150 | G44: 14450 | H44: 14700 | I44: 14900 | J44: 15050 | K44: 15150 | M44: Head-count is a core SG&A Driver. It is also the lever pulled in cost-synergy schedule
C45: Revenue per Employee | D45: $ | E45: =E90*1000000/E44 -> 435563.38 | F45: =F90*1000000/F44 -> 455517.67 | G45: =G90*1000000/G44 -> 467549.27 | H45: =H90*1000000/H44 -> 480339.35 | I45: =I90*1000000/I44 -> 493504.76 | J45: =J90*1000000/J44 -> 506818.21 | K45: =K90*1000000/K44 -> 520108.91
C46: SG&A Spending per Employee | D46: $ | E46: =-E95*1000000/E44 -> 74014 | F46: =E46*(1+F47) -> 76234.42 | G46: =F46*(1+G47) -> 78521.453 | H46: =G46*(1+H47) -> 80877.096 | I46: =H46*(1+I47) -> 83141.655 | J46: =I46*(1+J47) -> 85469.621 | K46: =J46*(1+K47) -> 87606.362 | M46: SG&A = Employees x cost per employee. This way we can directly link workforce reduction to dollars
C47: Growth Rate | D47: % | F47: 0.03 | G47: 0.03 | H47: 0.03 | I47: 0.028 | J47: 0.028 | K47: 0.025
C49: Depreciation % of Revenue | D49: % | E49: =-E96/E90 -> 0.0115 | F49: 0.0116 | G49: 0.0118 | H49: 0.0119 | I49: 0.012 | J49: 0.012 | K49: 0.012
C50: Amortisation of Intangibles % of Revenue | D50: % | E50: =-E97/E90 -> 0.0042 | F50: 0.0042 | G50: 0.0041 | H50: 0.0039 | I50: 0.0037 | J50: 0.0035 | K50: 0.0033 | M50: Existing tangibles amortise over time, so this % goes down over the period
C51: Legacy Merger & Integration Costs | D51: $M | E51: 0 | F51: 0 | G51: 0 | H51: 0 | I51: 0 | J51: 0 | K51: 0
C52: Impairment of Assets | D52: $M | E52: 0 | F52: 0 | G52: 0 | H52: 0 | I52: 0 | J52: 0 | K52: 0
C53: Other Income, Net | D53: $M | E53: 0 | F53: 0 | G53: 0 | H53: 0 | I53: 0 | J53: 0 | K53: 0
C55: Accounts Receivable % of Revenue | D55: % | E55: =E117/E90 -> 0.128 | F55: 0.128 | G55: 0.128 | H55: 0.128 | I55: 0.128 | J55: 0.128 | K55: 0.128
C56: Inventory & Other Current Assets % of COGS | D56: % | E56: =-E118/E91 -> 0.205 | F56: 0.205 | G56: 0.203 | H56: 0.2025 | I56: 0.201 | J56: 0.2 | K56: 0.2
C57: Operating Lease ROU Assets % of SG&A | D57: % | E57: =-E122/E95 -> 0.2331 | F57: 0.2331 | G57: 0.2331 | H57: 0.2331 | I57: 0.2331 | J57: 0.2331 | K57: 0.2331 | M57: ROU asset and lease liability are held equal, so the two cancel in working capital and the balance sheet stays clean.
C58: Accounts Payable % of COGS | D58: % | E58: =-E131/E91 -> 0.136 | F58: 0.136 | G58: 0.137 | H58: 0.138 | I58: 0.138 | J58: 0.139 | K58: 0.139
C59: Accrued Liabilities % of SG&A | D59: % | E59: =-E132/E95 -> 0.27 | F59: 0.27 | G59: 0.27 | H59: 0.27 | I59: 0.27 | J59: 0.27 | K59: 0.27
C61: Stock-Based Compensation % of Revenue | D61: % | E61: =E156/E90 -> 0.0028 | F61: 0.0028 | G61: 0.0028 | H61: 0.0028 | I61: 0.0028 | J61: 0.0028 | K61: 0.0028
C62: Deferred Income Taxes % of Book Taxes | D62: % | E62: =-E157/E107 -> 0.12 | F62: 0.12 | G62: 0.1 | H62: 0.08 | I62: 0.06 | J62: 0.05 | K62: 0.05
C63: Other Non-Cash Items | D63: $M | E63: =E158 -> -6 | F63: 0 | G63: 0 | H63: 0 | I63: 0 | J63: 0 | K63: 0
C65: Capital Expenditures % of Revenue | D65: % | E65: =-E169/E90 -> 0.013 | F65: 0.013 | G65: 0.0135 | H65: 0.0135 | I65: 0.013 | J65: 0.013 | K65: 0.0125
C66: Proceeds from Sale of PP&E | D66: $M | E66: =E170 -> 4 | F66: 4 | G66: 4 | H66: 4 | I66: 4 | J66: 4 | K66: 4
C67: Acquisition Spending | D67: $M | E67: =-E171 -> 64.9 | F67: 0 | G67: 0 | H67: 0 | I67: 0 | J67: 0 | K67: 0 | M67: Projections assume no more spending on M&A
C69: Debt Issuances | D69: $M | E69: =E174 -> 450 | F69: 0 | G69: 0 | H69: 0 | I69: 0 | J69: 0 | K69: 0 | M69: No new debt is issued in the projections
C70: Debt Repayments | D70: $M | E70: 420 | F70: 120 | G70: 130 | H70: 140 | I70: 150 | J70: 160 | K70: 170 | M70: Contractual amortisation + volunteer repayment
C71: Share Repurchases | D71: $M | E71: =-E176 -> 95 | F71: 0 | G71: 0 | H71: 0 | I71: 0 | J71: 0 | K71: 0 | M71: Share repurchase is suspended. So, share dilution is just through deal consideration.
C72: Common Dividends | D72: $M | E72: =-E177 -> 0 | F72: 85 | G72: 95 | H72: 105 | I72: 115 | J72: 125 | K72: 135 | M72: Assumes that dividend repayment begins in FY25. Since, share buyback stopped, dividend absorbs most of the cashflow
C73: Debt Issuance Fees Paid | D73: $M | E73: =-E178 -> 9 | F73: 0 | G73: 0 | H73: 0 | I73: 0 | J73: 0 | K73: 0
C75: Weighted Average Interest Rate on Debt | D75: % | E75: 0.0575 | F75: 0.0575 | G75: 0.0575 | H75: 0.0575 | I75: 0.0575 | J75: 0.0575 | K75: 0.0575 | M75: Assumes coupon rate rather than blended interest
C76: Beginning Total Debt Balance | D76: $M | E76: 1624.5 | F76: 1650 | G76: 1534.2 | H76: 1408.1 | I76: 1271.7 | J76: 1125 | K76: 968
C77: Interest Income % of Beginning Cash | D77: % | E77: 0.035 | F77: 0.035 | G77: 0.035 | H77: 0.035 | I77: 0.035 | J77: 0.035 | K77: 0.035
C78: Amortisation of Debt Issuance Fees | D78: $M | E78: =E154 -> 4.5 | F78: 4.2 | G78: 3.9 | H78: 3.6 | I78: 3.3 | J78: 3 | K78: 2.7
B81: 3. INCOME STATEMENT | G81: Projected:
E82: =Merger_Model!$E$89 -> 45657 | F82: =Merger_Model!$F$89 -> 46022 | G82: =Merger_Model!$G$89 -> 46387 | H82: =Merger_Model!$H$89 -> 46752 | I82: =Merger_Model!$I$89 -> 47118 | J82: =Merger_Model!$J$89 -> 47483 | K82: =Merger_Model!$K$89 -> 47848
C84: Revenue:
C85: (+) Fasteners & MRO Consumables | D85: $ M | E85: 2180 | F85: =E85*(1+F36) -> 2245.4 | G85: =F85*(1+G36) -> 2323.989 | H85: =G85*(1+H36) -> 2400.6806 | I85: =H85*(1+I36) -> 2472.7011 | J85: =I85*(1+J36) -> 2541.9367 | K85: =J85*(1+K36) -> 2605.4851
C86: (+) Power Transmission & Automation | D86: $ M | E86: 1395 | F86: =E86*(1+F37) -> 1471.725 | G86: =F86*(1+G37) -> 1560.0285 | H86: =G86*(1+H37) -> 1645.8301 | I86: =H86*(1+I37) -> 1728.1216 | J86: =I86*(1+J37) -> 1805.887 | K86: =J86*(1+K37) -> 1878.1225
C87: (+) Fluid Handling & Process | D87: $ M | E87: 1120 | F87: =E87*(1+F38) -> 1159.2 | G87: =F87*(1+G38) -> 1211.364 | H87: =G87*(1+H38) -> 1262.2413 | I87: =H87*(1+I38) -> 1310.2065 | J87: =I87*(1+J38) -> 1356.0637 | K87: =J87*(1+K38) -> 1396.7456
C88: (+) Safety & Facility Solutions | D88: $ M | E88: 880 | F88: =E88*(1+F39) -> 919.6 | G88: =F88*(1+G39) -> 965.58 | H88: =G88*(1+H39) -> 1011.9278 | I88: =H88*(1+I39) -> 1057.4646 | J88: =I88*(1+J39) -> 1099.7632 | K88: =J88*(1+K39) -> 1138.2549
C89: (+) Engineered Services & Solutions | D89: $ M | E89: 610 | F89: =E89*(1+F40) -> 649.65 | G89: =F89*(1+G40) -> 695.1255 | H89: =G89*(1+H40) -> 740.30866 | I89: =H89*(1+I40) -> 784.72718 | J89: =I89*(1+J40) -> 823.96354 | K89: =J89*(1+K40) -> 861.04189
C90: Total Revenue | D90: $ M | E90: =SUM(E85:E89) -> 6185 | F90: =SUM(F85:F89) -> 6445.575 | G90: =SUM(G85:G89) -> 6756.087 | H90: =SUM(H85:H89) -> 7060.9885 | I90: =SUM(I85:I89) -> 7353.2209 | J90: =SUM(J85:J89) -> 7627.6141 | K90: =SUM(K85:K89) -> 7879.65
C91: (-) Cost of Sales | D91: $ M | E91: -4545.975 | F91: =-F90*F42 -> -4731.052 | G91: =-G90*G42 -> -4945.4557 | H91: =-H90*H42 -> -5154.5216 | I91: =-I90*I42 -> -5360.498 | J91: =-J90*J42 -> -5552.9031 | K91: =-K90*K42 -> -5736.3852
C92: Gross Profit | D92: $ M | E92: =SUM(E90:E91) -> 1639.025 | F92: =SUM(F90:F91) -> 1714.5229 | G92: =SUM(G90:G91) -> 1810.6313 | H92: =SUM(H90:H91) -> 1906.4669 | I92: =SUM(I90:I91) -> 1992.7229 | J92: =SUM(J90:J91) -> 2074.711 | K92: =SUM(K90:K91) -> 2143.2648
C94: Operating Expenses:
C95: (-) Selling, General & Administrative | D95: $ M | E95: -1050.9988 | F95: =-F44/1000000*F46 -> -1078.717 | G95: =-G44/1000000*G46 -> -1134.635 | H95: =-H44/1000000*H46 -> -1188.8933 | I95: =-I44/1000000*I46 -> -1238.8107 | J95: =-J44/1000000*J46 -> -1286.3178 | K95: =-K44/1000000*K46 -> -1327.2364
C96: (-) Depreciation | D96: $ M | E96: -71.1275 | F96: =-F90*F49 -> -74.76867 | G96: =-G90*G49 -> -79.721827 | H96: =-H90*H49 -> -84.025763 | I96: =-I90*I49 -> -88.23865 | J96: =-J90*J49 -> -91.531369 | K96: =-K90*K49 -> -94.5558
C97: (-) Amortisation of Intangibles | D97: $ M | E97: -25.977 | F97: =-F90*F50 -> -27.071415 | G97: =-G90*G50 -> -27.699957 | H97: =-H90*H50 -> -27.537855 | I97: =-I90*I50 -> -27.206917 | J97: =-J90*J50 -> -26.696649 | K97: =-K90*K50 -> -26.002845
C98: (-) Legacy Merger & Integration Costs | D98: $ M | E98: 0 | F98: =-F51 -> 0 | G98: =-G51 -> 0 | H98: =-H51 -> 0 | I98: =-I51 -> 0 | J98: =-J51 -> 0 | K98: =-K51 -> 0
C99: (-) Impairment of Assets | D99: $ M | E99: 0 | F99: =-F52 -> 0 | G99: =-G52 -> 0 | H99: =-H52 -> 0 | I99: =-I52 -> 0 | J99: =-J52 -> 0 | K99: =-K52 -> 0
C100: Total Operating Expenses | D100: $ M | E100: =SUM(E95:E99) -> -1148.1033 | F100: =SUM(F95:F99) -> -1180.5571 | G100: =SUM(G95:G99) -> -1242.0568 | H100: =SUM(H95:H99) -> -1300.4569 | I100: =SUM(I95:I99) -> -1354.2562 | J100: =SUM(J95:J99) -> -1404.5458 | K100: =SUM(K95:K99) -> -1447.795
C102: Operating Income (EBIT) | D102: $ M | E102: =SUM(E92,E100) -> 490.9217 | F102: =SUM(F92,F100) -> 533.96582 | G102: =SUM(G92,G100) -> 568.57454 | H102: =SUM(H92,H100) -> 606.00996 | I102: =SUM(I92,I100) -> 638.46663 | J102: =SUM(J92,J100) -> 670.16522 | K102: =SUM(K92,K100) -> 695.46978
C103: (-) Interest Expense | D103: $ M | E103: -98.641875 | F103: =-(F75*AVERAGE(F76,F135)+F78) -> -95.74575 | G103: =-(G75*AVERAGE(G76,G135)+G78) -> -88.491125 | H103: =-(H75*AVERAGE(H76,H135)+H78) -> -80.64425 | I103: =-(I75*AVERAGE(I76,I135)+I78) -> -72.205125 | J103: =-(J75*AVERAGE(J76,J135)+J78) -> -63.17375 | K103: =-(K75*AVERAGE(K76,K135)+K78) -> -53.550125
C104: (+) Interest Income | D104: $ M | E104: 2.275 | F104: =E116*F77 -> 7.3514821 | G104: =F116*G77 -> 12.675755 | H104: =G116*H77 -> 18.966993 | I104: =H116*I77 -> 25.697874 | J104: =I116*J77 -> 33.117288 | K104: =J116*K77 -> 41.28206 | M104: Cash interest on the average debt balance plus non-cash amortisation of capitalised issuance fees.
C105: (+) Other Income, Net | D105: $ M | E105: 0 | F105: =F53 -> 0 | G105: =G53 -> 0 | H105: =H53 -> 0 | I105: =I53 -> 0 | J105: =J53 -> 0 | K105: =K53 -> 0
C106: Pre-Tax Income | D106: $ M | E106: =SUM(E102:E105) -> 394.55482 | F106: =SUM(F102:F105) -> 445.57155 | G106: =SUM(G102:G105) -> 492.75917 | H106: =SUM(H102:H105) -> 544.3327 | I106: =SUM(I102:I105) -> 591.95937 | J106: =SUM(J102:J105) -> 640.10876 | K106: =SUM(K102:K105) -> 683.20171
C107: (-) Income Tax Provision | D107: $ M | E107: -94.693158 | F107: =-F106*$E$10 -> -106.93717 | G107: =-G106*$E$10 -> -118.2622 | H107: =-H106*$E$10 -> -130.63985 | I107: =-I106*$E$10 -> -142.07025 | J107: =-J106*$E$10 -> -153.6261 | K107: =-K106*$E$10 -> -163.96841
C108: Net Income | D108: $ M | E108: =SUM(E106:E107) -> 299.86167 | F108: =SUM(F106:F107) -> 338.63438 | G108: =SUM(G106:G107) -> 374.49697 | H108: =SUM(H106:H107) -> 413.69285 | I108: =SUM(I106:I107) -> 449.88912 | J108: =SUM(J106:J107) -> 486.48266 | K108: =SUM(K106:K107) -> 519.2333
C110: Average Diluted Shares | E110: =$E$15 -> 118.7058 | F110: =$E$15 -> 118.7058 | G110: =$E$15 -> 118.7058 | H110: =$E$15 -> 118.7058 | I110: =$E$15 -> 118.7058 | J110: =$E$15 -> 118.7058 | K110: =$E$15 -> 118.7058 | M110: Held constant. With no buy-backs of shares, the only share-count change in this analysis is the stock issued in the transaction.
C111: Earnings per Share (EPS) | E111: =E108/E110 -> 2.5260912 | F111: =F108/F110 -> 2.8527198 | G111: =G108/G110 -> 3.154833 | H111: =H108/H110 -> 3.4850266 | I111: =I108/I110 -> 3.7899508 | J111: =J108/J110 -> 4.0982216 | K111: =K108/K110 -> 4.3741191
B113: 4. BALANCE SHEET | G113: Projected:
E114: =Merger_Model!$E$89 -> 45657 | F114: =Merger_Model!$F$89 -> 46022 | G114: =Merger_Model!$G$89 -> 46387 | H114: =Merger_Model!$H$89 -> 46752 | I114: =Merger_Model!$I$89 -> 47118 | J114: =Merger_Model!$J$89 -> 47483 | K114: =Merger_Model!$K$89 -> 47848
C115: ASSETS
C116: Cash & Cash Equivalents | D116: $M | E116: 210.04235 | F116: =F184 -> 362.16442 | G116: =G184 -> 541.91409 | H116: =H184 -> 734.22496 | I116: =I184 -> 946.20822 | J116: =J184 -> 1179.4874 | K116: =K184 -> 1420.3402
C117: Accounts Receivable | D117: $M | E117: 791.68 | F117: =F90*F55 -> 825.0336 | G117: =G90*G55 -> 864.77914 | H117: =H90*H55 -> 903.80653 | I117: =I90*I55 -> 941.21227 | J117: =J90*J55 -> 976.33461 | K117: =K90*K55 -> 1008.5952
C118: Inventory & Other Current Assets | D118: $M | E118: 931.92488 | F118: =-F91*F56 -> 969.86567 | G118: =-G91*G56 -> 1003.9275 | H118: =-H91*H56 -> 1043.7906 | I118: =-I91*I56 -> 1077.4601 | J118: =-J91*J56 -> 1110.5806 | K118: =-K91*K56 -> 1147.277
C119: Total Current Assets | D119: $M | E119: =SUM(E116:E118) -> 1933.6472 | F119: =SUM(F116:F118) -> 2157.0637 | G119: =SUM(G116:G118) -> 2410.6207 | H119: =SUM(H116:H118) -> 2681.8221 | I119: =SUM(I116:I118) -> 2964.8806 | J119: =SUM(J116:J118) -> 3266.4026 | K119: =SUM(K116:K118) -> 3576.2124
C121: Net Property, Plant & Equipment | D121: $M | E121: 585 | F121: =E121-F152-F155-F169-F170 -> 590.02381 | G121: =F121-G152-G155-G169-G170 -> 597.50915 | H121: =G121-H152-H155-H169-H170 -> 604.80673 | I121: =H121-I152-I155-I169-I170 -> 608.15996 | J121: =I121-J152-J155-J169-J170 -> 611.78757 | K121: =J121-K152-K155-K169-K170 -> 611.72739
C122: Operating Lease Right-of-Use Assets | D122: $M | E122: 244.98782 | F122: =-F95*F57 -> 251.44894 | G122: =-G95*G57 -> 264.48342 | H122: =-H95*H57 -> 277.13103 | I122: =-I95*I57 -> 288.76676 | J122: =-J95*J57 -> 299.84068 | K122: =-K95*K57 -> 309.3788
C123: Goodwill | D123: $M | E123: 1120 | F123: =E123-F171 -> 1120 | G123: =F123-G171 -> 1120 | H123: =G123-H171 -> 1120 | I123: =H123-I171 -> 1120 | J123: =I123-J171 -> 1120 | K123: =J123-K171 -> 1120
C124: Other Intangible Assets | D124: $M | E124: 265 | F124: =E124-F153 -> 237.92858 | G124: =F124-G153 -> 210.22863 | H124: =G124-H153 -> 182.69077 | I124: =H124-I153 -> 155.48386 | J124: =I124-J153 -> 128.78721 | K124: =J124-K153 -> 102.78436
...

Sheet Target
B2: Target: Calder Fluid & Flow Systems, Inc. (CFFS) — Standalone Operating Model
B3: ($ in Millions Except Per Share and Per Unit Data)
B4: Calder designs and distributes flow-control equipment — valves and actuation, engineered pump packages, skid assemblies and instrumentation — with a growing aftermarket and field service arm. Higher gross margin and more engineered content than a pure-play distributor.
B5: 1. FINANCIAL PROFILE & CURRENT MARKET VALUATION | D5: Units
C7: Company Name: | D7: Name | E7: Calder Fluid & Flow Systems, Inc.
C8: Ticker: | D8: Name | E8: CFFS
C9: Last Fiscal Year: | D9: Date | E9: 45657
C10: Effective Tax Rate: | D10: % | E10: 0.245 | M10: Blended federal + state rate, held flat. Drives the tax provision in every projected year.
C11: Share Price (Undisturbed) | D11: $ as Stated | E11: 37.8 | M11: Unaffected price one day prior to announcement — the basis for the offer premium.
C13: Basic Shares Outstanding | D13: M sh | E13: 54.2 | P13: Treasury Stock Method:
C14: (+) Net Dilution from Options & RSUs | D14: M sh | E14: =T20 -> 1.3936508 | M14: Treasury stock method — schedule in columns P:S. Options are dilutive only when in the money.
C15: Diluted Shares Outstanding | D15: M sh | E15: =SUM(E13:E14) -> 55.593651 | P15: Name: | R15: Units (M) | S15: Strike | T15: Net Dilution
P16: Options | R16: 1.9 | S16: 24 | T16: =IF($E$11>S16,R16-R16*S16/$E$11, 0) -> 0.69365079
C17: Current Equity Value (Market Capitalisation) | D17: $M | E17: =E15*E11 -> 2101.44 | P17: RSUs / Restricted Stock | R17: 0.7 | S17: n/a | T17: =R17 -> 0.7
C18: (-) Cash & Cash Equivalents | D18: $M | E18: =-E116 -> -118.00792
C19: (+) Total Debt & Finance Leases | D19: $M | E19: =E135 -> 545
C20: (+) Operating Lease Liabilities | D20: $M | E20: 0 | M20: Deliberately excluded: Rent is part of SG&A, so, lease is excluded. Treated the same way on Pub_Comps and MA_Comps. | P20: Total Net Dilution | R20: =SUM(R16:R17) -> 2.6 | T20: =SUM(T16:T17) -> 1.3936508
C21: (+) Preferred Stock | D21: $M | E21: 0
C22: (+) Noncontrolling Interests | D22: $M | E22: 0
C23: (-) NOLs & Non-Core Assets | D23: $M | E23: 0 | M23: Neither company carries material NOLs or non-core assets; set to zero to keep the bridge clean.
C24: Current Enterprise Value (TEV) | D24: $M | E24: =SUM(E17:E23) -> 2528.4321
C26: TEV / FY24A EBITDA | D26: x | E26: =E24/E192 -> 8.945408
C27: TEV / FY25E EBITDA | D27: x | E27: =E24/F192 -> 7.9580209
C28: Price / FY24A EPS | D28: x | E28: =E11/E111 -> 14.447803
B32: 2. OPERATING DRIVERS & PROJECTION ASSUMPTIONS | G32: Projected: | M32: Every projected line item is driven from this block of drivers.
E33: =Merger_Model!$E$89 -> 45657 | F33: =Merger_Model!$F$89 -> 46022 | G33: =Merger_Model!$G$89 -> 46387 | H33: =Merger_Model!$H$89 -> 46752 | I33: =Merger_Model!$I$89 -> 47118 | J33: =Merger_Model!$J$89 -> 47483 | K33: =Merger_Model!$K$89 -> 47848
C35: Revenue Growth Rates by Segment:
C36: Valves & Actuation | D36: % | E36: n/a | F36: 0.045 | G36: 0.05 | H36: 0.048 | I36: 0.045 | J36: 0.04 | K36: 0.035
C37: Pumps & Fluid Handling | D37: % | E37: n/a | F37: 0.05 | G37: 0.055 | H37: 0.052 | I37: 0.048 | J37: 0.045 | K37: 0.04
C38: Engineered Assemblies | D38: % | E38: n/a | F38: 0.03 | G38: 0.04 | H38: 0.04 | I38: 0.038 | J38: 0.035 | K38: 0.03
C39: Instrumentation & Controls | D39: % | E39: n/a | F39: 0.055 | G39: 0.06 | H39: 0.055 | I39: 0.052 | J39: 0.048 | K39: 0.045
C40: Aftermarket & Field Services | D40: % | E40: n/a | F40: 0.065 | G40: 0.07 | H40: 0.065 | I40: 0.06 | J40: 0.055 | K40: 0.05
C42: Cost of Sales % of Revenue | D42: % | E42: =-E91/E90 -> 0.71 | F42: 0.708 | G42: 0.705 | H42: 0.703 | I42: 0.701 | J42: 0.7 | K42: 0.7 | M42: Gross-margin improves due to private-label penetration and also due to normalisation of freight and input costs
C44: Total Employees | D44: # | E44: 6300 | F44: 6280 | G44: 6420 | H44: 6540 | I44: 6650 | J44: 6740 | K44: 6820 | M44: Head-count is a core SG&A Driver. It is also the lever pulled in cost-synergy schedule
C45: Revenue per Employee | D45: $ | E45: =E90*1000000/E44 -> 410317.46 | F45: =F90*1000000/F44 -> 431289.81 | G45: =G90*1000000/G44 -> 444552.1 | H45: =H90*1000000/H44 -> 458725.82 | I45: =I90*1000000/I44 -> 472682.54 | J45: =J90*1000000/J44 -> 486767.39 | K45: =K90*1000000/K44 -> 499763.72
C46: SG&A Spending per Employee | D46: $ | E46: =-E95*1000000/E44 -> 72222 | F46: =E46*(1+F47) -> 74388.66 | G46: =F46*(1+G47) -> 76620.32 | H46: =G46*(1+H47) -> 78918.929 | I46: =H46*(1+I47) -> 81128.659 | J46: =I46*(1+J47) -> 83400.262 | K46: =J46*(1+K47) -> 85485.268 | M46: SG&A = Employees x cost per employee. This way we can directly link workforce reduction to dollars
C47: Growth Rate | D47: % | F47: 0.03 | G47: 0.03 | H47: 0.03 | I47: 0.028 | J47: 0.028 | K47: 0.025
C49: Depreciation % of Revenue | D49: % | E49: =-E96/E90 -> 0.0155 | F49: 0.0156 | G49: 0.0157 | H49: 0.0157 | I49: 0.0156 | J49: 0.0155 | K49: 0.0155
C50: Amortisation of Intangibles % of Revenue | D50: % | E50: =-E97/E90 -> 0.0062 | F50: 0.0061 | G50: 0.0059 | H50: 0.0057 | I50: 0.0055 | J50: 0.0053 | K50: 0.0051 | M50: Existing tangibles amortise over time, so this % goes down over the period
C51: Legacy Merger & Integration Costs | D51: $M | E51: 0 | F51: 6 | G51: 3 | H51: 0 | I51: 0 | J51: 0 | K51: 0 | M51: This is integration costs of arlier acquistions. Expect it to complete by FY27
C52: Impairment of Assets | D52: $M | E52: 0 | F52: 0 | G52: 0 | H52: 0 | I52: 0 | J52: 0 | K52: 0
C53: Other Income, Net | D53: $M | E53: 0 | F53: 3 | G53: 3 | H53: 3 | I53: 3 | J53: 3 | K53: 3
C55: Accounts Receivable % of Revenue | D55: % | E55: =E117/E90 -> 0.152 | F55: 0.152 | G55: 0.152 | H55: 0.152 | I55: 0.152 | J55: 0.152 | K55: 0.152
C56: Inventory & Other Current Assets % of COGS | D56: % | E56: =-E118/E91 -> 0.242 | F56: 0.24 | G56: 0.238 | H56: 0.236 | I56: 0.235 | J56: 0.234 | K56: 0.234
C57: Operating Lease ROU Assets % of SG&A | D57: % | E57: =-E122/E95 -> 0.18 | F57: 0.18 | G57: 0.18 | H57: 0.18 | I57: 0.18 | J57: 0.18 | K57: 0.18 | M57: ROU asset and lease liability are held equal, so the two cancel in working capital and the balance sheet stays clean.
C58: Accounts Payable % of COGS | D58: % | E58: =-E131/E91 -> 0.125 | F58: 0.125 | G58: 0.125 | H58: 0.125 | I58: 0.125 | J58: 0.125 | K58: 0.125
C59: Accrued Liabilities % of SG&A | D59: % | E59: =-E132/E95 -> 0.265 | F59: 0.265 | G59: 0.265 | H59: 0.265 | I59: 0.265 | J59: 0.265 | K59: 0.265
C61: Stock-Based Compensation % of Revenue | D61: % | E61: =E156/E90 -> 0.0032 | F61: 0.0032 | G61: 0.0032 | H61: 0.0032 | I61: 0.0032 | J61: 0.0032 | K61: 0.0032
C62: Deferred Income Taxes % of Book Taxes | D62: % | E62: =-E157/E107 -> 0.08 | F62: 0.08 | G62: 0.06 | H62: 0.05 | I62: 0.04 | J62: 0.04 | K62: 0.04
C63: Other Non-Cash Items | D63: $M | E63: =E158 -> -2.7 | F63: 0 | G63: 0 | H63: 0 | I63: 0 | J63: 0 | K63: 0
C65: Capital Expenditures % of Revenue | D65: % | E65: =-E169/E90 -> 0.021 | F65: 0.021 | G65: 0.0205 | H65: 0.02 | I65: 0.0195 | J65: 0.019 | K65: 0.019
C66: Proceeds from Sale of PP&E | D66: $M | E66: =E170 -> 2 | F66: 2 | G66: 2 | H66: 2 | I66: 2 | J66: 2 | K66: 2
C67: Acquisition Spending | D67: $M | E67: =-E171 -> 31.5 | F67: 0 | G67: 0 | H67: 0 | I67: 0 | J67: 0 | K67: 0 | M67: Projections assume no more spending on M&A
C69: Debt Issuances | D69: $M | E69: =E174 -> 180 | F69: 0 | G69: 0 | H69: 0 | I69: 0 | J69: 0 | K69: 0 | M69: No new debt is issued in the projections
C70: Debt Repayments | D70: $M | E70: 165 | F70: 40 | G70: 45 | H70: 50 | I70: 55 | J70: 60 | K70: 65 | M70: Contractual amortisation + volunteer repayment
C71: Share Repurchases | D71: $M | E71: =-E176 -> 25 | F71: 0 | G71: 0 | H71: 0 | I71: 0 | J71: 0 | K71: 0 | M71: Share repurchase is suspended. So, share dilution is just through deal consideration.
C72: Common Dividends | D72: $M | E72: =-E177 -> 0 | F72: 30 | G72: 34 | H72: 38 | I72: 42 | J72: 46 | K72: 50 | M72: Assumes that dividend repayment begins in FY25. Since, share buyback stopped, dividend absorbs most of the cashflow
C73: Debt Issuance Fees Paid | D73: $M | E73: =-E178 -> 3.4 | F73: 0 | G73: 0 | H73: 0 | I73: 0 | J73: 0 | K73: 0
C75: Weighted Average Interest Rate on Debt | D75: % | E75: 0.0625 | F75: 0.0625 | G75: 0.0625 | H75: 0.0625 | I75: 0.0625 | J75: 0.0625 | K75: 0.0625 | M75: Assumes coupon rate rather than blended interest
C76: Beginning Total Debt Balance | D76: $M | E76: 531.6 | F76: =E135 -> 545 | G76: =F135 -> 506.7 | H76: =G135 -> 463.3 | I76: =H135 -> 414.8 | J76: =I135 -> 361.2 | K76: =J135 -> 302.5
C77: Interest Income % of Beginning Cash | D77: % | E77: 0.035 | F77: 0.035 | G77: 0.035 | H77: 0.035 | I77: 0.035 | J77: 0.035 | K77: 0.035
C78: Amortisation of Debt Issuance Fees | D78: $M | E78: =E154 -> 1.8 | F78: 1.7 | G78: 1.6 | H78: 1.5 | I78: 1.4 | J78: 1.3 | K78: 1.2
B81: 3. INCOME STATEMENT | G81: Projected:
E82: =Merger_Model!$E$89 -> 45657 | F82: =Merger_Model!$F$89 -> 46022 | G82: =Merger_Model!$G$89 -> 46387 | H82: =Merger_Model!$H$89 -> 46752 | I82: =Merger_Model!$I$89 -> 47118 | J82: =Merger_Model!$J$89 -> 47483 | K82: =Merger_Model!$K$89 -> 47848
C84: Revenue:
C85: (+) Valves & Actuation | D85: $ M | E85: 845 | F85: =E85*(1+F36) -> 883.025 | G85: =F85*(1+G36) -> 927.17625 | H85: =G85*(1+H36) -> 971.68071 | I85: =H85*(1+I36) -> 1015.4063 | J85: =I85*(1+J36) -> 1056.0226 | K85: =J85*(1+K36) -> 1092.9834
C86: (+) Pumps & Fluid Handling | D86: $ M | E86: 710 | F86: =E86*(1+F37) -> 745.5 | G86: =F86*(1+G37) -> 786.5025 | H86: =G86*(1+H37) -> 827.40063 | I86: =H86*(1+I37) -> 867.11586 | J86: =I86*(1+J37) -> 906.13607 | K86: =J86*(1+K37) -> 942.38152
C87: (+) Engineered Assemblies | D87: $ M | E87: 445 | F87: =E87*(1+F38) -> 458.35 | G87: =F87*(1+G38) -> 476.684 | H87: =G87*(1+H38) -> 495.75136 | I87: =H87*(1+I38) -> 514.58991 | J87: =I87*(1+J38) -> 532.60056 | K87: =J87*(1+K38) -> 548.57858
C88: (+) Instrumentation & Controls | D88: $ M | E88: 140 | F88: =E88*(1+F39) -> 147.7 | G88: =F88*(1+G39) -> 156.562 | H88: =G88*(1+H39) -> 165.17291 | I88: =H88*(1+I39) -> 173.7619 | J88: =I88*(1+J39) -> 182.10247 | K88: =J88*(1+K39) -> 190.29708
C89: (+) Aftermarket & Field Services | D89: $ M | E89: 445 | F89: =E89*(1+F40) -> 473.925 | G89: =F89*(1+G40) -> 507.09975 | H89: =G89*(1+H40) -> 540.06123 | I89: =H89*(1+I40) -> 572.46491 | J89: =I89*(1+J40) -> 603.95048 | K89: =J89*(1+K40) -> 634.148
C90: Total Revenue | D90: $ M | E90: =SUM(E85:E89) -> 2585 | F90: =SUM(F85:F89) -> 2708.5 | G90: =SUM(G85:G89) -> 2854.0245 | H90: =SUM(H85:H89) -> 3000.0668 | I90: =SUM(I85:I89) -> 3143.3389 | J90: =SUM(J85:J89) -> 3280.8122 | K90: =SUM(K85:K89) -> 3408.3886
C91: (-) Cost of Sales | D91: $ M | E91: -1835.35 | F91: =-F90*F42 -> -1917.618 | G91: =-G90*G42 -> -2012.0873 | H91: =-H90*H42 -> -2109.047 | I91: =-I90*I42 -> -2203.4806 | J91: =-J90*J42 -> -2296.5685 | K91: =-K90*K42 -> -2385.872
C92: Gross Profit | D92: $ M | E92: =SUM(E90:E91) -> 749.65 | F92: =SUM(F90:F91) -> 790.882 | G92: =SUM(G90:G91) -> 841.93723 | H92: =SUM(H90:H91) -> 891.01985 | I92: =SUM(I90:I91) -> 939.85834 | J92: =SUM(J90:J91) -> 984.24365 | K92: =SUM(K90:K91) -> 1022.5166
C94: Operating Expenses:
C95: (-) Selling, General & Administrative | D95: $ M | E95: -454.9986 | F95: =-F44/1000000*F46 -> -467.16078 | G95: =-G44/1000000*G46 -> -491.90245 | H95: =-H44/1000000*H46 -> -516.1298 | I95: =-I44/1000000*I46 -> -539.50559 | J95: =-J44/1000000*J46 -> -562.11777 | K95: =-K44/1000000*K46 -> -583.00953
C96: (-) Depreciation | D96: $ M | E96: -40.0675 | F96: =-F90*F49 -> -42.2526 | G96: =-G90*G49 -> -44.808185 | H96: =-H90*H49 -> -47.101049 | I96: =-I90*I49 -> -49.036087 | J96: =-J90*J49 -> -50.852589 | K96: =-K90*K49 -> -52.830023
C97: (-) Amortisation of Intangibles | D97: $ M | E97: -16.027 | F97: =-F90*F50 -> -16.52185 | G97: =-G90*G50 -> -16.838745 | H97: =-H90*H50 -> -17.100381 | I97: =-I90*I50 -> -17.288364 | J97: =-J90*J50 -> -17.388305 | K97: =-K90*K50 -> -17.382782
C98: (-) Legacy Merger & Integration Costs | D98: $ M | E98: -12 | F98: =-F51 -> -6 | G98: =-G51 -> -3 | H98: =-H51 -> 0 | I98: =-I51 -> 0 | J98: =-J51 -> 0 | K98: =-K51 -> 0
C99: (-) Impairment of Assets | D99: $ M | E99: -2.5 | F99: =-F52 -> 0 | G99: =-G52 -> 0 | H99: =-H52 -> 0 | I99: =-I52 -> 0 | J99: =-J52 -> 0 | K99: =-K52 -> 0
C100: Total Operating Expenses | D100: $ M | E100: =SUM(E95:E99) -> -525.5931 | F100: =SUM(F95:F99) -> -531.93523 | G100: =SUM(G95:G99) -> -556.54938 | H100: =SUM(H95:H99) -> -580.33123 | I100: =SUM(I95:I99) -> -605.83004 | J100: =SUM(J95:J99) -> -630.35866 | K100: =SUM(K95:K99) -> -653.22234
C102: Operating Income (EBIT) | D102: $ M | E102: =SUM(E92,E100) -> 224.0569 | F102: =SUM(F92,F100) -> 258.94677 | G102: =SUM(G92,G100) -> 285.38785 | H102: =SUM(H92,H100) -> 310.68862 | I102: =SUM(I92,I100) -> 334.0283 | J102: =SUM(J92,J100) -> 353.885 | K102: =SUM(K92,K100) -> 369.29423
C103: (-) Interest Expense | D103: $ M | E103: -35.44375 | F103: =-(F75*AVERAGE(F76,F135)+F78) -> -34.565625 | G103: =-(G75*AVERAGE(G76,G135)+G78) -> -31.9125 | H103: =-(H75*AVERAGE(H76,H135)+H78) -> -28.940625 | I103: =-(I75*AVERAGE(I76,I135)+I78) -> -25.65 | J103: =-(J75*AVERAGE(J76,J135)+J78) -> -22.040625 | K103: =-(K75*AVERAGE(K76,K135)+K78) -> -18.1125
C104: (+) Interest Income | D104: $ M | E104: 0.8365 | F104: =F77*F183 -> 4.1302772 | G104: =G77*G183 -> 7.7091235 | H104: =H77*H183 -> 11.832548 | I104: =I77*I183 -> 16.534279 | J104: =J77*J183 -> 21.728774 | K104: =K77*K183 -> 27.453528 | M104: Cash interest on the average debt balance plus non-cash amortisation of capitalised issuance fees.
C105: (+) Other Income, Net | D105: $ M | E105: 3.2 | F105: =F53 -> 3 | G105: =G53 -> 3 | H105: =H53 -> 3 | I105: =I53 -> 3 | J105: =J53 -> 3 | K105: =K53 -> 3
C106: Pre-Tax Income | D106: $ M | E106: =SUM(E102:E105) -> 192.64965 | F106: =SUM(F102:F105) -> 231.51142 | G106: =SUM(G102:G105) -> 264.18447 | H106: =SUM(H102:H105) -> 296.58055 | I106: =SUM(I102:I105) -> 327.91258 | J106: =SUM(J102:J105) -> 356.57314 | K106: =SUM(K102:K105) -> 381.63526
C107: (-) Income Tax Provision | D107: $ M | E107: -47.199164 | F107: =-F106*$E$10 -> -56.720297 | G107: =-G106*$E$10 -> -64.725195 | H107: =-H106*$E$10 -> -72.662234 | I107: =-I106*$E$10 -> -80.338582 | J107: =-J106*$E$10 -> -87.36042 | K107: =-K106*$E$10 -> -93.500639
C108: Net Income | D108: $ M | E108: =SUM(E106:E107) -> 145.45049 | F108: =SUM(F106:F107) -> 174.79112 | G108: =SUM(G106:G107) -> 199.45927 | H108: =SUM(H106:H107) -> 223.91831 | I108: =SUM(I106:I107) -> 247.574 | J108: =SUM(J106:J107) -> 269.21272 | K108: =SUM(K106:K107) -> 288.13462
C110: Average Diluted Shares | E110: =$E$15 -> 55.593651 | F110: =$E$15 -> 55.593651 | G110: =$E$15 -> 55.593651 | H110: =$E$15 -> 55.593651 | I110: =$E$15 -> 55.593651 | J110: =$E$15 -> 55.593651 | K110: =$E$15 -> 55.593651 | M110: Held constant. With no buy-backs of shares, the only share-count change in this analysis is the stock issued in the transaction.
C111: Earnings per Share (EPS) | E111: =E108/E110 -> 2.6163147 | F111: =F108/F110 -> 3.1440842 | G111: =G108/G110 -> 3.5878067 | H111: =H108/H110 -> 4.0277677 | I111: =I108/I110 -> 4.4532783 | J111: =J108/J110 -> 4.8425085 | K111: =K108/K110 -> 5.1828692
B113: 4. BALANCE SHEET | G113: Projected:
E114: =Merger_Model!$E$89 -> 45657 | F114: =Merger_Model!$F$89 -> 46022 | G114: =Merger_Model!$G$89 -> 46387 | H114: =Merger_Model!$H$89 -> 46752 | I114: =Merger_Model!$I$89 -> 47118 | J114: =Merger_Model!$J$89 -> 47483 | K114: =Merger_Model!$K$89 -> 47848
C115: ASSETS
C116: Cash & Cash Equivalents | D116: $M | E116: 118.00792 | F116: =F184 -> 220.26067 | G116: =G184 -> 338.07279 | H116: =H184 -> 472.40798 | I116: =I184 -> 620.82212 | J116: =J184 -> 784.38651 | K116: =K184 -> 957.23206
C117: Accounts Receivable | D117: $M | E117: 392.92 | F117: =F90*F55 -> 411.692 | G117: =G90*G55 -> 433.81172 | H117: =H90*H55 -> 456.01016 | I117: =I90*I55 -> 477.78752 | J117: =J90*J55 -> 498.68345 | K117: =K90*K55 -> 518.07506
C118: Inventory & Other Current Assets | D118: $M | E118: 444.1547 | F118: =-F91*F56 -> 460.22832 | G118: =-G91*G56 -> 478.87677 | H118: =-H91*H56 -> 497.73509 | I118: =-I91*I56 -> 517.81794 | J118: =-J91*J56 -> 537.39703 | K118: =-K91*K56 -> 558.29405
C119: Total Current Assets | D119: $M | E119: =SUM(E116:E118) -> 955.08262 | F119: =SUM(F116:F118) -> 1092.181 | G119: =SUM(G116:G118) -> 1250.7613 | H119: =SUM(H116:H118) -> 1426.1532 | I119: =SUM(I116:I118) -> 1616.4276 | J119: =SUM(J116:J118) -> 1820.467 | K119: =SUM(K116:K118) -> 2033.6012
C121: Net Property, Plant & Equipment | D121: $M | E121: 268 | F121: =E121-F152-F155-F169-F170 -> 280.6259 | G121: =F121-G152-G155-G169-G170 -> 292.32522 | H121: =G121-H152-H155-H169-H170 -> 303.22551 | I121: =H121-I152-I155-I169-I170 -> 313.48453 | J121: =I121-J152-J155-J169-J170 -> 322.96737 | K121: =J121-K152-K155-K169-K170 -> 332.89673
C122: Operating Lease Right-of-Use Assets | D122: $M | E122: 81.899748 | F122: =-F95*F57 -> 84.088941 | G122: =-G95*G57 -> 88.542442 | H122: =-H95*H57 -> 92.903364 | I122: =-I95*I57 -> 97.111005 | J122: =-J95*J57 -> 101.1812 | K122: =-K95*K57 -> 104.94172
C123: Goodwill | D123: $M | E123: 470 | F123: =E123-F171 -> 470 | G123: =F123-G171 -> 470 | H123: =G123-H171 -> 470 | I123: =H123-I171 -> 470 | J123: =I123-J171 -> 470 | K123: =J123-K171 -> 470
C124: Other Intangible Assets | D124: $M | E124: 205 | F124: =E124-F153 -> 188.47815 | G124: =F124-G153 -> 171.63941 | H124: =G124-H153 -> 154.53902 | I124: =H124-I153 -> 137.25066 | J124: =I124-J153 -> 119.86236 | K124: =J124-K153 -> 102.47957
...

Sheet Synergies
B2: Synergy Estimates - Meridian Industrial Supply, Inc. / Calder Fluid & Flow Systems, Inc.
B3: ($ in millions, except per-share and per-unit data)
B4: Cost synergies are built bottom-up from headcount; revenue synergies from cross-selling Calder's flow-control lines through Meridian's branch network. Both are switched on/off from the Merger_Model tab.
B5: 1. EXPENSE (COST) SYNERGIES — BUILT FROM HEADCOUNT | M5: The single most scrutinised number in the deal. Building it off a named reduction in force makes it defensible rather than a plug.
D6: ($ in millions) | G6: =Merger_Model!$G$89 -> 46387 | H6: =Merger_Model!$H$89 -> 46752 | I6: =Merger_Model!$I$89 -> 47118 | J6: =Merger_Model!$J$89 -> 47483 | K6: =Merger_Model!$K$89 -> 47848
C8: Target - Reduction in Force | D8: # people | G8: 340 | H8: 440 | I8: 500 | J8: 500 | K8: 500 | M8: Duplicate corporate, finance, IT and branch-administration roles at Calder. Ramps over three years, then holds flat.
C9: Target - SG&A Cost per Employee | D9: $ | G9: =Target!G46 -> 76620.32 | H9: =Target!H46 -> 78918.929 | I9: =Target!I46 -> 81128.659 | J9: =Target!J46 -> 83400.262 | K9: =Target!K46 -> 85485.268
C10: Target - Cost Savings | D10: $M | G10: =G8*G9/1000000 -> 26.050909 | H10: =H8*H9/1000000 -> 34.724329 | I10: =I8*I9/1000000 -> 40.56433 | J10: =J8*J9/1000000 -> 41.700131 | K10: =K8*K9/1000000 -> 42.742634
C12: Acquirer - Reduction in Force | D12: # people | G12: 400 | H12: 580 | I12: 660 | J12: 660 | K12: 660 | M12: Overlapping branch and distribution-centre roles at Meridian in markets where the two networks overlap.
C13: Acquirer - SG&A Cost per Employee | D13: $ | G13: =Acquirer!G46 -> 78521.453 | H13: =Acquirer!H46 -> 80877.096 | I13: =Acquirer!I46 -> 83141.655 | J13: =Acquirer!J46 -> 85469.621 | K13: =Acquirer!K46 -> 87606.362
C14: Acquirer - Cost Savings | D14: $M | G14: =G12*G13/1000000 -> 31.408581 | H14: =H12*H13/1000000 -> 46.908716 | I14: =I12*I13/1000000 -> 54.873492 | J14: =J12*J13/1000000 -> 56.40995 | K14: =K12*K13/1000000 -> 57.820199
C16: Gross Run-Rate Expense Synergies | D16: $M | G16: =G10+G14 -> 57.45949 | H16: =H10+H14 -> 81.633045 | I16: =I10+I14 -> 95.437822 | J16: =J10+J14 -> 98.110081 | K16: =K10+K14 -> 100.56283
C17: (x) Realisation Factor | D17: % | G17: =Merger_Model!$E$12 -> 1 | H17: =Merger_Model!$E$12 -> 1 | I17: =Merger_Model!$E$12 -> 1 | J17: =Merger_Model!$E$12 -> 1 | K17: =Merger_Model!$E$12 -> 1 | M17: Master haircut on cost synergies, set on Merger_Model. 100% = management's plan delivered in full; this is the key variable in the EPS and IRR sensitivities.
C18: Realised Expense Synergies | D18: $M | G18: =G16*G17*Merger_Model!$E$11 -> 57.45949 | H18: =H16*H17*Merger_Model!$E$11 -> 81.633045 | I18: =I16*I17*Merger_Model!$E$11 -> 95.437822 | J18: =J16*J17*Merger_Model!$E$11 -> 98.110081 | K18: =K16*K17*Merger_Model!$E$11 -> 100.56283 | M18: Multiplied by the Include Expense Synergies switch (1/0) on Merger_Model.
B20: 2. REVENUE SYNERGIES — CROSS-SELL INTO THE ACQUIRER'S NETWORK | M20: Deliberately modest versus the sell-side case: only two of Calder's five segments are assumed to benefit, and only through Meridian's existing branches.
D21: ($ in millions) | G21: =Merger_Model!$G$89 -> 46387 | H21: =Merger_Model!$H$89 -> 46752 | I21: =Merger_Model!$I$89 -> 47118 | J21: =Merger_Model!$J$89 -> 47483 | K21: =Merger_Model!$K$89 -> 47848
C22: Uplift to Target Segment Revenue:
C23: Valves & Actuation | D23: % | G23: 0.04 | H23: 0.08 | I23: 0.12 | J23: 0.14 | K23: 0.14 | M23: Valves and pumps are the two lines Meridian's 230 branches can carry immediately; engineered assemblies and instrumentation need specification selling and are excluded.
C24: Pumps & Fluid Handling | D24: % | G24: 0.05 | H24: 0.1 | I24: 0.15 | J24: 0.18 | K24: 0.18
C26: (+) Incremental Revenue | D26: $M | G26: =G23*Target!G85*Merger_Model!$E$10+Synergies!G24*Target!G86*Merger_Model!$E$10 -> 76.412175 | H26: =H23*Target!H85*Merger_Model!$E$10+Synergies!H24*Target!H86*Merger_Model!$E$10 -> 160.47452 | I26: =I23*Target!I85*Merger_Model!$E$10+Synergies!I24*Target!I86*Merger_Model!$E$10 -> 251.91614 | J26: =J23*Target!J85*Merger_Model!$E$10+Synergies!J24*Target!J86*Merger_Model!$E$10 -> 310.94766 | K26: =K23*Target!K85*Merger_Model!$E$10+Synergies!K24*Target!K86*Merger_Model!$E$10 -> 322.64635
C27: (-) Incremental Cost of Sales | D27: $M | G27: =-G26*Target!G42 -> -53.870583 | H27: =-H26*Target!H42 -> -112.81359 | I27: =-I26*Target!I42 -> -176.59321 | J27: =-J26*Target!J42 -> -217.66336 | K27: =-K26*Target!K42 -> -225.85244 | M27: Costed at Calder's existing gross margin — no assumption that incremental volume is more profitable than the base business.
C28: (-) Incremental Operating Expenses | D28: $M | G28: =G26*Target!G95/Target!G90 -> -13.169942 | H28: =H26*Target!H95/Target!H90 -> -27.607945 | I28: =I26*Target!I95/Target!I90 -> -43.237515 | J28: =J26*Target!J95/Target!J90 -> -53.276199 | K28: =K26*Target!K95/Target!K90 -> -55.189099 | M28: Charged at Calder's existing SG&A margin, so the revenue synergy carries a full cost load rather than dropping straight to EBIT.
C29: Incremental Operating Income | D29: $M | G29: =SUM(G26:G28) -> 9.3716499 | H29: =SUM(H26:H28) -> 20.052987 | I29: =SUM(I26:I28) -> 32.085411 | J29: =SUM(J26:J28) -> 40.008098 | K29: =SUM(K26:K28) -> 41.604805
B31: 3. MERGER & INTEGRATION COSTS TO ACHIEVE | M31: Synergies are never free. Following the case convention, total costs to achieve equal 100% of the Year 3 run-rate cost synergy.
D32: ($ in millions) | G32: =Merger_Model!$G$89 -> 46387 | H32: =Merger_Model!$H$89 -> 46752 | I32: =Merger_Model!$I$89 -> 47118 | J32: =Merger_Model!$J$89 -> 47483 | K32: =Merger_Model!$K$89 -> 47848
C33: Integration Costs % of Year 3 Expense Synergies | D33: % | E33: 1
C34: Total Merger & Integration Costs | D34: $M | E34: =$E$33*I16*Merger_Model!$E$12 -> 95.437822 | M34: Sized off the GROSS Year 3 (FY28E) run-rate saving and scaled by the realisation factor — if you only capture half the savings you only spend half the cost to get them.
C35: Annual Recognition | D35: % | G35: 0.66666667 | H35: 0.33333333 | I35: 0 | J35: 0 | K35: 0 | M35: Severance, branch closure and systems-migration spend is front-loaded: two-thirds in Year 1, one-third in Year 2.
C36: Merger & Integration Costs | D36: $M | G36: =$E$34*G35 -> 63.625215 | H36: =$E$34*H35 -> 31.812607 | I36: =$E$34*I35 -> 0 | J36: =$E$34*J35 -> 0 | K36: =$E$34*K35 -> 0
B38: 4. NET PRE-TAX SYNERGY EFFECT
C40: Total Pre-Tax Synergies, Net of Costs to Achieve | D40: $M | G40: =G18+G29-G36 -> 3.2059251 | H40: =H18+H29-H36 -> 69.873424 | I40: =I18+I29-I36 -> 127.52323 | J40: =J18+J29-J36 -> 138.11818 | K40: =K18+K29-K36 -> 142.16764
C41: (-) Tax Effect | D41: $M | G41: =-G40*Acquirer!$E$10 -> -0.76942201 | H41: =-H40*Acquirer!$E$10 -> -16.769622 | I41: =-I40*Acquirer!$E$10 -> -30.605576 | J41: =-J40*Acquirer!$E$10 -> -33.148363 | K41: =-K40*Acquirer!$E$10 -> -34.120233
C42: After-Tax Synergies, Net of Costs to Achieve | D42: $M | G42: =G40+G41 -> 2.436503 | H42: =H40+H41 -> 53.103803 | I42: =I40+I41 -> 96.917657 | J42: =J40+J41 -> 104.96982 | K42: =K40+K41 -> 108.0474
B44: 5. VALUE OF SYNERGIES TO THE ACQUIRER vs. PREMIUM PAID | M44: The acid test: is the acquirer handing more value to the target's shareholders than the synergies are worth?
C46: Discount Rate (Acquirer's WACC) | D46: % | E46: =WACC!$F$44 -> 0.10390378
C47: Long-Term Growth Rate of Synergies | E47: 0.015 | G47: =Merger_Model!$G$89 -> 46387 | H47: =Merger_Model!$H$89 -> 46752 | I47: =Merger_Model!$I$89 -> 47118 | J47: =Merger_Model!$J$89 -> 47483 | K47: =Merger_Model!$K$89 -> 47848 | M47: Below long-run inflation — cost savings erode as wages reset and competitors respond.
C48: After-Tax Synergy Cash Flow | D48: $M | G48: =G42 -> 2.436503 | H48: =H42 -> 53.103803 | I48: =I42 -> 96.917657 | J48: =J42 -> 104.96982 | K48: =K42 -> 108.0474
C49: (+) Terminal Value of Synergies | D49: $M | K49: =K48*(1+$E$47)/($E$46-$E$47) -> 1233.5597 | M49: Perpetuity growth on the Year 5 after-tax run-rate. By then the costs to achieve are behind us, so this capitalises a clean recurring saving.
C50: Discount Period | D50: # yrs | G50: 1 | H50: 2 | I50: 3 | J50: 4 | K50: 5
C51: Present Value | D51: $M | G51: =(G48+G49)/(1+$E$46)^G50 -> 2.2071698 | H51: =(H48+H49)/(1+$E$46)^H50 -> 43.577587 | I51: =(I48+I49)/(1+$E$46)^I50 -> 72.045896 | J51: =(J48+J49)/(1+$E$46)^J50 -> 70.687001 | K51: =(K48+K49)/(1+$E$46)^K50 -> 818.40684
C52: Present Value of Synergies | D52: $M | E52: =SUM(G51:K51) -> 1006.9245
C54: Equity Purchase Premium Paid | D54: $M | E54: =Merger_Model!$E$20-Target!$E$17 -> 596.4
C55: PV of Synergies / Premium Paid | D55: x | E55: =E52/E54 -> 1.6883375 | M55: Above 1.0x the synergies more than pay for the premium — but note how much of that value sits in the terminal value, and how quickly it falls away in the realisation sensitivity.

Sheet Combined_BS
B2: Balance Sheet Combination at Close — MIDS / CFFS
B3: ($ in millions, except per-share and per-unit data)
B4: Opening pro-forma balance sheet as at the 12/31/2025 close date. This is a point-in-time purchase-accounting exercise; the combined balance sheet is not projected forward.
B5: PRO-FORMA BALANCE SHEET AT CLOSE (FY25E) | M5: Column H isolates every acquisition adjustment so a reviewer can trace each one back to the Sources & Uses and the PPA.
D6: ($ in millions) | E6: Acquirer FY25E | F6: Target FY25E | G6: Combined | H6: Adjustments | I6: Pro-Forma
C7: ASSETS
C8: Cash & Cash Equivalents | D8: $M | E8: =Acquirer!F116 -> 362.16442 | F8: =Target!F116 -> 220.26067 | G8: =E8+F8 -> 582.42509 | H8: =-Merger_Model!E49-Merger_Model!E46-Merger_Model!E44*Merger_Model!E20-Merger_Model!E45*(Merger_Model!E50+Merger_Model!E21) -> -49.1124 | I8: =G8+H8 -> 533.31269 | M8: Cash consideration plus advisory, legal and debt financing fees all settle out of the combined cash balance at close.
C9: Accounts Receivable | D9: $M | E9: =Acquirer!F117 -> 825.0336 | F9: =Target!F117 -> 411.692 | G9: =E9+F9 -> 1236.7256 | H9: 0 | I9: =G9+H9 -> 1236.7256
C10: Inventory & Other Current Assets | D10: $M | E10: =Acquirer!F118 -> 969.86567 | F10: =Target!F118 -> 460.22832 | G10: =E10+F10 -> 1430.094 | H10: 0 | I10: =G10+H10 -> 1430.094
C11: Total Current Assets | D11: $M | E11: =SUM(E8:E10) -> 2157.0637 | F11: =SUM(F8:F10) -> 1092.181 | G11: =SUM(G8:G10) -> 3249.2447 | H11: =SUM(H8:H10) -> -49.1124 | I11: =SUM(I8:I10) -> 3200.1323
C13: Net Property, Plant & Equipment | D13: $M | E13: =Acquirer!F121 -> 590.02381 | F13: =Target!F121 -> 280.6259 | G13: =E13+F13 -> 870.64971 | H13: =Merger_Model!K75 -> 42.093885 | I13: =G13+H13 -> 912.74359 | M13: Written up to fair value per the PPA.
C14: Operating Lease Right-of-Use Assets | D14: $M | E14: =Acquirer!F122 -> 251.44894 | F14: =Target!F122 -> 84.088941 | G14: =E14+F14 -> 335.53788 | H14: 0 | I14: =G14+H14 -> 335.53788
C15: Goodwill | D15: $M | E15: =Acquirer!F123 -> 1120 | F15: =Target!F123 -> 470 | G15: =E15+F15 -> 1590 | H15: =-Target!F123+Merger_Model!E83 -> 1233.7025 | I15: =G15+H15 -> 2823.7025 | M15: Target's historical goodwill is written off in full and replaced with the goodwill created in this transaction.
C16: Other Intangible Assets | D16: $M | E16: =Acquirer!F124 -> 237.92858 | F16: =Target!F124 -> 188.47815 | G16: =E16+F16 -> 426.40674 | H16: =Merger_Model!K84 -> 377.6976 | I16: =G16+H16 -> 804.10433 | M16: Trade names and customer relationships recognised for the first time on acquisition.
C17: Other Long-Term Assets | D17: $M | E17: =Acquirer!F125 -> 48 | F17: =Target!F125 -> 26 | G17: =E17+F17 -> 74 | H17: 0 | I17: =G17+H17 -> 74
C18: Total Long-Term Assets | D18: $M | E18: =SUM(E13:E17) -> 2247.4013 | F18: =SUM(F13:F17) -> 1049.193 | G18: =SUM(G13:G17) -> 3296.5943 | H18: =SUM(H13:H17) -> 1653.494 | I18: =SUM(I13:I17) -> 4950.0883
C20: TOTAL ASSETS | D20: $M | E20: =E11+E18 -> 4404.465 | F20: =F11+F18 -> 2141.374 | G20: =G11+G18 -> 6545.839 | H20: =H11+H18 -> 1604.3816 | I20: =I11+I18 -> 8150.2206
C22: LIABILITIES & SHAREHOLDERS' EQUITY
C23: Accounts Payable | D23: $M | E23: =Acquirer!F131 -> 643.42308 | F23: =Target!F131 -> 239.70225 | G23: =E23+F23 -> 883.12533 | H23: 0 | I23: =G23+H23 -> 883.12533
C24: Accrued Liabilities | D24: $M | E24: =Acquirer!F132 -> 291.2536 | F24: =Target!F132 -> 123.79761 | G24: =E24+F24 -> 415.05121 | H24: 0 | I24: =G24+H24 -> 415.05121
C25: Total Current Liabilities | D25: $M | E25: =SUM(E23:E24) -> 934.67668 | F25: =SUM(F23:F24) -> 363.49986 | G25: =SUM(G23:G24) -> 1298.1765 | H25: =SUM(H23:H24) -> 0 | I25: =SUM(I23:I24) -> 1298.1765
C27: Existing Debt | D27: $M | E27: =Acquirer!F135 -> 1534.2 | F27: =Target!F135 -> 506.7 | G27: =E27+F27 -> 2040.9 | H27: =-Merger_Model!E21*Merger_Model!E45 -> -10.134 | I27: =G27+H27 -> 2030.766 | M27: Calder's debt is refinanced on identical terms so the principal is unchanged; only the capitalised financing fee moves the carrying value.
C28: New Transaction Debt | D28: $M | E28: 0 | F28: 0 | G28: =E28+F28 -> 0 | H28: =Merger_Model!$E$50-Merger_Model!E50*Merger_Model!$E$45 -> 0 | I28: =G28+H28 -> 0 | M28: Recognised net of capitalised issuance fees, which are then amortised to interest expense over the five-year term.
C29: Operating Lease Liabilities | D29: $M | E29: =Acquirer!F136 -> 251.44894 | F29: =Target!F136 -> 84.088941 | G29: =E29+F29 -> 335.53788 | H29: 0 | I29: =G29+H29 -> 335.53788
C30: Net Deferred Tax Liability | D30: $M | E30: =Acquirer!F137 -> 74.832461 | F30: =Target!F137 -> 12.537624 | G30: =E30+F30 -> 87.370085 | H30: =-Target!F137+Merger_Model!K86 -> 88.212333 | I30: =G30+H30 -> 175.58242 | M30: Historical DTL is eliminated and a new one booked on the non-deductible asset write-ups.
C31: Other Long-Term Liabilities | D31: $M | E31: =Acquirer!F138 -> 88.024945 | F31: =Target!F138 -> 41.98924 | G31: =E31+F31 -> 130.01418 | H31: 0 | I31: =G31+H31 -> 130.01418
C32: Total Long-Term Liabilities | D32: $M | E32: =SUM(E27:E31) -> 1948.5063 | F32: =SUM(F27:F31) -> 645.3158 | G32: =SUM(G27:G31) -> 2593.8222 | H32: =SUM(H27:H31) -> 78.078333 | I32: =SUM(I27:I31) -> 2671.9005
C34: Total Liabilities | D34: $M | E34: =E25+E32 -> 2883.183 | F34: =F25+F32 -> 1008.8157 | G34: =G25+G32 -> 3891.9987 | H34: =H25+H32 -> 78.078333 | I34: =I25+I32 -> 3970.077
C36: Common Shareholders' Equity | D36: $M | E36: =Acquirer!F143 -> 1521.282 | F36: =Target!F143 -> 1132.5583 | G36: =E36+F36 -> 2653.8403 | H36: =-Target!F143+Merger_Model!E51-Merger_Model!E46-Merger_Model!E44*Merger_Model!E20 -> 1526.3033 | I36: =G36+H36 -> 4180.1436 | M36: Target's book equity is eliminated, the stock consideration is added to the acquirer's equity, and advisory and legal fees are expensed straight against equity.
C38: TOTAL LIABILITIES & EQUITY | D38: $M | E38: =E34+E36 -> 4404.465 | F38: =F34+F36 -> 2141.374 | G38: =G34+G36 -> 6545.839 | H38: =H34+H36 -> 1604.3816 | I38: =I34+I36 -> 8150.2206
C40: Balance Sheet Check (must equal zero) | D40: $M | E40: =ROUND(E20-E38,6) -> 0 | F40: =ROUND(F20-F38,6) -> 0 | G40: =ROUND(G20-G38,6) -> 0 | H40: =ROUND(H20-H38,6) -> 0 | I40: =ROUND(I20-I38,6) -> 0

Sheet DCF_IRR
B2: Calder Fluid & Flow Systems, Inc. - Discounted Cash Flow Valuation & Acquisition IRR
B3: ($ in millions, except per-share and per-unit data)
B4: Ten-year unlevered DCF on Calder standalone, plus the IRR the acquirer earns on the purchase price once synergies are included. Notes are in column R.
B5: 1. DCF ASSUMPTIONS & OUTPUT
C7: Discount Rate (Target WACC) | E7: =WACC!E44 -> 0.10573578 | R7: Pulled from the WACC tab — Calder's own capital structure, not the acquirer's.
C8: Mid-Year Convention (1 = Yes, 0 = No) | E8: 1 | R8: Cash flows are assumed to arrive evenly through the year rather than all on 31 December.
C9: Terminal FCF Growth Rate | E9: 0.0225 | R9: Below long-run nominal GDP. Higher than it would have been a decade ago because the whole rate and inflation structure is higher — the discount rate reflects the same shift.
C10: Terminal EBITDA Multiple | E10: 8.5 | R10: Cross-check on the growth method; set slightly below today's trading comps to reflect a more mature business by FY34.
C11: Terminal Discount Period | E11: 9 | R11: The terminal value is struck at the end of FY34 and discounted a full nine years, even under the mid-year convention.
E14: Perpetuity Growth | G14: Terminal Multiple
C15: Sum of PV of Unlevered Free Cash Flow | E15: =SUM(G54:P54) -> 1479.3361 | G15: =E15 -> 1479.3361
C16: Terminal Value | E16: =P49*(1+$E$9)/($E$7-$E$9) -> 3598.8465 | G16: =$E$10*P56 -> 4147.3936 | R16: Two independent routes to the same question: capitalise the final cash flow, or apply an exit multiple to final-year EBITDA.
C17: PV of Terminal Value | E17: =E16/(1+$E$7)^$E$11 -> 1456.4684 | G17: =G16/(1+$E$7)^$E$11 -> 1678.4678
C18: Implied Enterprise Value | E18: =E15+E17 -> 2935.8045 | G18: =G15+G17 -> 3157.8039
C19: % of Implied TEV from Terminal Value | E19: =E17/E18 -> 0.49610538 | G19: =G17/G18 -> 0.53153008 | R19: Above roughly 75% the valuation is really a bet on the terminal assumption rather than on the forecast.
C20: (+) Cash & Cash Equivalents | E20: =Target!$F$116 -> 220.26067 | G20: =E20 -> 220.26067
C21: (-) Total Debt | E21: =-Target!F135 -> -506.7 | G21: =E21 -> -506.7
C22: Net Cash / (Debt) Bridge | E22: =E20+E21 -> -286.43933 | G22: =E22 -> -286.43933
C23: Implied Equity Value | E23: =E18+E22 -> 2649.3652 | G23: =G18+G22 -> 2871.3645
C24: Diluted Shares Outstanding | E24: =Target!$E$15 -> 55.593651 | G24: =E24 -> 55.593651
C25: Implied Share Price | E25: =E23/E24 -> 47.655895 | G25: =G23/G24 -> 51.649145
C26: Premium / (Discount) to Current Price | E26: =E25/Target!E11-1 -> 0.26073797 | G26: =G25/Target!E11-1 -> 0.3663795 | R26: Compare against the 14% offer premium — this is the core evidence for case question 2.
C28: Implied Terminal FCF Growth (from the multiple method) | E28: =($E$7*G16-P49)/(G16+P49) -> 0.032782679
C29: Implied Terminal EBITDA Multiple (from the growth method) | E29: =E16/P56 -> 7.3757637 | R29: Sanity check: each method should imply a sensible value for the other's key input. Large divergence means one of the two is wrong.
B31: 2. UNLEVERED FREE CASH FLOW PROJECTIONS | L31: extended | M31: FY25E-FY30E link directly to the Target operating model; FY31E-FY34E are extended here with fading growth and stable margins. | N31: extended | O31: extended | P31: extended
D32: ($ in millions) | F32: =Merger_Model!$F$89 -> 46022 | G32: =Merger_Model!$G$89 -> 46387 | H32: =Merger_Model!$H$89 -> 46752 | I32: =Merger_Model!$I$89 -> 47118 | J32: =Merger_Model!$J$89 -> 47483 | K32: =Merger_Model!$K$89 -> 47848 | L32: =EOMONTH(K32,12) -> 48213 | N32: =EOMONTH(L32,12) -> 48579 | O32: =EOMONTH(N32,12) -> 48944 | P32: =EOMONTH(O32,12) -> 49309
C33: Total Revenue | D33: $M | F33: =Target!F90 -> 2708.5 | G33: =Target!G90 -> 2854.0245 | H33: =Target!H90 -> 3000.0668 | I33: =Target!I90 -> 3143.3389 | J33: =Target!J90 -> 3280.8122 | K33: =Target!K90 -> 3408.3886 | L33: =K33*(1+L34) -> 3510.6402 | N33: =L33*(1+N34) -> 3608.9381 | O33: =N33*(1+O34) -> 3699.1616 | P33: =O33*(1+P34) -> 3782.3927
C34: Growth Rate | D34: % | F34: =Target!F194 -> 0.047775629 | G34: =Target!G194 -> 0.053728817 | H34: =Target!H194 -> 0.051170669 | I34: =Target!I194 -> 0.047756296 | J34: =Target!J194 -> 0.043734786 | K34: =Target!K194 -> 0.038885611 | L34: 0.03 | N34: 0.028 | O34: 0.025 | P34: 0.0225 | R34: Growth fades from 3.0% to 2.25% by FY34 so that the terminal year is a genuine steady state consistent with the terminal growth rate above.
C36: Earnings Before Interest & Taxes (EBIT) | D36: $M | F36: =Target!F102 -> 258.94677 | G36: =Target!G102 -> 285.38785 | H36: =Target!H102 -> 310.68862 | I36: =Target!I102 -> 334.0283 | J36: =Target!J102 -> 353.885 | K36: =Target!K102 -> 369.29423 | L36: =L33*L37 -> 384.4151 | N36: =N33*N37 -> 395.17873 | O36: =O33*O37 -> 403.20861 | P36: =P33*P37 -> 412.28081
C37: EBIT Margin | D37: % | F37: =F36/F33 -> 0.09560523 | G37: =G36/G33 -> 0.099994883 | H37: =H36/H33 -> 0.10356057 | I37: =I36/I33 -> 0.10626544 | J37: =J36/J33 -> 0.10786506 | K37: =K36/K33 -> 0.10834863 | L37: 0.1095 | N37: 0.1095 | O37: 0.109 | P37: 0.109 | R37: Held flat at roughly the FY30E level — margin expansion is assumed to stop once the business is mature.
C38: (-) Taxes on EBIT | D38: $M | F38: =-F36*Target!$E$10 -> -63.441957 | G38: =-G36*Target!$E$10 -> -69.920022 | H38: =-H36*Target!$E$10 -> -76.118713 | I38: =-I36*Target!$E$10 -> -81.836934 | J38: =-J36*Target!$E$10 -> -86.701824 | K38: =-K36*Target!$E$10 -> -90.477087 | L38: =-L36*Target!$E$10 -> -94.181701 | N38: =-N36*Target!$E$10 -> -96.818788 | O38: =-O36*Target!$E$10 -> -98.786111 | P38: =-P36*Target!$E$10 -> -101.0088 | R38: Taxed at the full unlevered rate — the interest tax shield belongs in the WACC, not the cash flow.
C39: Net Operating Profit After Tax (NOPAT) | D39: $M | F39: =F36+F38 -> 195.50481 | G39: =G36+G38 -> 215.46782 | H39: =H36+H38 -> 234.56991 | I39: =I36+I38 -> 252.19137 | J39: =J36+J38 -> 267.18317 | K39: =K36+K38 -> 278.81715 | L39: =L36+L38 -> 290.2334 | N39: =N36+N38 -> 298.35994 | O39: =O36+O38 -> 304.4225 | P39: =P36+P38 -> 311.27201
C41: (+) Depreciation & Amortisation | D41: $M | F41: =Target!F152+Target!F153 -> 58.77445 | G41: =Target!G152+Target!G153 -> 61.646929 | H41: =Target!H152+Target!H153 -> 64.20143 | I41: =Target!I152+Target!I153 -> 66.324451 | J41: =Target!J152+Target!J153 -> 68.240893 | K41: =Target!K152+Target!K153 -> 70.212804 | L41: =L33*L42 -> 70.212804 | N41: =N33*N42 -> 72.178763 | O41: =O33*O42 -> 73.983232 | P41: =P33*P42 -> 75.647855
C42: % of Revenue | D42: % | F42: =F41/F33 -> 0.0217 | G42: =G41/G33 -> 0.0216 | H42: =H41/H33 -> 0.0214 | I42: =I41/I33 -> 0.0211 | J42: =J41/J33 -> 0.0208 | K42: =K41/K33 -> 0.0206 | L42: 0.02 | N42: 0.02 | O42: 0.02 | P42: 0.02
C43: (+/-) Deferred Income Taxes | D43: $M | F43: =Target!F157 -> 4.5376238 | G43: =Target!G157 -> 3.8835117 | H43: =Target!H157 -> 3.6331117 | I43: =Target!I157 -> 3.2135433 | J43: =Target!J157 -> 3.4944168 | K43: =Target!K157 -> 3.7400256 | L43: =0 -> 0 | N43: =0 -> 0 | O43: =0 -> 0 | P43: =0 -> 0
C44: (+/-) Change in Working Capital | D44: $M | F44: =Target!F166 -> -21.339141 | G44: =Target!G166 -> -22.402974 | H44: =Target!H166 -> -22.516544 | I44: =Target!I166 -> -23.861421 | J44: =Target!J166 -> -22.846812 | K44: =Target!K166 -> -23.589371 | L44: =-(L33-K33)*L45 -> -22.495365 | N44: =-(N33-L33)*N45 -> -21.625544 | O44: =-(O33-N33)*O45 -> -19.84916 | P44: =-(P33-O33)*P45 -> -18.31085
C45: % of Change in Revenue | D45: % | F45: =IFERROR(-F44/(F33-E33),0) -> 0.0078785826 | G45: =IFERROR(-G44/(G33-F33),0) -> 0.15394641 | H45: =IFERROR(-H44/(H33-G33),0) -> 0.15417819 | I45: =IFERROR(-I44/(I33-H33),0) -> 0.1665462 | J45: =IFERROR(-J44/(J33-I33),0) -> 0.16619096 | K45: =IFERROR(-K44/(K33-J33),0) -> 0.1849039 | L45: 0.22 | N45: 0.22 | O45: 0.22 | P45: 0.22 | R45: Growth consumes working capital: roughly 22 cents of receivables and inventory for every extra dollar of revenue.
C46: (-) Capital Expenditures, Net of Disposals | D46: $M | F46: =Target!F169+Target!F170 -> -54.8785 | G46: =Target!G169+Target!G170 -> -56.507502 | H46: =Target!H169+Target!H170 -> -58.001337 | I46: =Target!I169+Target!I170 -> -59.295109 | J46: =Target!J169+Target!J170 -> -60.335431 | K46: =Target!K169+Target!K170 -> -62.759383 | L46: =-L33*L47 -> -66.702164 | N46: =-N33*N47 -> -68.569825 | O46: =-O33*O47 -> -72.133651 | P46: =-P33*P47 -> -75.647855
C47: % of Revenue | D47: % | F47: =-F46/F33 -> 0.020261584 | G47: =-G46/G33 -> 0.019799235 | H47: =-H46/H33 -> 0.019333348 | I47: =-I46/I33 -> 0.018863734 | J47: =-J46/J33 -> 0.018390395 | K47: =-K46/K33 -> 0.018413212 | L47: 0.019 | N47: 0.019 | O47: 0.0195 | P47: 0.02 | R47: Net capex converges toward D&A by FY34, consistent with a business no longer adding capacity.
C49: Unlevered Free Cash Flow | D49: $M | F49: =F39+F41+F43+F44+F46 -> 182.59924 | G49: =G39+G41+G43+G44+G46 -> 202.08779 | H49: =H39+H41+H43+H44+H46 -> 221.88657 | I49: =I39+I41+I43+I44+I46 -> 238.57283 | J49: =J39+J41+J43+J44+J46 -> 255.73624 | K49: =K39+K41+K43+K44+K46 -> 266.42122 | L49: =L39+L41+L43+L44+L46 -> 271.24868 | N49: =N39+N41+N43+N44+N46 -> 280.34333 | O49: =O39+O41+O43+O44+O46 -> 286.42292 | P49: =P39+P41+P43+P44+P46 -> 292.96116
C50: Growth Rate | G50: =IFERROR(G49/F49-1,0) -> 0.10672852 | H50: =IFERROR(H49/G49-1,0) -> 0.097971206 | I50: =IFERROR(I49/H49-1,0) -> 0.075201757 | J50: =IFERROR(J49/I49-1,0) -> 0.071941996 | K50: =IFERROR(K49/J49-1,0) -> 0.041781271 | L50: =IFERROR(L49/K49-1,0) -> 0.018119639 | N50: =IFERROR(N49/L49-1,0) -> 0.033528842 | O50: =IFERROR(O49/N49-1,0) -> 0.021686236 | P50: =IFERROR(P49/O49-1,0) -> 0.022827207
C52: Discount Period | G52: =1-$E$8*0.5 -> 0.5 | H52: =2-$E$8*0.5 -> 1.5 | I52: =3-$E$8*0.5 -> 2.5 | J52: =4-$E$8*0.5 -> 3.5 | K52: =5-$E$8*0.5 -> 4.5 | L52: =6-$E$8*0.5 -> 5.5 | N52: =7-$E$8*0.5 -> 6.5 | O52: =8-$E$8*0.5 -> 7.5 | P52: =9-$E$8*0.5 -> 8.5 | R52: Mid-year convention subtracts half a year from each period.
C53: Discount Factor | G53: =1/(1+$E$7)^G52 -> 0.95098643 | H53: =1/(1+$E$7)^H52 -> 0.86004853 | I53: =1/(1+$E$7)^I52 -> 0.77780655 | J53: =1/(1+$E$7)^J52 -> 0.70342894 | K53: =1/(1+$E$7)^K52 -> 0.63616368 | L53: =1/(1+$E$7)^L52 -> 0.57533065 | N53: =1/(1+$E$7)^N52 -> 0.52031476 | O53: =1/(1+$E$7)^O52 -> 0.47055976 | P53: =1/(1+$E$7)^P52 -> 0.42556257
C54: PV of Unlevered Free Cash Flow | G54: =G49*G53 -> 192.18274 | H54: =H49*H53 -> 190.83322 | I54: =I49*I53 -> 185.56351 | J54: =J49*J53 -> 179.89227 | K54: =K49*K53 -> 169.48751 | L54: =L49*L53 -> 156.05768 | N54: =N49*N53 -> 145.86678 | O54: =O49*O53 -> 134.7791 | P54: =P49*P53 -> 124.67331
C56: Memo: EBITDA | F56: =F36+F41 -> 317.72122 | G56: =G36+G41 -> 347.03477 | H56: =H36+H41 -> 374.89005 | I56: =I36+I41 -> 400.35275 | J56: =J36+J41 -> 422.12589 | K56: =K36+K41 -> 439.50704 | L56: =L36+L41 -> 454.62791 | N56: =N36+N41 -> 467.35749 | O56: =O36+O41 -> 477.19185 | P56: =P36+P41 -> 487.92866
B59: 3. DCF SENSITIVITIES — IMPLIED SHARE PRICE | M59: Each cell re-runs the full DCF from the cash-flow row, so these are live formulas rather than static data tables.
C61: Grid A — Terminal FCF Growth Rate (columns) vs. Discount Rate (rows)
F62: Terminal FCF Growth Rate
E63: =E25 -> 47.655895 | F63: 0.0125 | G63: 0.0175 | H63: 0.0225 | I63: 0.0275 | J63: 0.0325
E64: 0.09 | F64: 54.798982 | G64: 57.152422 | H64: 59.85452 | I64: 62.988954 | J64: 66.668507
E65: 0.095 | F65: 51.136924 | G65: 53.130745 | H65: 55.399576 | I65: 58.004531 | J65: 61.026278
C66: Discount Rate (WACC) | E66: 0.1 | F66: 47.898636 | G66: 49.601388 | H66: 51.523849 | I66: 53.711478 | J66: 56.2232
E67: 0.105 | F67: 45.015093 | G67: 46.479651 | H67: 48.121733 | I67: 49.975695 | J67: 52.085377
E68: 0.11 | F68: 42.431447 | G68: 43.69917 | H68: 45.111777 | I68: 46.695609 | J68: 48.483806
E69: 0.115 | F69: 40.103568 | G69: 41.207208 | H69: 42.430161 | I69: 43.792879 | J69: 45.320776
E70: 0.12 | F70: 37.995554 | G70: 38.961334 | H70: 40.026169 | I70: 41.206121 | J70: 42.520925
C73: Grid B — Terminal EBITDA Multiple (columns) vs. Discount Rate (rows)
F74: Terminal EBITDA Multiple
E75: =G25 -> 51.649145 | F75: 7.5 | G75: 8 | H75: 8.5 | I75: 9 | J75: 9.5
E76: 0.09 | F76: 53.408175 | G76: 55.428693 | H76: 57.449211 | I76: 59.469729 | J76: 61.490246
E77: 0.095 | F77: 51.645842 | G77: 53.584826 | H77: 55.523809 | I77: 57.462792 | J77: 59.401776
C78: Discount Rate (WACC) | E78: 0.1 | F78: 49.954415 | G78: 51.815504 | H78: 53.676592 | I78: 55.53768 | J78: 57.398768
E79: 0.105 | F79: 48.330612 | G79: 50.117267 | H79: 51.903922 | I79: 53.690576 | J79: 55.477231
E80: 0.11 | F80: 46.77132 | G80: 48.486834 | H80: 50.202348 | I80: 51.917862 | J80: 53.633377
E81: 0.115 | F81: 45.273583 | G81: 46.92109 | H81: 48.568598 | I81: 50.216105 | J81: 51.863612
E82: 0.12 | F82: 43.834598 | G82: 45.417081 | H82: 46.999564 | I82: 48.582046 | J82: 50.164529
B86: 4. IRR ON THE ACQUISITION (INCLUDING SYNERGIES) | M86: Treats the deal as an investment: pay the purchase enterprise value today, receive Calder's unlevered cash flow plus synergies.
C88: Purchase Enterprise Value | E88: =Merger_Model!$E$23 -> 2984.2793
C89: Acquirer's WACC (hurdle rate) | E89: =WACC!F44 -> 0.10390378
C90: Long-Term Growth Rate | E90: =Synergies!$E$47 -> 0.015
C91: Synergy Realisation Factor | E91: =Merger_Model!$E$12 -> 1
F93: Close | G93: FY26E | H93: FY27E | I93: FY28E | J93: FY29E | K93: FY30E
C94: Target Unlevered Free Cash Flow | G94: =G49 -> 202.08779 | H94: =H49 -> 221.88657 | I94: =I49 -> 238.57283 | J94: =J49 -> 255.73624 | K94: =K49 -> 266.42122
C95: (+) After-Tax Synergies, Net of Costs to Achieve | G95: =Synergies!G42 -> 2.436503 | H95: =Synergies!H42 -> 53.103803 | I95: =Synergies!I42 -> 96.917657 | J95: =Synergies!J42 -> 104.96982 | K95: =Synergies!K42 -> 108.0474
C96: (+) Terminal Value | K96: =(K94+K95)*(1+$E$90)/($E$89-$E$90) -> 4275.2476 | R96: Perpetuity on the Year 5 combined cash flow, discounted at the acquirer's WACC.
C97: Total Cash Flow to the Acquirer | F97: =-$E$88 -> -2984.2793 | G97: =SUM(G94,G95,G96) -> 204.52429 | H97: =SUM(H94,H95,H96) -> 274.99037 | I97: =SUM(I94,I95,I96) -> 335.49049 | J97: =SUM(J94,J95,J96) -> 360.70605 | K97: =SUM(K94,K95,K96) -> 4649.7162
C99: Memo: the same at 100% realisation | G99: =IFERROR(G95/$E$91,0) -> 2.436503 | H99: =IFERROR(H95/$E$91,0) -> 53.103803 | I99: =IFERROR(I95/$E$91,0) -> 96.917657 | J99: =IFERROR(J95/$E$91,0) -> 104.96982 | K99: =IFERROR(K95/$E$91,0) -> 108.0474
C101: Internal Rate of Return (IRR) | E101: =IRR(F97:K97) -> 0.16216723
C102: IRR less Acquirer's WACC (value spread) | E102: =E101-$E$89 -> 0.058263452 | R102: A positive spread means the deal earns more than the cost of the capital used to fund it — the cleanest single test of whether the price is justified.
C105: Sensitivity A — IRR vs. Purchase Enterprise Value | R105: Each row is a complete cash-flow stream with only the entry price changed, so IRR() can be applied directly.
C107: Purchase TEV at 85% of base | D107: =$E$88*0.85 -> 2536.6374 | E107: =IRR(F107:K107) -> 0.20670792 | F107: =-D107 -> -2536.6374 | G107: =G97 -> 204.52429 | H107: =H97 -> 274.99037 | I107: =I97 -> 335.49049 | J107: =J97 -> 360.70605 | K107: =K97 -> 4649.7162
C108: Purchase TEV at 92% of base | D108: =$E$88*0.925 -> 2760.4584 | E108: =IRR(F108:K108) -> 0.18325007 | F108: =-D108 -> -2760.4584 | G108: =G97 -> 204.52429 | H108: =H97 -> 274.99037 | I108: =I97 -> 335.49049 | J108: =J97 -> 360.70605 | K108: =K97 -> 4649.7162
C109: Purchase TEV at 100% of base | D109: =$E$88*1 -> 2984.2793 | E109: =IRR(F109:K109) -> 0.16216723 | F109: =-D109 -> -2984.2793 | G109: =G97 -> 204.52429 | H109: =H97 -> 274.99037 | I109: =I97 -> 335.49049 | J109: =J97 -> 360.70605 | K109: =K97 -> 4649.7162
C110: Purchase TEV at 108% of base | D110: =$E$88*1.075 -> 3208.1003 | E110: =IRR(F110:K110) -> 0.14305829 | F110: =-D110 -> -3208.1003 | G110: =G97 -> 204.52429 | H110: =H97 -> 274.99037 | I110: =I97 -> 335.49049 | J110: =J97 -> 360.70605 | K110: =K97 -> 4649.7162
C111: Purchase TEV at 115% of base | D111: =$E$88*1.15 -> 3431.9212 | E111: =IRR(F111:K111) -> 0.12561304 | F111: =-D111 -> -3431.9212 | G111: =G97 -> 204.52429 | H111: =H97 -> 274.99037 | I111: =I97 -> 335.49049 | J111: =J97 -> 360.70605 | K111: =K97 -> 4649.7162
C114: Sensitivity B — IRR vs. Expense Synergy Realisation | R114: The deal's return is highly geared to synergy delivery — at zero realisation the IRR collapses toward the standalone cash-flow yield.
C116: Synergies realised at 125% | D116: 1.25 | E116: =IRR(F116:K116) -> 0.17946736 | F116: =-$E$88 -> -2984.2793 | G116: =(G94+G99*$D116) -> 205.13342 | H116: =(H94+H99*$D116) -> 288.26633 | I116: =(I94+I99*$D116) -> 359.7199 | J116: =(J94+J99*$D116) -> 386.94851 | K116: =(K94+K99*$D116)*(1+(1+$E$90)/($E$89-$E$90)) -> 4985.118
C117: Synergies realised at 100% | D117: 1 | E117: =IRR(F117:K117) -> 0.16216723 | F117: =-$E$88 -> -2984.2793 | G117: =(G94+G99*$D117) -> 204.52429 | H117: =(H94+H99*$D117) -> 274.99037 | I117: =(I94+I99*$D117) -> 335.49049 | J117: =(J94+J99*$D117) -> 360.70605 | K117: =(K94+K99*$D117)*(1+(1+$E$90)/($E$89-$E$90)) -> 4649.7162
C118: Synergies realised at 75% | D118: 0.75 | E118: =IRR(F118:K118) -> 0.14390606 | F118: =-$E$88 -> -2984.2793 | G118: =(G94+G99*$D118) -> 203.91517 | H118: =(H94+H99*$D118) -> 261.71442 | I118: =(I94+I99*$D118) -> 311.26107 | J118: =(J94+J99*$D118) -> 334.4636 | K118: =(K94+K99*$D118)*(1+(1+$E$90)/($E$89-$E$90)) -> 4314.3144
C119: Synergies realised at 50% | D119: 0.5 | E119: =IRR(F119:K119) -> 0.12454668 | F119: =-$E$88 -> -2984.2793 | G119: =(G94+G99*$D119) -> 203.30604 | H119: =(H94+H99*$D119) -> 248.43847 | I119: =(I94+I99*$D119) -> 287.03166 | J119: =(J94+J99*$D119) -> 308.22115 | K119: =(K94+K99*$D119)*(1+(1+$E$90)/($E$89-$E$90)) -> 3978.9126
C120: Synergies realised at 25% | D120: 0.25 | E120: =IRR(F120:K120) -> 0.10391859 | F120: =-$E$88 -> -2984.2793 | G120: =(G94+G99*$D120) -> 202.69691 | H120: =(H94+H99*$D120) -> 235.16252 | I120: =(I94+I99*$D120) -> 262.80225 | J120: =(J94+J99*$D120) -> 281.97869 | K120: =(K94+K99*$D120)*(1+(1+$E$90)/($E$89-$E$90)) -> 3643.5109
C121: Synergies realised at 0% | D121: 0 | E121: =IRR(F121:K121) -> 0.081805874 | F121: =-$E$88 -> -2984.2793 | G121: =(G94+G99*$D121) -> 202.08779 | H121: =(H94+H99*$D121) -> 221.88657 | I121: =(I94+I99*$D121) -> 238.57283 | J121: =(J94+J99*$D121) -> 255.73624 | K121: =(K94+K99*$D121)*(1+(1+$E$90)/($E$89-$E$90)) -> 3308.1091

Sheet WACC
B2: Weighted Average Cost of Capital — Discount Rate Derivation
B3: ($ in millions, except per-share and per-unit data)
B4: One unlevered beta is drawn from the peer group and re-levered to each company's own capital structure, giving a target WACC for the DCF and an acquirer WACC for valuing synergies and the deal IRR.
B5: 1. MARKET ASSUMPTIONS
B7: Risk-Free Rate | F7: 0.0425 | M7: 10-year government bond yield at the analysis date.
B8: Equity Risk Premium | F8: 0.055 | M8: Long-run supply-side premium for a developed market.
B9: Marginal Tax Rate (used to unlever peer betas) | F9: 0.24
B11: 2. PEER GROUP — UNLEVERING OBSERVED BETAS | M11: Hamada: Unlevered Beta = Levered Beta / (1 + (1 - t) x Debt / Equity). Strips out each peer's financing decision.
B12: Company | C12: Ticker | D12: Levered Beta | E12: Total Debt | F12: Equity Value | G12: Debt / Equity | H12: Unlevered Beta
B13: Anchorpoint Industrial Group | C13: APIG | D13: 1.42 | E13: =Pub_Comps!H9 -> 1180 | F13: =Pub_Comps!F9 -> 4453.68 | G13: =E13/F13 -> 0.26494944 | H13: =D13/(1+(1-$F$9)*G13) -> 1.1819922
B14: Ardent Flow Technologies | C14: ARFT | D14: 1.31 | E14: =Pub_Comps!H10 -> 690 | F14: =Pub_Comps!F10 -> 2951.65 | G14: =E14/F14 -> 0.23376755 | H14: =D14/(1+(1-$F$9)*G14) -> 1.1123722
B15: Castellan Supply Holdings | C15: CSLH | D15: 1.88 | E15: =Pub_Comps!H11 -> 2240 | F15: =Pub_Comps!F11 -> 3104.64 | G15: =E15/F15 -> 0.72150072 | H15: =D15/(1+(1-$F$9)*G15) -> 1.2142032
B16: Delaney Process Solutions | C16: DLPS | D16: 1.24 | E16: =Pub_Comps!H12 -> 415 | F16: =Pub_Comps!F12 -> 2482.35 | G16: =E16/F16 -> 0.16718029 | H16: =D16/(1+(1-$F$9)*G16) -> 1.1002105
B17: Ellsworth Bearing & Drive | C17: EBDC | D17: 1.61 | E17: =Pub_Comps!H13 -> 985 | F17: =Pub_Comps!F13 -> 2837.32 | G17: =E17/F17 -> 0.34715859 | H17: =D17/(1+(1-$F$9)*G17) -> 1.2738949
B18: Harlow Valve & Controls | C18: HVCX | D18: 1.36 | E18: =Pub_Comps!H14 -> 560 | F18: =Pub_Comps!F14 -> 2317.07 | G18: =E18/F18 -> 0.24168454 | H18: =D18/(1+(1-$F$9)*G18) -> 1.1489589
B19: Kestrel MRO Distribution | C19: KMRO | D19: 2.05 | E19: =Pub_Comps!H15 -> 3120 | F19: =Pub_Comps!F15 -> 3890.435 | G19: =E19/F19 -> 0.80196688 | H19: =D19/(1+(1-$F$9)*G19) -> 1.2736916
B20: Northvale Fasteners | C20: NVFS | D20: 1.18 | E20: =Pub_Comps!H16 -> 340 | F20: =Pub_Comps!F16 -> 2360.28 | G20: =E20/F20 -> 0.14405071 | H20: =D20/(1+(1-$F$9)*G20) -> 1.0635627
B21: Sable Point Industrial | C21: SPIN | D21: 1.72 | E21: =Pub_Comps!H17 -> 1675 | F21: =Pub_Comps!F17 -> 3757.24 | G21: =E21/F21 -> 0.44580596 | H21: =D21/(1+(1-$F$9)*G21) -> 1.2847206
B22: Trellis Flow Group | C22: TRFG | D22: 1.49 | E22: =Pub_Comps!H18 -> 820 | F22: =Pub_Comps!F18 -> 2608.925 | G22: =E22/F22 -> 0.3143057 | H22: =D22/(1+(1-$F$9)*G22) -> 1.2027067
B24: Median | D24: =MEDIAN(D13:D22) -> 1.455 | G24: =MEDIAN(G13:G22) -> 0.28962757 | H24: =MEDIAN(H13:H22) -> 1.1923494
B26: 3. RE-LEVERED BETA, COST OF EQUITY AND WACC
E27: Target (CFFS) | F27: Acquirer (MIDS)
B28: Median Unlevered Beta (peer group) | E28: =$H$24 -> 1.1923494 | F28: =$H$24 -> 1.1923494
B29: Total Debt | E29: =Target!$E$19 -> 545 | F29: =Acquirer!$E$19 -> 1650
B30: Equity Value | E30: =Target!E17 -> 2101.44 | F30: =Acquirer!$E$17 -> 4095.35
B31: Debt / Equity | E31: =E29/E30 -> 0.25934597 | F31: =F29/F30 -> 0.40289597
B32: Effective Tax Rate | E32: =Target!$E$10 -> 0.245 | F32: =Acquirer!$E$10 -> 0.24
B33: Re-Levered Beta | E33: =$H$24*(1+(1-E32)*E31) -> 1.4258188 | F33: =$H$24*(1+(1-F32)*F31) -> 1.5574479 | M33: Re-levered to each company's own capital structure — the acquirer carries more leverage, so it earns a higher beta.
B34: Cost of Equity (Rf + Beta x ERP) | E34: =$F$7+E33*$F$8 -> 0.12092004 | F34: =$F$7+F33*$F$8 -> 0.12815964
B36: Pre-Tax Cost of Debt | E36: =Target!$F$75 -> 0.0625 | F36: =Acquirer!F75 -> 0.0575 | M36: Each company's own blended borrowing rate, taken straight from its operating model.
B37: After-Tax Cost of Debt | E37: =E36*(1-E32) -> 0.0471875 | F37: =F36*(1-F32) -> 0.0437
B39: % Equity | E39: =E30/(E29+E30) -> 0.79406297 | F39: =F30/(F29+F30) -> 0.71281123
B40: % Debt | E40: =E29/(E29+E30) -> 0.20593703 | F40: =F29/(F29+F30) -> 0.28718877
B42: WACC = Cost of Equity x % Equity + After-Tax Cost of Debt x % Debt
B44: WACC — Current Capital Structure | E44: =E34*E39+E37*E40 -> 0.10573578 | F44: =F34*F39+F37*F40 -> 0.10390378 | M44: E44 discounts Calder's cash flows in the DCF. F44 discounts the synergies and is the hurdle rate for the deal IRR.

Sheet Pub_Comps
B2: Comparable Public Companies - North American Industrial Distributors & Flow-Control Suppliers
B3: ($ in millions, except per-share and per-unit data)
B4: Screened for revenue of $1bn-$8bn and a comparable end-market mix. Meridian and Calder are shown inside the set, with their statistics linked live from their own tabs.
B5: OPERATING & VALUATION STATISTICS | M5: TEV excludes operating lease liabilities on the same basis as the company tabs, so the multiples are directly comparable.
B8: Company | C8: Ticker | D8: Share Price | E8: Diluted Shares | F8: Equity Value | G8: Cash | H8: Total Debt | I8: Enterprise Value | J8: FY25E Revenue | K8: FY26E Revenue | L8: FY25E EBITDA | M8: FY26E EBITDA | N8: FY25E EBITDA Margin | O8: TEV / FY25E Rev | P8: TEV / FY25E EBITDA | Q8: TEV / FY26E EBITDA
B9: Anchorpoint Industrial Group | C9: APIG | D9: 48.2 | E9: 92.4 | F9: =D9*E9 -> 4453.68 | G9: 240 | H9: 1180 | I9: =F9-G9+H9 -> 5393.68 | J9: 4180 | K9: 4420 | L9: 505 | M9: 555 | N9: =L9/J9 -> 0.1208134 | O9: =I9/J9 -> 1.2903541 | P9: =I9/L9 -> 10.680554 | Q9: =I9/M9 -> 9.7183423
B10: Ardent Flow Technologies | C10: ARFT | D10: 61.75 | E10: 47.8 | F10: =D10*E10 -> 2951.65 | G10: 165 | H10: 690 | I10: =F10-G10+H10 -> 3476.65 | J10: 1780 | K10: 1900 | L10: 278 | M10: 308 | N10: =L10/J10 -> 0.15617978 | O10: =I10/J10 -> 1.9531742 | P10: =I10/L10 -> 12.505935 | Q10: =I10/M10 -> 11.287825
B11: Castellan Supply Holdings | C11: CSLH | D11: 22.4 | E11: 138.6 | F11: =D11*E11 -> 3104.64 | G11: 118 | H11: 2240 | I11: =F11-G11+H11 -> 5226.64 | J11: 5640 | K11: 5880 | L11: 560 | M11: 615 | N11: =L11/J11 -> 0.09929078 | O11: =I11/J11 -> 0.92670922 | P11: =I11/L11 -> 9.3332857 | Q11: =I11/M11 -> 8.4986016
B12: Delaney Process Solutions | C12: DLPS | D12: 74.1 | E12: 33.5 | F12: =D12*E12 -> 2482.35 | G12: 205 | H12: 415 | I12: =F12-G12+H12 -> 2692.35 | J12: 1240 | K12: 1320 | L12: 205 | M12: 228 | N12: =L12/J12 -> 0.16532258 | O12: =I12/J12 -> 2.17125 | P12: =I12/L12 -> 13.133415 | Q12: =I12/M12 -> 11.808553
B13: Ellsworth Bearing & Drive | C13: EBDC | D13: 39.85 | E13: 71.2 | F13: =D13*E13 -> 2837.32 | G13: 96 | H13: 985 | I13: =F13-G13+H13 -> 3726.32 | J13: 2860 | K13: 3010 | L13: 340 | M13: 374 | N13: =L13/J13 -> 0.11888112 | O13: =I13/J13 -> 1.3029091 | P13: =I13/L13 -> 10.959765 | Q13: =I13/M13 -> 9.9634225
B14: Harlow Valve & Controls | C14: HVCX | D14: 55.3 | E14: 41.9 | F14: =D14*E14 -> 2317.07 | G14: 142 | H14: 560 | I14: =F14-G14+H14 -> 2735.07 | J14: 1510 | K14: 1615 | L14: 228 | M14: 252 | N14: =L14/J14 -> 0.15099338 | O14: =I14/J14 -> 1.8113046 | P14: =I14/L14 -> 11.995921 | Q14: =I14/M14 -> 10.853452
B15: Kestrel MRO Distribution | C15: KMRO | D15: 18.95 | E15: 205.3 | F15: =D15*E15 -> 3890.435 | G15: 88 | H15: 3120 | I15: =F15-G15+H15 -> 6922.435 | J15: 7320 | K15: 7610 | L15: 730 | M15: 800 | N15: =L15/J15 -> 0.099726776 | O15: =I15/J15 -> 0.94568784 | P15: =I15/L15 -> 9.4827877 | Q15: =I15/M15 -> 8.6530438
B16: Northvale Fasteners | C16: NVFS | D16: 88.4 | E16: 26.7 | F16: =D16*E16 -> 2360.28 | G16: 310 | H16: 340 | I16: =F16-G16+H16 -> 2390.28 | J16: 985 | K16: 1045 | L16: 185 | M16: 202 | N16: =L16/J16 -> 0.18781726 | O16: =I16/J16 -> 2.4266802 | P16: =I16/L16 -> 12.920432 | Q16: =I16/M16 -> 11.833069
B17: Sable Point Industrial | C17: SPIN | D17: 31.6 | E17: 118.9 | F17: =D17*E17 -> 3757.24 | G17: 130 | H17: 1675 | I17: =F17-G17+H17 -> 5302.24 | J17: 3940 | K17: 4130 | L17: 490 | M17: 540 | N17: =L17/J17 -> 0.12436548 | O17: =I17/J17 -> 1.3457462 | P17: =I17/L17 -> 10.820898 | Q17: =I17/M17 -> 9.818963
B18: Trellis Flow Group | C18: TRFG | D18: 44.75 | E18: 58.3 | F18: =D18*E18 -> 2608.925 | G18: 178 | H18: 820 | I18: =F18-G18+H18 -> 3250.925 | J18: 2240 | K18: 2390 | L18: 285 | M18: 315 | N18: =L18/J18 -> 0.12723214 | O18: =I18/J18 -> 1.4513058 | P18: =I18/L18 -> 11.406754 | Q18: =I18/M18 -> 10.320397
B19: Meridian Industrial Supply, Inc. | C19: MIDS | D19: =Acquirer!E11 -> 34.5 | E19: =Acquirer!E15 -> 118.7058 | F19: =D19*E19 -> 4095.35 | G19: =Acquirer!F116 -> 362.16442 | H19: =Acquirer!F135 -> 1534.2 | I19: =F19-G19+H19 -> 5267.3856 | J19: =Acquirer!F90 -> 6445.575 | K19: =Acquirer!G90 -> 6756.087 | L19: =Acquirer!F192 -> 635.80591 | M19: =Acquirer!G192 -> 675.99633 | N19: =L19/J19 -> 0.098642232 | O19: =I19/J19 -> 0.81720957 | P19: =I19/L19 -> 8.2845811 | Q19: =I19/M19 -> 7.7920329 | R19: Linked live from the Acquirer tab - the comp set updates automatically if the operating model changes.
B20: Calder Fluid & Flow Systems, Inc. | C20: CFFS | D20: =Target!E11 -> 37.8 | E20: =Target!E15 -> 55.593651 | F20: =D20*E20 -> 2101.44 | G20: =Target!F116 -> 220.26067 | H20: =Target!F135 -> 506.7 | I20: =F20-G20+H20 -> 2387.8793 | J20: =Target!F90 -> 2708.5 | K20: =Target!G90 -> 2854.0245 | L20: =Target!F192 -> 317.72122 | M20: =Target!G192 -> 347.03477 | N20: =L20/J20 -> 0.11730523 | O20: =I20/J20 -> 0.88162427 | P20: =I20/L20 -> 7.5156433 | Q20: =I20/M20 -> 6.8808071
B22: Maximum | N22: =MAX(N9:N20) -> 0.18781726 | O22: =MAX(O9:O20) -> 2.4266802 | P22: =MAX(P9:P20) -> 13.133415 | Q22: =MAX(Q9:Q20) -> 11.833069
B23: 75th Percentile | N23: =QUARTILE(N9:N20,3) -> 0.15228998 | O23: =QUARTILE(O9:O20,3) -> 1.846772 | P23: =QUARTILE(P9:P20,3) -> 12.123425 | Q23: =QUARTILE(Q9:Q20,3) -> 10.962045
B24: Median | N24: =MEDIAN(N9:N20) -> 0.12258944 | O24: =MEDIAN(O9:O20) -> 1.3243276 | P24: =MEDIAN(P9:P20) -> 10.890331 | Q24: =MEDIAN(Q9:Q20) -> 9.8911927 | R24: The median is the reference point used on the Merger_Model and Value_Creation tabs. Note that Meridian trades below the peer median — the reason a 100% stock deal is expensive for its shareholders.
B25: 25th Percentile | N25: =QUARTILE(N9:N20,1) -> 0.11291062 | O25: =QUARTILE(O9:O20,1) -> 0.94094319 | P25: =QUARTILE(P9:P20,1) -> 9.4454122 | Q25: =QUARTILE(Q9:Q20,1) -> 8.6144332
B26: Minimum | N26: =MIN(N9:N20) -> 0.098642232 | O26: =MIN(O9:O20) -> 0.81720957 | P26: =MIN(P9:P20) -> 7.5156433 | Q26: =MIN(Q9:Q20) -> 6.8808071

Sheet MA_Comps
B2: Precedent Transactions -Industrial Distribution & Flow Control
B3: ($ in millions, except per-share and per-unit data)
B4: Control transactions announced 2020-2024 with enterprise values between $700m and $4bn in comparable end markets.
B5: SELECTED PRECEDENT TRANSACTIONS | M5: Precedents carry a control premium, so they typically print above the trading comps.
B8: Acquirer | C8: Target | D8: Announced | E8: Enterprise Value | F8: LTM Revenue | G8: LTM EBITDA | H8: TEV / Revenue | I8: TEV / EBITDA
B9: Anchorpoint Industrial Group | C9: Verity Bearing Corporation | D9: Nov-2024 | E9: 1285 | F9: 640 | G9: 118 | H9: =E9/F9 -> 2.0078125 | I9: =E9/G9 -> 10.889831
B10: Kestrel MRO Distribution | C10: Thorne Pipe & Supply Co. | D10: Jun-2024 | E10: 2340 | F10: 1480 | G10: 208 | H10: =E10/F10 -> 1.5810811 | I10: =E10/G10 -> 11.25
B11: Sable Point Industrial | C11: Redgate Fastener Group | D11: Feb-2024 | E11: 985 | F11: 520 | G11: 92 | H11: =E11/F11 -> 1.8942308 | I11: =E11/G11 -> 10.706522
B12: Hollis Capital Partners | C12: Marchand Flow Group | D12: Sep-2023 | E12: 1760 | F12: 1105 | G12: 172 | H12: =E12/F12 -> 1.5927602 | I12: =E12/G12 -> 10.232558
B13: Trellis Flow Group | C13: Ostrander Valve Company | D13: Apr-2023 | E13: 745 | F13: 385 | G13: 71 | H13: =E13/F13 -> 1.9350649 | I13: =E13/G13 -> 10.492958
B14: Castellan Supply Holdings | C14: Pinehurst Industrial Distribution | D14: Nov-2022 | E14: 3120 | F14: 2650 | G14: 312 | H14: =E14/F14 -> 1.1773585 | I14: =E14/G14 -> 10
B15: Ellsworth Bearing & Drive | C15: Caldicott Power Products | D15: May-2021 | E15: 1420 | F15: 890 | G15: 142 | H15: =E15/F15 -> 1.5955056 | I15: =E15/G15 -> 10
B16: Brightwater Partners LLC | C16: Halvorsen Process Equipment | D16: Aug-2020 | E16: 1095 | F16: 610 | G16: 96 | H16: =E16/F16 -> 1.795082 | I16: =E16/G16 -> 11.40625
C19: Maximum | H19: =MAX(H9:H16) -> 2.0078125 | I19: =MAX(I9:I16) -> 11.40625
C20: 75th Percentile | H20: =QUARTILE(H9:H16,3) -> 1.9044393 | I20: =QUARTILE(I9:I16,3) -> 10.979873
C21: Median | H21: =MEDIAN(H9:H16) -> 1.6952938 | I21: =MEDIAN(I9:I16) -> 10.59974
C22: 25th Percentile | H22: =QUARTILE(H9:H16,1) -> 1.5898404 | I22: =QUARTILE(I9:I16,1) -> 10.174419
C23: Minimum | H23: =MIN(H9:H16) -> 1.1773585 | I23: =MIN(I9:I16) -> 10
C25: This Transaction -Calder Fluid & Flow Systems | H25: =Merger_Model!$E$25 -> 1.1018199 | I25: =Merger_Model!$E$27 -> 9.3927607 | K25: The proposed price sits below the precedent median -the basis for arguing the offer is fair to Meridian, and that Calder's board may push for more.

Sheet Contrib
B2: Relative Contribution Analysis -MIDS / CFFS
B3: ($ in millions, except per-share and per-unit data)
B4: Asks a different question from a DCF: if each side contributes X% of the combined company's earnings, should it not own X% of it? Each metric implies its own 'fair' exchange ratio.
B5: 1. CONTRIBUTION BY METRIC | M5: Ownership under the proposed deal is shown at the bottom for comparison against each metric's implied split.
D7: Acquirer | E7: Target | F7: Combined | G7: Acquirer % | H7: Target % | I7: Implied Combined Equity Value | J7: Target Implied Equity Value | K7: Implied Exchange Ratio | L7: Implied Price / Share | M7: Implied Premium
C8: Equity Value (Undisturbed) | D8: =Acquirer!$E$17 -> 4095.35 | E8: =Target!$E$17 -> 2101.44 | F8: =D8+E8 -> 6196.79 | G8: =D8/F8 -> 0.66088249 | H8: =E8/F8 -> 0.33911751 | I8: =Acquirer!$E$17/G8 -> 6196.79 | J8: =I8*H8 -> 2101.44 | K8: =L8/Acquirer!$E$11 -> 1.0956522 | L8: =J8/Target!$E$15 -> 37.8 | M8: =L8/Target!$E$11-1 -> 0 | O8: Combined equity value is inferred as the acquirer's own market value divided by its contribution percentage -i.e. the market's view of Meridian is taken as given and Calder is valued off it.
C9: Revenue -FY26E | D9: =Acquirer!G90 -> 6756.087 | E9: =Target!G90 -> 2854.0245 | F9: =D9+E9 -> 9610.1115 | G9: =D9/F9 -> 0.70301859 | H9: =E9/F9 -> 0.29698141 | I9: =Acquirer!$E$17/G9 -> 5825.3794 | J9: =I9*H9 -> 1730.0294 | K9: =L9/Acquirer!$E$11 -> 0.90200552 | L9: =J9/Target!$E$15 -> 31.119191 | M9: =L9/Target!$E$11-1 -> -0.17674099 | O9: Revenue-based contribution flatters Calder least: it is the smaller but higher-margin business, so it contributes more EBITDA than revenue.
C10: Revenue -FY27E | D10: =Acquirer!H90 -> 7060.9885 | E10: =Target!H90 -> 3000.0668 | F10: =D10+E10 -> 10061.055 | G10: =D10/F10 -> 0.7018139 | H10: =E10/F10 -> 0.2981861 | I10: =Acquirer!$E$17/G10 -> 5835.3789 | J10: =I10*H10 -> 1740.0289 | K10: =L10/Acquirer!$E$11 -> 0.90721905 | L10: =J10/Target!$E$15 -> 31.299057 | M10: =L10/Target!$E$11-1 -> -0.17198261
C11: EBITDA -FY26E | D11: =Acquirer!G192 -> 675.99633 | E11: =Target!G192 -> 347.03477 | F11: =D11+E11 -> 1023.0311 | G11: =D11/F11 -> 0.66077788 | H11: =E11/F11 -> 0.33922212 | I11: =Acquirer!$E$17/G11 -> 6197.771 | J11: =I11*H11 -> 2102.421 | K11: =L11/Acquirer!$E$11 -> 1.0961636 | L11: =J11/Target!$E$15 -> 37.817646 | M11: =L11/Target!$E$11-1 -> 0.00046681692
C12: EBITDA -FY27E | D12: =Acquirer!H192 -> 717.57358 | E12: =Target!H192 -> 374.89005 | F12: =D12+E12 -> 1092.4636 | G12: =D12/F12 -> 0.65683979 | H12: =E12/F12 -> 0.34316021 | I12: =Acquirer!$E$17/G12 -> 6234.9299 | J12: =I12*H12 -> 2139.5799 | K12: =L12/Acquirer!$E$11 -> 1.1155376 | L12: =J12/Target!$E$15 -> 38.486047 | M12: =L12/Target!$E$11-1 -> 0.018149398
C13: EBIT -FY26E | D13: =Acquirer!G102 -> 568.57454 | E13: =Target!G102 -> 285.38785 | F13: =D13+E13 -> 853.96239 | G13: =D13/F13 -> 0.66580748 | H13: =E13/F13 -> 0.33419252 | I13: =Acquirer!$E$17/G13 -> 6150.9523 | J13: =I13*H13 -> 2055.6023 | K13: =L13/Acquirer!$E$11 -> 1.0717532 | L13: =J13/Target!$E$15 -> 36.975486 | M13: =L13/Target!$E$11-1 -> -0.021812541
C14: Net Income -FY26E | D14: =Acquirer!G108 -> 374.49697 | E14: =Target!G108 -> 199.45927 | F14: =D14+E14 -> 573.95624 | G14: =D14/F14 -> 0.65248349 | H14: =E14/F14 -> 0.34751651 | I14: =Acquirer!$E$17/G14 -> 6276.5573 | J14: =I14*H14 -> 2181.2073 | K14: =L14/Acquirer!$E$11 -> 1.1372414 | L14: =J14/Target!$E$15 -> 39.234828 | M14: =L14/Target!$E$11-1 -> 0.037958413
C15: Net Income -FY27E | D15: =Acquirer!H108 -> 413.69285 | E15: =Target!H108 -> 223.91831 | F15: =D15+E15 -> 637.61117 | G15: =D15/F15 -> 0.64881683 | H15: =E15/F15 -> 0.35118317 | I15: =Acquirer!$E$17/G15 -> 6312.028 | J15: =I15*H15 -> 2216.678 | K15: =L15/Acquirer!$E$11 -> 1.1557352 | L15: =J15/Target!$E$15 -> 39.872863 | M15: =L15/Target!$E$11-1 -> 0.054837649
C16: Total Assets at Close | D16: =Acquirer!F128 -> 4404.465 | E16: =Target!F128 -> 2141.374 | F16: =D16+E16 -> 6545.839 | G16: =D16/F16 -> 0.67286486 | H16: =E16/F16 -> 0.32713514 | I16: =Acquirer!$E$17/G16 -> 6086.4377 | J16: =I16*H16 -> 1991.0877 | K16: =L16/Acquirer!$E$11 -> 1.0381165 | L16: =J16/Target!$E$15 -> 35.815019 | M16: =L16/Target!$E$11-1 -> -0.052512726
C17: Common Shareholders' Equity at Close | D17: =Acquirer!F143 -> 1521.282 | E17: =Target!F143 -> 1132.5583 | F17: =D17+E17 -> 2653.8403 | G17: =D17/F17 -> 0.57323795 | H17: =E17/F17 -> 0.42676205 | I17: =Acquirer!$E$17/G17 -> 7144.2408 | J17: =I17*H17 -> 3048.8908 | K17: =L17/Acquirer!$E$11 -> 1.5896356 | L17: =J17/Target!$E$15 -> 54.842429 | M17: =L17/Target!$E$11-1 -> 0.4508579
C19: Maximum | K19: =MAX(K8:K17) -> 1.5896356 | L19: =MAX(L8:L17) -> 54.842429 | M19: =MAX(M8:M17) -> 0.4508579
C20: Median | K20: =MEDIAN(K8:K17) -> 1.0959079 | L20: =MEDIAN(L8:L17) -> 37.808823 | M20: =MEDIAN(M8:M17) -> 0.00023340846
C21: Minimum | K21: =MIN(K8:K17) -> 0.90200552 | L21: =MIN(L8:L17) -> 31.119191 | M21: =MIN(M8:M17) -> -0.17674099
C23: PROPOSED TRANSACTION
C24: Exchange Ratio Offered | E24: =Merger_Model!$E$14 -> 1.4
C25: Offer Price per Share | E25: =Merger_Model!$E$15 -> 48.3
C26: Premium Offered | E26: =Merger_Model!$E$17 -> 0.27777778
C27: Pro-Forma Ownership -Acquirer | E27: =Acquirer!$E$15/Merger_Model!G130 -> 0.6028611 | O27: Compare the target's pro-forma ownership against its contribution percentages above. Owning materially more than it contributes on earnings is the quantitative case that the exchange ratio is too generous.
C28: Pro-Forma Ownership -Target | E28: =Merger_Model!$E$53/Merger_Model!G130 -> 0.3971389

Sheet Value_Creation
B2: Value Creation Analysis — MIDS / CFFS Combined Entity
B3: ($ in millions, except per-share and per-unit data)
B4: Treats the combined company as a new, larger comparable and asks what it would be worth if the market re-rated it toward the multiples that larger, more diversified industrial platforms command.
B5: 1. REFERENCE MULTIPLES
C7: Company | D7: Ticker | E7: Share Price | F7: Diluted Shares | G7: Equity Value | H7: Enterprise Value | I7: FY26E EBITDA | J7: TEV / FY26E EBITDA
C8: Standalone Entities
C9: Meridian Industrial Supply, Inc. | D9: MIDS | E9: =Acquirer!$E$11 -> 34.5 | F9: =Acquirer!$E$15 -> 118.7058 | G9: =E9*F9 -> 4095.35 | H9: =G9-Acquirer!G116+Acquirer!G135 -> 4961.5359 | I9: =Acquirer!G192 -> 675.99633 | J9: =H9/I9 -> 7.3395901
C10: Calder Fluid & Flow Systems, Inc. | D10: CFFS | E10: =Target!$E$11 -> 37.8 | F10: =Target!$E$15 -> 55.593651 | G10: =E10*F10 -> 2101.44 | H10: =G10-Target!G116+Target!G135 -> 2226.6672 | I10: =Target!G192 -> 347.03477 | J10: =H10/I10 -> 6.4162654
C12: Larger-Cap Diversified Industrial Platforms
C13: Vantar Industrial Holdings | D13: VNTR | E13: 142.6 | F13: 385.4 | G13: =E13*F13 -> 54958.04 | H13: =G13-(1850)+(4200) -> 57308.04 | I13: 4980 | J13: =H13/I13 -> 11.507639 | L13: Both trade at a premium to Meridian on scale, end-market diversification and margin. Whether the combined company earns that premium is the whole question.
C14: Coventree Global Technologies | D14: CVGT | E14: 268.35 | F14: 96.8 | G14: =E14*F14 -> 25976.28 | H14: =G14-(720)+(2900) -> 28156.28 | I14: 2270 | J14: =H14/I14 -> 12.403648
C15: Average of Larger-Cap Platforms | J15: =AVERAGE(J13:J14) -> 11.955643
B17: 2. IMPLIED VALUE OF THE COMBINED ENTITY (FY26E)
C19: Acquirer FY26E EBITDA | E19: =Acquirer!G192 -> 675.99633
C20: (+) Target FY26E EBITDA | E20: =Target!G192 -> 347.03477
C21: (+) Synergies, Net of Costs to Achieve | E21: =Synergies!G40 -> 3.2059251 | L21: Pre-tax synergies less the costs to achieve — in Year 1 the costs still outweigh the savings, which is why the early-year figure is small or negative.
C22: Combined FY26E EBITDA | E22: =SUM(E19:E21) -> 1026.237
C24: Applied TEV / EBITDA Multiple | E24: =$J$15 -> 11.955643
C25: Implied Combined Enterprise Value | E25: =E22*E24 -> 12269.324
C26: (+) Combined Cash at FY26E | E26: =Merger_Model!G170 -> 834.92069
C27: (-) Combined Debt at FY26E | E27: =-Merger_Model!G175 -> -1871.4
C28: Implied Combined Equity Value | E28: =E25+E26+E27 -> 11232.844
C29: Pro-Forma Diluted Shares | E29: =Merger_Model!G130 -> 196.90406
C30: Implied Share Price | E30: =E28/E29 -> 57.047297
C31: Acquirer Share Price Prior to the Transaction | E31: =Acquirer!E11 -> 34.5
C33: Per-Share Value Created / (Destroyed) | E33: =E30-E31 -> 22.547297 | L33: This is a RE-RATING result, not purely a synergy result. It only materialises if the market awards the combined company large-cap multiples.
C34: % Value Created / (Destroyed) | E34: =E33/E31 -> 0.65354484
C35: LIKE-FOR-LIKE TEST — FY28E (Year 3), holding Meridian's OWN multiple constant
C36: Meridian standalone FY28E implied price per share | E36: =(Acquirer!I192*Value_Creation!J9-Acquirer!I135+Acquirer!I116)/Acquirer!E15 -> 45.108283 | L36: Both sides are valued in the SAME year at the SAME multiple, so the only difference between them is the synergies net of the shares issued to pay for Calder.
C37: Combined entity FY28E implied price per share | E37: =(Merger_Model!I179*Value_Creation!J9-Merger_Model!I175+Merger_Model!I170)/Merger_Model!I130 -> 48.755592
C38: Per-share value created, synergies only (no re-rating) | E38: =E37-E36 -> 3.6473091 | L38: This is the honest, synergy-only answer and the number to lead with in front of a sceptical board. The headline figure above additionally requires the market to re-rate the combined company toward large-cap multiples — something the acquirer does not control.
C39: % value created, synergies only | E39: =E38/E36 -> 0.08085675
B42: 3. SENSITIVITIES — PER-SHARE VALUE CREATED
C44: Grid A — Combined FY26E TEV / EBITDA Multiple (columns) vs. Exchange Ratio (rows) | L44: Paying a higher exchange ratio hands more of the combined company to Calder's holders, so value created falls as you move down the rows.
E46: =E33 -> 22.547297 | F46: 8 | G46: 9.5 | H46: 11 | I46: 12.5 | J46: 14
E47: 1.25 | F47: =($E$22*F$46+($E$26+$E$27))/(Acquirer!$E$15+Value_Creation!$E47*Merger_Model!$E$19)-Value_Creation!$E$31 -> 3.5500798 | G47: =($E$22*G$46+($E$26+$E$27))/(Acquirer!$E$15+Value_Creation!$E47*Merger_Model!$E$19)-Value_Creation!$E$31 -> 11.71531 | H47: =($E$22*H$46+($E$26+$E$27))/(Acquirer!$E$15+Value_Creation!$E47*Merger_Model!$E$19)-Value_Creation!$E$31 -> 19.88054 | I47: =($E$22*I$46+($E$26+$E$27))/(Acquirer!$E$15+Value_Creation!$E47*Merger_Model!$E$19)-Value_Creation!$E$31 -> 28.045771 | J47: =($E$22*J$46+($E$26+$E$27))/(Acquirer!$E$15+Value_Creation!$E47*Merger_Model!$E$19)-Value_Creation!$E$31 -> 36.211001
C48: Exchange Ratio | E48: 1.3 | F48: =($E$22*F$46+($E$26+$E$27))/(Acquirer!$E$15+Value_Creation!$E48*Merger_Model!$E$19)-Value_Creation!$E$31 -> 2.994639 | G48: =($E$22*G$46+($E$26+$E$27))/(Acquirer!$E$15+Value_Creation!$E48*Merger_Model!$E$19)-Value_Creation!$E$31 -> 11.040676 | H48: =($E$22*H$46+($E$26+$E$27))/(Acquirer!$E$15+Value_Creation!$E48*Merger_Model!$E$19)-Value_Creation!$E$31 -> 19.086714 | I48: =($E$22*I$46+($E$26+$E$27))/(Acquirer!$E$15+Value_Creation!$E48*Merger_Model!$E$19)-Value_Creation!$E$31 -> 27.132751 | J48: =($E$22*J$46+($E$26+$E$27))/(Acquirer!$E$15+Value_Creation!$E48*Merger_Model!$E$19)-Value_Creation!$E$31 -> 35.178788
E49: 1.35 | F49: =($E$22*F$46+($E$26+$E$27))/(Acquirer!$E$15+Value_Creation!$E49*Merger_Model!$E$19)-Value_Creation!$E$31 -> 2.4551812 | G49: =($E$22*G$46+($E$26+$E$27))/(Acquirer!$E$15+Value_Creation!$E49*Merger_Model!$E$19)-Value_Creation!$E$31 -> 10.385455 | H49: =($E$22*H$46+($E$26+$E$27))/(Acquirer!$E$15+Value_Creation!$E49*Merger_Model!$E$19)-Value_Creation!$E$31 -> 18.31573 | I49: =($E$22*I$46+($E$26+$E$27))/(Acquirer!$E$15+Value_Creation!$E49*Merger_Model!$E$19)-Value_Creation!$E$31 -> 26.246004 | J49: =($E$22*J$46+($E$26+$E$27))/(Acquirer!$E$15+Value_Creation!$E49*Merger_Model!$E$19)-Value_Creation!$E$31 -> 34.176278
E50: 1.4 | F50: =($E$22*F$46+($E$26+$E$27))/(Acquirer!$E$15+Value_Creation!$E50*Merger_Model!$E$19)-Value_Creation!$E$31 -> 1.9310262 | G50: =($E$22*G$46+($E$26+$E$27))/(Acquirer!$E$15+Value_Creation!$E50*Merger_Model!$E$19)-Value_Creation!$E$31 -> 9.7488211 | H50: =($E$22*H$46+($E$26+$E$27))/(Acquirer!$E$15+Value_Creation!$E50*Merger_Model!$E$19)-Value_Creation!$E$31 -> 17.566616 | I50: =($E$22*I$46+($E$26+$E$27))/(Acquirer!$E$15+Value_Creation!$E50*Merger_Model!$E$19)-Value_Creation!$E$31 -> 25.384411 | J50: =($E$22*J$46+($E$26+$E$27))/(Acquirer!$E$15+Value_Creation!$E50*Merger_Model!$E$19)-Value_Creation!$E$31 -> 33.202206
E51: 1.45 | F51: =($E$22*F$46+($E$26+$E$27))/(Acquirer!$E$15+Value_Creation!$E51*Merger_Model!$E$19)-Value_Creation!$E$31 -> 1.421532 | G51: =($E$22*G$46+($E$26+$E$27))/(Acquirer!$E$15+Value_Creation!$E51*Merger_Model!$E$19)-Value_Creation!$E$31 -> 9.1299937 | H51: =($E$22*H$46+($E$26+$E$27))/(Acquirer!$E$15+Value_Creation!$E51*Merger_Model!$E$19)-Value_Creation!$E$31 -> 16.838455 | I51: =($E$22*I$46+($E$26+$E$27))/(Acquirer!$E$15+Value_Creation!$E51*Merger_Model!$E$19)-Value_Creation!$E$31 -> 24.546917 | J51: =($E$22*J$46+($E$26+$E$27))/(Acquirer!$E$15+Value_Creation!$E51*Merger_Model!$E$19)-Value_Creation!$E$31 -> 32.255379
E52: 1.5 | F52: =($E$22*F$46+($E$26+$E$27))/(Acquirer!$E$15+Value_Creation!$E52*Merger_Model!$E$19)-Value_Creation!$E$31 -> 0.92609198 | G52: =($E$22*G$46+($E$26+$E$27))/(Acquirer!$E$15+Value_Creation!$E52*Merger_Model!$E$19)-Value_Creation!$E$31 -> 8.5282364 | H52: =($E$22*H$46+($E$26+$E$27))/(Acquirer!$E$15+Value_Creation!$E52*Merger_Model!$E$19)-Value_Creation!$E$31 -> 16.130381 | I52: =($E$22*I$46+($E$26+$E$27))/(Acquirer!$E$15+Value_Creation!$E52*Merger_Model!$E$19)-Value_Creation!$E$31 -> 23.732525 | J52: =($E$22*J$46+($E$26+$E$27))/(Acquirer!$E$15+Value_Creation!$E52*Merger_Model!$E$19)-Value_Creation!$E$31 -> 31.334669
C53: Grid B — Combined FY26E TEV / EBITDA Multiple (columns) vs. Synergy Adjustment (rows) | L53: Replaces the modelled Year 1 synergy with a flat dollar assumption, so a reviewer can see how much of the value creation is synergy versus re-rating.
E55: =E33 -> 22.547297 | F55: 8 | G55: 9.5 | H55: 11 | I55: 12.5 | J55: 14
E56: 100 | F56: =(($E$22-$E$21+$E56)*F$55+($E$26+$E$27))/$E$29-$E$31 -> 5.8636653 | G56: =(($E$22-$E$21+$E56)*G$55+($E$26+$E$27))/$E$29-$E$31 -> 14.41883 | H56: =(($E$22-$E$21+$E56)*H$55+($E$26+$E$27))/$E$29-$E$31 -> 22.973995 | I56: =(($E$22-$E$21+$E56)*I$55+($E$26+$E$27))/$E$29-$E$31 -> 31.529159 | J56: =(($E$22-$E$21+$E56)*J$55+($E$26+$E$27))/$E$29-$E$31 -> 40.084324
C57: Synergy Adjustment ($M) | E57: 75 | F57: =(($E$22-$E$21+$E57)*F$55+($E$26+$E$27))/$E$29-$E$31 -> 4.8479422 | G57: =(($E$22-$E$21+$E57)*G$55+($E$26+$E$27))/$E$29-$E$31 -> 13.212659 | H57: =(($E$22-$E$21+$E57)*H$55+($E$26+$E$27))/$E$29-$E$31 -> 21.577376 | I57: =(($E$22-$E$21+$E57)*I$55+($E$26+$E$27))/$E$29-$E$31 -> 29.942092 | J57: =(($E$22-$E$21+$E57)*J$55+($E$26+$E$27))/$E$29-$E$31 -> 38.306809
E58: 50 | F58: =(($E$22-$E$21+$E58)*F$55+($E$26+$E$27))/$E$29-$E$31 -> 3.8322191 | G58: =(($E$22-$E$21+$E58)*G$55+($E$26+$E$27))/$E$29-$E$31 -> 12.006488 | H58: =(($E$22-$E$21+$E58)*H$55+($E$26+$E$27))/$E$29-$E$31 -> 20.180756 | I58: =(($E$22-$E$21+$E58)*I$55+($E$26+$E$27))/$E$29-$E$31 -> 28.355025 | J58: =(($E$22-$E$21+$E58)*J$55+($E$26+$E$27))/$E$29-$E$31 -> 36.529293
E59: 25 | F59: =(($E$22-$E$21+$E59)*F$55+($E$26+$E$27))/$E$29-$E$31 -> 2.816496 | G59: =(($E$22-$E$21+$E59)*G$55+($E$26+$E$27))/$E$29-$E$31 -> 10.800316 | H59: =(($E$22-$E$21+$E59)*H$55+($E$26+$E$27))/$E$29-$E$31 -> 18.784137 | I59: =(($E$22-$E$21+$E59)*I$55+($E$26+$E$27))/$E$29-$E$31 -> 26.767957 | J59: =(($E$22-$E$21+$E59)*J$55+($E$26+$E$27))/$E$29-$E$31 -> 34.751778
E60: 0 | F60: =(($E$22-$E$21+$E60)*F$55+($E$26+$E$27))/$E$29-$E$31 -> 1.8007729 | G60: =(($E$22-$E$21+$E60)*G$55+($E$26+$E$27))/$E$29-$E$31 -> 9.5941453 | H60: =(($E$22-$E$21+$E60)*H$55+($E$26+$E$27))/$E$29-$E$31 -> 17.387518 | I60: =(($E$22-$E$21+$E60)*I$55+($E$26+$E$27))/$E$29-$E$31 -> 25.18089 | J60: =(($E$22-$E$21+$E60)*J$55+($E$26+$E$27))/$E$29-$E$31 -> 32.974263
E61: -25 | F61: =(($E$22-$E$21+$E61)*F$55+($E$26+$E$27))/$E$29-$E$31 -> 0.78504982 | G61: =(($E$22-$E$21+$E61)*G$55+($E$26+$E$27))/$E$29-$E$31 -> 8.3879741 | H61: =(($E$22-$E$21+$E61)*H$55+($E$26+$E$27))/$E$29-$E$31 -> 15.990898 | I61: =(($E$22-$E$21+$E61)*I$55+($E$26+$E$27))/$E$29-$E$31 -> 23.593823 | J61: =(($E$22-$E$21+$E61)*J$55+($E$26+$E$27))/$E$29-$E$31 -> 31.196747
E62: -50 | F62: =(($E$22-$E$21+$E62)*F$55+($E$26+$E$27))/$E$29-$E$31 -> -0.23067328 | G62: =(($E$22-$E$21+$E62)*G$55+($E$26+$E$27))/$E$29-$E$31 -> 7.181803 | H62: =(($E$22-$E$21+$E62)*H$55+($E$26+$E$27))/$E$29-$E$31 -> 14.594279 | I62: =(($E$22-$E$21+$E62)*I$55+($E$26+$E$27))/$E$29-$E$31 -> 22.006755 | J62: =(($E$22-$E$21+$E62)*J$55+($E$26+$E$27))/$E$29-$E$31 -> 29.419232
