Workbook

Sheet Cover
B2: COLLINS FOODS LIMITED (ASX: CKF)
B3: Discounted Cash Flow Valuation — FY27E to FY35E
B5: Prepared by | C5: Prasad Lambor
B6: Valuation date | C6: 8 August 2026
B7: Base year | C7: FY26A — 53 weeks ended 3 May 2026
B8: Currency | C8: A$ millions unless stated
B9: Primary source | C9: CKF FY26 Results Presentation, released 30 June 2026
B11: PURPOSE
B12: An enterprise discounted cash flow of Collins Foods, built bottom-up from restaurant count and average unit volume for each of the three operating geographies. Designed to be interrogated: every assumption sits in a labelled cell with its source, and the two lease-accounting treatments are computed in parallel and reconciled.
B17: COLOUR CONVENTION
B18: Blue text | C18: Hardcoded input or scenario lever — this is what you change
B19: Black text | C19: Formula calculated on this sheet — do not overwrite
B20: Green text | C20: Link to another sheet in this workbook
B21: Yellow fill | C21: Key assumption or a cell needing your judgement or market data
B22: Red text | C22: Warning or a figure requiring verification
B24: SHEET INDEX
B25: Control | C25: Switches, valuation summary and integrity checks. Start here.
B26: Assumptions | C26: Every forecast driver, as three scenario blocks plus the live selected case.
B27: Historicals | C27: FY23A–FY26A reported actuals, with the source of every figure and the AASB 16 bridge.
B28: Model | C28: The engine: drivers to revenue to EBITDA to EBIT to NOPAT to free cash flow, on both lease bases.
B29: WACC | C29: Cost of equity, cost of debt and capital structure — one WACC per lease basis.
B30: DCF | C30: Discounting, terminal value, enterprise value, equity bridge and the pre/post reconciliation.
B31: Sensitivity | C31: Live WACC versus growth and WACC versus exit multiple grids.
B32: Comps | C32: Trading comparables template and football field. Market data to be populated.
B33: Notes & Audit | C33: Source mapping for every hardcoded number, and the reasoning behind each convention.
B36: IMPORTANT | C36: Educational and illustrative only. Not investment advice and not a professional valuation. Forecasts are the author's own and are not company guidance.

Sheet Control
B2: CONTROL PANEL
C3: Change the switches and the whole model re-runs. Start here.
C5: SWITCHES
C6: Switch | D6: Setting | E6: Reads as | F6: Options
C7: Scenario | D7: 3 | E7: =CHOOSE($D$7,"Base","Upside","Downside") -> Downside | F7: 1 = Base | 2 = Upside | 3 = Downside
C8: Kwench by KFC initiative | D8: 1 | E8: =CHOOSE($D$8,"Included","Excluded") -> Included | F8: 1 = Include the uplift | 2 = Strip it out, to isolate what the initiative is worth
C9: Terminal value method | D9: 1 | E9: =CHOOSE($D$9,"Gordon growth","Exit multiple") -> Gordon growth | F9: 1 = Gordon growth perpetuity | 2 = Exit EV/EBITDA multiple
C10: Discounting convention | D10: 1 | E10: =CHOOSE($D$10,"Mid-year","Year-end") -> Mid-year | F10: 1 = Mid-year | 2 = Year-end
C12: VALUATION SUMMARY
C13: Output | D13: Value | F13: Comment
C14: Enterprise value (A$m) | D14: =DCF!E41 -> 955.51948 | F14: PV of forecast cash flows plus PV of terminal value
C15: Net debt deducted (A$m) | D15: =DCF!E44 -> -119.6 | F15: Includes lease liabilities only on a post-AASB 16 basis
C16: Equity value (A$m) | D16: =DCF!E45 -> 835.91948 | F16: Enterprise value less net debt
C17: Shares on issue (m) | D17: =DCF!E46 -> 118.07692 | F17: Underlying NPAT divided by reported basic EPS
C18: Value per share (A$) | D18: =DCF!E47 -> 7.0794483 | F18: The headline output
C19: Current share price (A$) | D19: =DCF!E48 -> 8.24 | F19: Early August 2026
C20: Premium / (discount) to market | D20: =DCF!E49 -> -0.14084365 | F20: Positive means the model says CKF is undervalued
C21: Implied FY27E EV/EBITDA | D21: =DCF!E52 -> 5.942252 | F21: Sense-check against the trading comparables
C22: Terminal value as % of EV | D22: =DCF!E53 -> 0.58249958 | F22: How much of the answer is the perpetuity assumption
C24: INTEGRITY CHECKS
C25: Check | D25: Result | E25: Status | F25: What it proves
C26: FY26A modelled revenue less reported | D26: =Model!E40-Historicals!H6 -> 0 | E26: =IF(ABS(D26)<0.5,"OK","CHECK") -> OK | F26: The driver build reproduces the actual year — the wiring is right
C27: FY26A modelled EBITDA less reported | D27: =Model!E45-Historicals!H7 -> 0.0009 | E27: =IF(ABS(D27)<0.5,"OK","CHECK") -> OK | F27: Margin and cost assumptions rebuild reported EBITDA
C28: Segment revenue sums to group | D28: =Model!E40-Model!E12-Model!E34 -> 0 | E28: =IF(ABS(D28)<0.1,"OK","CHECK") -> OK | F28: No segment double-counted or dropped
C29: AASB 16 bridge closes | D29: =Historicals!H69 -> 6.9988599 | E29: =IF(AND(D29>0,D29<15),"OK","CHECK") -> OK | F29: Rent, ROU depreciation and lease interest reconcile between the two bases
C30: Scenario switch in valid range | D30: =D7 -> 3 | E30: =IF(AND(D30>=1,D30<=3),"OK","CHECK") -> OK | F30: CHOOSE() returns an error outside 1 to 3
C31: WACC less terminal growth | D31: =DCF!E9-DCF!E17 -> 0.074350867 | E31: =IF(D31>0.005,"OK","CHECK") -> OK | F31: Gordon growth explodes as growth approaches WACC
C32: FY27E capex versus $80-100m guidance | D32: =Model!F61 -> 86.644204 | E32: =IF($D$7<>1,"n/a",IF(AND(D32>=75,D32<=105),"OK","CHECK")) -> n/a | F32: Base case only — the Upside deliberately builds more restaurants than guidance, so it should spend more
C33: Terminal value share of EV | D33: =DCF!E53 -> 0.58249958 | E33: =IF(D33<0.75,"OK",IF(D33<0.85,"NOTE","HIGH")) -> OK | F33: NOTE is normal for a stable business on a 5-year horizon; validate it with the implied exit multiple below
C34: Lease liabilities excluded from bridge | D34: =DCF!E43 -> 0 | E34: =IF(D34=0,"OK","CHECK") -> OK | F34: Must be zero, because rent is still an operating cost in the cash flows
C35: Implied Gordon exit multiple is sane | D35: =DCF!E37 -> 6.2388065 | E35: =IF(AND(D35>3,D35<14),"OK","CHECK") -> OK | F35: A Gordon terminal value implying a wild multiple means bad inputs
C36: Europe split sums to reported revenue | D36: =Historicals!H46 -> 0 | E36: =IF(ABS(D36)<0.1,"OK","CHECK") -> OK | F36: Germany and Netherlands are solved independently, so this is a real cross-check
C37: FY26A D&A per roll-forward vs reported | D37: ='Capex & PPE'!E51+(Historicals!H14-Historicals!H67) -> 0 | E37: =IF(ABS(D37)<0.1,"OK","CHECK") -> OK | F37: The fixed asset roll-forward reproduces reported depreciation and amortisation
C38: FY26A closing gross debt vs reported | D38: ='Debt & Leases'!E17-Historicals!H52 -> 0 | E38: =IF(ABS(D38)<0.1,"OK","CHECK") -> OK | F38: Debt schedule anchors to the reported balance sheet
C39: FY26A closing lease liability vs reported | D39: ='Debt & Leases'!E42-Historicals!H54 -> 0 | E39: =IF(ABS(D39)<0.1,"OK","CHECK") -> OK | F39: Lease roll-forward anchors to the reported balance sheet
C40: Cash never falls below the minimum | D40: =MIN('Debt & Leases'!F28:N28)-'Debt & Leases'!E10 -> 0 | E40: =IF(D40>=-0.1,"OK","CHECK") -> OK | F40: The plan is fundable — no year requires cash the company does not have
C41: Covenant never breached | D41: =MAX('Debt & Leases'!F33:N33) -> 1.0849832 | E41: =IF(D41<'Debt & Leases'!E11,"OK","BREACH") -> OK | F41: Net leverage stays inside the covenant across the forecast

Sheet Assumptions
B2: FORECAST ASSUMPTIONS
C5: BASE CASE
C6: Driver | D6: Unit | E6: FY27E | F6: FY28E | G6: FY29E | H6: FY30E | I6: FY31E | J6: FY32E | K6: FY33E | L6: FY34E | M6: FY35E | O6: Basis and source
C7: KFC AUSTRALIA
C8: Net new restaurants | D8: no. | E8: 8 | F8: 8 | G8: 8 | H8: 8 | I8: 8 | J8: 7 | K8: 6 | L8: 5 | M8: 4 | O8: Management guides 7-10 new Australian restaurants in FY27 (p.35). FY26 actual: 8 opened, 1 closed, 1 relocated.
C9: Same store sales growth | D9: % | E9: 0.035 | F9: 0.03 | G9: 0.0275 | H9: 0.025 | I9: 0.025 | J9: 0.025 | K9: 0.025 | L9: 0.025 | M9: 0.025 | O9: FY26 actual +2.7%. First 8 weeks of FY27 running at +4.0% (p.35). Base fades toward long-run food inflation plus modest traffic growth.
C10: Kwench incremental sales uplift | D10: % | E10: 0.015 | F10: 0.01 | G10: 0.0025 | H10: 0 | I10: 0 | J10: 0 | K10: 0 | L10: 0 | M10: 0 | O10: Management cites an initial 2-3% sales increase, with 80% of the network rolled out by April 2027 and 100% by mid-2027 (p.31). Applied on top of same store sales and phased over the rollout.
C11: Restaurant-level EBITDA margin | D11: % | E11: 0.21 | F11: 0.21 | G11: 0.211 | H11: 0.211 | I11: 0.212 | J11: 0.212 | K11: 0.212 | L11: 0.212 | M11: 0.212 | O11: FY26 actual 21.0%, down 26bps on delivery channel mix and value investment. Base assumes stabilisation; downside assumes Australian labour inflation is not offset by productivity.
C12: Segment G&A as % of revenue | D12: % | E12: 0.0195 | F12: 0.0195 | G12: 0.0192 | H12: 0.019 | I12: 0.019 | J12: 0.019 | K12: 0.019 | L12: 0.019 | M12: 0.019 | O12: FY26 actual 1.88% (restaurant EBITDA $260.5m less segment EBITDA $237.1m = $23.4m). Steps up in FY27 for the $2m+ training investment flagged on p.28.
C13: KFC GERMANY
C14: Net new restaurants | D14: no. | E14: 15 | F14: 10 | G14: 13 | H14: 16 | I14: 16 | J14: 10 | K14: 7 | L14: 5 | M14: 3 | O14: Base follows management's base-case network chart (p.33): 25 restaurants at FY26 post-Munich, then 32 / 42 / 55 / 71 through FY30. Upside follows the upper range 36 / 58 / 86 / 115. FY27 includes the 8 acquired Munich restaurants.
C15: of which acquired rather than built | D15: no. | E15: 8 | F15: 0 | G15: 0 | H15: 0 | I15: 0 | J15: 0 | K15: 0 | L15: 0 | M15: 0 | O15: The Munich acquisition of 8 restaurants completed 1 June 2026. These are bought, not built, so they must be excluded from new-restaurant capex and charged instead as acquisition consideration — otherwise the model double-counts the cost of the same 8 restaurants.
C16: Same store sales growth | D16: % | E16: -0.02 | F16: 0.02 | G16: 0.025 | H16: 0.025 | I16: 0.025 | J16: 0.025 | K16: 0.025 | L16: 0.025 | M16: 0.025 | O16: FY26 actual +3.7%. First 8 weeks of FY27 at -7.2% on a prolonged heatwave, weaker limited-time offers and soft consumer confidence (p.35). Base assumes a part-year drag then recovery.
C17: KFC NETHERLANDS
C18: Net new restaurants | D18: no. | E18: 1 | F18: 1 | G18: 1 | H18: 1 | I18: 1 | J18: 1 | K18: 1 | L18: 0 | M18: 0 | O18: A mature network — FY26 added one net restaurant. No expansion programme is disclosed.
C19: Same store sales growth | D19: % | E19: -0.03 | F19: 0.01 | G19: 0.015 | H19: 0.02 | I19: 0.02 | J19: 0.02 | K19: 0.02 | L19: 0.02 | M19: 0.02 | O19: FY26 actual 0.0%. First 8 weeks of FY27 at -7.8% (p.35). The Corporate Franchise Agreement has been extended to 31 December 2029 and Yum! resumes marketing responsibility from 1 January 2027 (p.23).
C20: KFC EUROPE — SHARED
C21: Restaurant-level EBITDA margin | D21: % | E21: 0.19 | F21: 0.193 | G21: 0.195 | H21: 0.198 | I21: 0.2 | J21: 0.201 | K21: 0.202 | L21: 0.202 | M21: 0.202 | O21: FY26 actual 19.3%, down 53bps on avian-influenza poultry costs which management expects to dissipate over FY27 (p.35). Modelled at the Europe level because CKF does not disclose margin by country.
C22: Segment G&A as % of revenue | D22: % | E22: 0.069 | F22: 0.067 | G22: 0.065 | H22: 0.063 | I22: 0.062 | J22: 0.06 | K22: 0.058 | L22: 0.057 | M22: 0.056 | O22: FY26 actual 6.52% (restaurant EBITDA $67.8m less segment EBITDA $44.9m = $22.9m). FY27 absorbs the $3m incremental German G&A investment flagged on p.33, then leverages as the network scales.
C23: GROUP COSTS, CAPITAL AND WORKING CAPITAL
C24: Unallocated corporate costs as % of revenue | D24: % | E24: 0.0235 | F24: 0.0235 | G24: 0.0233 | H24: 0.023 | I24: 0.023 | J24: 0.0228 | K24: 0.0226 | L24: 0.0225 | M24: 0.0225 | O24: FY26 actual 2.35%: segment EBITDA of $237.1m + $44.9m = $282.0m less reported group EBITDA of $244.5m = $37.5m. Not separately disclosed — derived as the residual.
C25: Rent expense as % of revenue | D25: % | E25: 0.0526 | F25: 0.0526 | G25: 0.0526 | H25: 0.0526 | I25: 0.0526 | J25: 0.0526 | K25: 0.0526 | L25: 0.0526 | M25: 0.0526 | O25: FY26 implied 5.26% ($83.7m of rent, being post-AASB 16 EBITDA less pre-AASB 16 EBITDA). Only used on the pre-AASB 16 basis.
C26: Maintenance and remodel capex as % of revenue | D26: % | E26: 0.019 | F26: 0.021 | G26: 0.022 | H26: 0.022 | I26: 0.022 | J26: 0.022 | K26: 0.022 | L26: 0.022 | M26: 0.022 | O26: FY26 actual: $15.3m asset capital maintenance + $16.8m remodels + $6.0m digital and sustainability = $38.1m, or 2.39% of revenue (p.9). FY27 is lower because spend is diverted to Kwench.
C27: Kwench and other project capex | D27: A$m | E27: 35 | F27: 10 | G27: 0 | H27: 0 | I27: 0 | J27: 0 | K27: 0 | L27: 0 | M27: 0 | O27: Management guides Kwench capex of $35m in FY27 and $10m in FY28 (p.31). Modelled as discrete project spend rather than a percentage of revenue.
C28: New restaurant capex — Australia | D28: A$m/store | E28: 1.8 | F28: 1.85 | G28: 1.9 | H28: 1.95 | I28: 2 | J28: 2.05 | K28: 2.1 | L28: 2.16 | M28: 2.21 | O28: Derived from FY26 new restaurant capex of $13.8m (p.9) spread across Australian and German openings, escalated for build cost inflation.
C29: New restaurant capex — Germany | D29: A$m/store | E29: 2.2 | F29: 2.25 | G29: 2.3 | H29: 2.35 | I29: 2.4 | J29: 2.46 | K29: 2.52 | L29: 2.58 | M29: 2.65 | O29: Higher than Australia. FY27 German capex is guided at approximately $20m for around 7 new restaurants plus pipeline development (p.33).
C30: New restaurant capex — Netherlands | D30: A$m/store | E30: 2 | F30: 2.05 | G30: 2.1 | H30: 2.15 | I30: 2.2 | J30: 2.26 | K30: 2.31 | L30: 2.37 | M30: 2.43 | O30: Assumed between the Australian and German build cost. Not separately disclosed.
C31: Net working capital as % of revenue | D31: % | E31: -0.06 | F31: -0.06 | G31: -0.06 | H31: -0.06 | I31: -0.06 | J31: -0.06 | K31: -0.06 | L31: -0.06 | M31: -0.06 | O31: NEGATIVE by design: quick service restaurants collect cash instantly and pay suppliers on terms, so growth releases cash. REFINE THIS from the FY26 Annual Report receivables, inventory and payables notes — the results presentation does not give the detail.
C32: Effective tax rate | D32: % | E32: 0.3 | F32: 0.3 | G32: 0.3 | H32: 0.3 | I32: 0.3 | J32: 0.3 | K32: 0.3 | L32: 0.3 | M32: 0.3 | O32: Australian statutory rate. The FY26 underlying effective rate was 29.9% ($26.2m tax on $87.7m profit before tax, p.8), so the statutory rate is a fair proxy despite Dutch and German earnings.
C33: TERMINAL ASSUMPTIONS
C34: Terminal growth rate | D34: % | E34: 0.025 | O34: Long-run nominal growth. The RBA target band midpoint is 2.5%, so this assumes no real growth in perpetuity — appropriate for a mature franchisee operating in defined territories.
C35: Terminal exit EV/EBITDA multiple | D35: x | E35: 7 | O35: Applied to terminal year EBITDA on the active lease basis. CKF currently trades on roughly 6.8x FY26 pre-AASB 16 EBITDA. Populate the Comps sheet to sharpen this.
C38: UPSIDE CASE
C39: Driver | D39: Unit | E39: FY27E | F39: FY28E | G39: FY29E | H39: FY30E | I39: FY31E | J39: FY32E | K39: FY33E | L39: FY34E | M39: FY35E | O39: Basis and source
C40: KFC AUSTRALIA
C41: Net new restaurants | D41: no. | E41: 10 | F41: 10 | G41: 10 | H41: 10 | I41: 10 | J41: 9 | K41: 8 | L41: 7 | M41: 6
C42: Same store sales growth | D42: % | E42: 0.04 | F42: 0.035 | G42: 0.0325 | H42: 0.03 | I42: 0.03 | J42: 0.03 | K42: 0.03 | L42: 0.028 | M42: 0.028
C43: Kwench incremental sales uplift | D43: % | E43: 0.025 | F43: 0.015 | G43: 0.005 | H43: 0 | I43: 0 | J43: 0 | K43: 0 | L43: 0 | M43: 0
C44: Restaurant-level EBITDA margin | D44: % | E44: 0.213 | F44: 0.215 | G44: 0.216 | H44: 0.217 | I44: 0.218 | J44: 0.218 | K44: 0.218 | L44: 0.218 | M44: 0.218
C45: Segment G&A as % of revenue | D45: % | E45: 0.0192 | F45: 0.019 | G45: 0.0188 | H45: 0.0185 | I45: 0.0185 | J45: 0.0185 | K45: 0.0185 | L45: 0.0185 | M45: 0.0185
C46: KFC GERMANY
C47: Net new restaurants | D47: no. | E47: 19 | F47: 22 | G47: 28 | H47: 29 | I47: 25 | J47: 20 | K47: 15 | L47: 10 | M47: 6
C48: of which acquired rather than built | D48: no. | E48: 8 | F48: 0 | G48: 0 | H48: 0 | I48: 0 | J48: 0 | K48: 0 | L48: 0 | M48: 0
C49: Same store sales growth | D49: % | E49: 0 | F49: 0.03 | G49: 0.03 | H49: 0.03 | I49: 0.03 | J49: 0.03 | K49: 0.028 | L49: 0.028 | M49: 0.028
C50: KFC NETHERLANDS
C51: Net new restaurants | D51: no. | E51: 2 | F51: 2 | G51: 2 | H51: 2 | I51: 2 | J51: 2 | K51: 1 | L51: 1 | M51: 1
C52: Same store sales growth | D52: % | E52: -0.01 | F52: 0.02 | G52: 0.025 | H52: 0.025 | I52: 0.025 | J52: 0.025 | K52: 0.025 | L52: 0.025 | M52: 0.025
C53: KFC EUROPE — SHARED
C54: Restaurant-level EBITDA margin | D54: % | E54: 0.195 | F54: 0.2 | G54: 0.203 | H54: 0.205 | I54: 0.208 | J54: 0.21 | K54: 0.21 | L54: 0.21 | M54: 0.21
C55: Segment G&A as % of revenue | D55: % | E55: 0.068 | F55: 0.065 | G55: 0.062 | H55: 0.06 | I55: 0.059 | J55: 0.057 | K55: 0.055 | L55: 0.054 | M55: 0.053
C56: GROUP COSTS, CAPITAL AND WORKING CAPITAL
C57: Unallocated corporate costs as % of revenue | D57: % | E57: 0.0232 | F57: 0.023 | G57: 0.0228 | H57: 0.0225 | I57: 0.0225 | J57: 0.0222 | K57: 0.022 | L57: 0.0218 | M57: 0.0218
C58: Rent expense as % of revenue | D58: % | E58: 0.052 | F58: 0.0518 | G58: 0.0515 | H58: 0.0512 | I58: 0.051 | J58: 0.0508 | K58: 0.0506 | L58: 0.0505 | M58: 0.0505
C59: Maintenance and remodel capex as % of revenue | D59: % | E59: 0.019 | F59: 0.021 | G59: 0.022 | H59: 0.022 | I59: 0.022 | J59: 0.022 | K59: 0.022 | L59: 0.022 | M59: 0.022
C60: Kwench and other project capex | D60: A$m | E60: 35 | F60: 10 | G60: 0 | H60: 0 | I60: 0 | J60: 0 | K60: 0 | L60: 0 | M60: 0
C61: New restaurant capex — Australia | D61: A$m/store | E61: 1.8 | F61: 1.85 | G61: 1.9 | H61: 1.95 | I61: 2 | J61: 2.05 | K61: 2.1 | L61: 2.16 | M61: 2.21
C62: New restaurant capex — Germany | D62: A$m/store | E62: 2.15 | F62: 2.2 | G62: 2.25 | H62: 2.3 | I62: 2.35 | J62: 2.41 | K62: 2.47 | L62: 2.53 | M62: 2.59
C63: New restaurant capex — Netherlands | D63: A$m/store | E63: 2 | F63: 2.05 | G63: 2.1 | H63: 2.15 | I63: 2.2 | J63: 2.26 | K63: 2.31 | L63: 2.37 | M63: 2.43
C64: Net working capital as % of revenue | D64: % | E64: -0.062 | F64: -0.062 | G64: -0.062 | H64: -0.062 | I64: -0.062 | J64: -0.062 | K64: -0.062 | L64: -0.062 | M64: -0.062
C65: Effective tax rate | D65: % | E65: 0.295 | F65: 0.295 | G65: 0.295 | H65: 0.295 | I65: 0.295 | J65: 0.295 | K65: 0.295 | L65: 0.295 | M65: 0.295
C66: TERMINAL ASSUMPTIONS
C67: Terminal growth rate | D67: % | E67: 0.03
C68: Terminal exit EV/EBITDA multiple | D68: x | E68: 8
C71: DOWNSIDE CASE
C72: Driver | D72: Unit | E72: FY27E | F72: FY28E | G72: FY29E | H72: FY30E | I72: FY31E | J72: FY32E | K72: FY33E | L72: FY34E | M72: FY35E | O72: Basis and source
C73: KFC AUSTRALIA
C74: Net new restaurants | D74: no. | E74: 6 | F74: 6 | G74: 6 | H74: 6 | I74: 6 | J74: 5 | K74: 4 | L74: 3 | M74: 3
C75: Same store sales growth | D75: % | E75: 0.025 | F75: 0.02 | G75: 0.02 | H75: 0.02 | I75: 0.02 | J75: 0.02 | K75: 0.02 | L75: 0.02 | M75: 0.02
C76: Kwench incremental sales uplift | D76: % | E76: 0.01 | F76: 0.005 | G76: 0 | H76: 0 | I76: 0 | J76: 0 | K76: 0 | L76: 0 | M76: 0
C77: Restaurant-level EBITDA margin | D77: % | E77: 0.206 | F77: 0.205 | G77: 0.204 | H77: 0.204 | I77: 0.204 | J77: 0.204 | K77: 0.204 | L77: 0.204 | M77: 0.204
C78: Segment G&A as % of revenue | D78: % | E78: 0.02 | F78: 0.02 | G78: 0.0198 | H78: 0.0198 | I78: 0.0198 | J78: 0.0198 | K78: 0.0198 | L78: 0.0198 | M78: 0.0198
C79: KFC GERMANY
C80: Net new restaurants | D80: no. | E80: 11 | F80: 5 | G80: 5 | H80: 5 | I80: 5 | J80: 4 | K80: 3 | L80: 2 | M80: 2
C81: of which acquired rather than built | D81: no. | E81: 8 | F81: 0 | G81: 0 | H81: 0 | I81: 0 | J81: 0 | K81: 0 | L81: 0 | M81: 0
C82: Same store sales growth | D82: % | E82: -0.05 | F82: 0 | G82: 0.01 | H82: 0.015 | I82: 0.015 | J82: 0.015 | K82: 0.015 | L82: 0.015 | M82: 0.015
C83: KFC NETHERLANDS
C84: Net new restaurants | D84: no. | E84: 0 | F84: 0 | G84: 0 | H84: 0 | I84: 0 | J84: 0 | K84: 0 | L84: 0 | M84: 0
C85: Same store sales growth | D85: % | E85: -0.05 | F85: -0.01 | G85: 0.005 | H85: 0.01 | I85: 0.01 | J85: 0.01 | K85: 0.01 | L85: 0.01 | M85: 0.01
C86: KFC EUROPE — SHARED
C87: Restaurant-level EBITDA margin | D87: % | E87: 0.185 | F87: 0.185 | G87: 0.185 | H87: 0.185 | I87: 0.185 | J87: 0.185 | K87: 0.185 | L87: 0.185 | M87: 0.185
C88: Segment G&A as % of revenue | D88: % | E88: 0.071 | F88: 0.07 | G88: 0.069 | H88: 0.068 | I88: 0.068 | J88: 0.067 | K88: 0.067 | L88: 0.067 | M88: 0.067
C89: GROUP COSTS, CAPITAL AND WORKING CAPITAL
C90: Unallocated corporate costs as % of revenue | D90: % | E90: 0.024 | F90: 0.024 | G90: 0.024 | H90: 0.024 | I90: 0.024 | J90: 0.024 | K90: 0.024 | L90: 0.024 | M90: 0.024
C91: Rent expense as % of revenue | D91: % | E91: 0.0535 | F91: 0.054 | G91: 0.0545 | H91: 0.055 | I91: 0.0555 | J91: 0.056 | K91: 0.0565 | L91: 0.057 | M91: 0.0575
C92: Maintenance and remodel capex as % of revenue | D92: % | E92: 0.02 | F92: 0.022 | G92: 0.023 | H92: 0.023 | I92: 0.023 | J92: 0.023 | K92: 0.023 | L92: 0.023 | M92: 0.023
C93: Kwench and other project capex | D93: A$m | E93: 35 | F93: 12 | G93: 0 | H93: 0 | I93: 0 | J93: 0 | K93: 0 | L93: 0 | M93: 0
C94: New restaurant capex — Australia | D94: A$m/store | E94: 1.9 | F94: 1.95 | G94: 2 | H94: 2.05 | I94: 2.1 | J94: 2.15 | K94: 2.21 | L94: 2.26 | M94: 2.32
C95: New restaurant capex — Germany | D95: A$m/store | E95: 2.4 | F95: 2.45 | G95: 2.5 | H95: 2.55 | I95: 2.6 | J95: 2.67 | K95: 2.73 | L95: 2.8 | M95: 2.87
C96: New restaurant capex — Netherlands | D96: A$m/store | E96: 2.1 | F96: 2.15 | G96: 2.2 | H96: 2.25 | I96: 2.3 | J96: 2.36 | K96: 2.42 | L96: 2.48 | M96: 2.54
C97: Net working capital as % of revenue | D97: % | E97: -0.055 | F97: -0.055 | G97: -0.055 | H97: -0.055 | I97: -0.055 | J97: -0.055 | K97: -0.055 | L97: -0.055 | M97: -0.055
C98: Effective tax rate | D98: % | E98: 0.305 | F98: 0.305 | G98: 0.305 | H98: 0.305 | I98: 0.305 | J98: 0.305 | K98: 0.305 | L98: 0.305 | M98: 0.305
C99: TERMINAL ASSUMPTIONS
C100: Terminal growth rate | D100: % | E100: 0.02
C101: Terminal exit EV/EBITDA multiple | D101: x | E101: 6
C104: LIVE — SELECTED SCENARIO (formulas, do not overwrite)
C105: Driver | D105: Unit | E105: FY27E | F105: FY28E | G105: FY29E | H105: FY30E | I105: FY31E | J105: FY32E | K105: FY33E | L105: FY34E | M105: FY35E | O105: Active scenario:
C106: KFC AUSTRALIA | O106: =Control!E7 -> Downside
C107: Net new restaurants | D107: no. | E107: =CHOOSE(Control!$D$7,E8,E41,E74) -> 6 | F107: =CHOOSE(Control!$D$7,F8,F41,F74) -> 6 | G107: =CHOOSE(Control!$D$7,G8,G41,G74) -> 6 | H107: =CHOOSE(Control!$D$7,H8,H41,H74) -> 6 | I107: =CHOOSE(Control!$D$7,I8,I41,I74) -> 6 | J107: =CHOOSE(Control!$D$7,J8,J41,J74) -> 5 | K107: =CHOOSE(Control!$D$7,K8,K41,K74) -> 4 | L107: =CHOOSE(Control!$D$7,L8,L41,L74) -> 3 | M107: =CHOOSE(Control!$D$7,M8,M41,M74) -> 3
C108: Same store sales growth | D108: % | E108: =CHOOSE(Control!$D$7,E9,E42,E75) -> 0.025 | F108: =CHOOSE(Control!$D$7,F9,F42,F75) -> 0.02 | G108: =CHOOSE(Control!$D$7,G9,G42,G75) -> 0.02 | H108: =CHOOSE(Control!$D$7,H9,H42,H75) -> 0.02 | I108: =CHOOSE(Control!$D$7,I9,I42,I75) -> 0.02 | J108: =CHOOSE(Control!$D$7,J9,J42,J75) -> 0.02 | K108: =CHOOSE(Control!$D$7,K9,K42,K75) -> 0.02 | L108: =CHOOSE(Control!$D$7,L9,L42,L75) -> 0.02 | M108: =CHOOSE(Control!$D$7,M9,M42,M75) -> 0.02
C109: Kwench incremental sales uplift | D109: % | E109: =CHOOSE(Control!$D$7,E10,E43,E76) -> 0.01 | F109: =CHOOSE(Control!$D$7,F10,F43,F76) -> 0.005 | G109: =CHOOSE(Control!$D$7,G10,G43,G76) -> 0 | H109: =CHOOSE(Control!$D$7,H10,H43,H76) -> 0 | I109: =CHOOSE(Control!$D$7,I10,I43,I76) -> 0 | J109: =CHOOSE(Control!$D$7,J10,J43,J76) -> 0 | K109: =CHOOSE(Control!$D$7,K10,K43,K76) -> 0 | L109: =CHOOSE(Control!$D$7,L10,L43,L76) -> 0 | M109: =CHOOSE(Control!$D$7,M10,M43,M76) -> 0
...

Sheet Historicals
B2: REPORTED HISTORICALS
B4: Line item | D4: Unit | E4: FY23A | F4: FY24A | G4: FY25A | H4: FY26A | I4: Source
B5: Group
C6: Revenue | D6: A$m | G6: 1466.5 | H6: 1592.6 | I6: FY26 presentations
C7: Underlying EBITDA (post-AASB 16) | D7: A$m | G7: 230.1 | H7: 244.5 | I7: FY26 presentations
C8: Underlying EBITDA (pre-AASB 16) | D8: A$m | G8: 154.8 | H8: 160.8 | I8: FY26 presentations
C9: Underlying EBIT (post-AASB 16) | D9: A$m | G9: 118.7 | H9: 130.7 | I9: FY26 presentations
C10: Underlying EBIT (pre-AASB 16) | D10: A$m | G10: 99.3 | H10: 105.3 | I10: FY26 presentations
C11: Underlying NPAT (post-AASB 16) | D11: A$m | G11: 54.4 | H11: 61.4 | I11: FY26 presentations
C12: Underlying NPAT (pre-AASB 16) | D12: A$m | G12: 62.1 | H12: 66.3 | I12: FY26 presentations
C13: Statutory NPAT | D13: A$m | G13: 12.4 | H13: 47.1 | I13: FY26 presentations
C14: Underlying D&A | D14: A$m | G14: 111.3 | H14: 113.9 | I14: FY26 presentations
C15: Underlying net interest | D15: A$m | G15: 39.3 | H15: 43 | I15: FY26 presentations
C16: Basic EPS underlying (cents) | D16: cents | G16: 46.1 | H16: 52 | I16: FY26 presentations
B18: KFC Australia
C19: Restaurants at year end | D19: no. | G19: 288 | H19: 295 | I19: FY26 presentations
C20: Revenue | D20: A$m | E20: 1051.3 | F20: 1121 | G20: 1154.2 | H20: 1241.3 | I20: FY26 presentations
C21: Same store sales growth | D21: % | G21: 0.003 | H21: 0.027 | I21: FY26 presentations
C22: Restaurant-level EBITDA | D22: A$m | G22: 245.2 | H22: 260.5 | I22: FY26 presentations
C23: Restaurant-level EBITDA margin | D23: % | G23: 0.212 | H23: 0.21 | I23: FY26 presentations
C24: Segment EBITDA (post-AASB 16) | D24: A$m | E24: 201.6 | F24: 221.4 | G24: 222.6 | H24: 237.1 | I24: FY26 presentations
C25: Segment EBIT (post-AASB 16) | D25: A$m | E25: 136.1 | F25: 149.7 | G25: 146.2 | H25: 155.8 | I25: FY26 presentations
B27: KFC EUROPE (Germany and the Netherlands)
C28: Restaurants at year end | D28: no. | G28: 78 | H28: 80 | I28: FY26 presentations
C29: of which Germany | D29: no. | G29: 16 | H29: 17 | I29: FY26 presentations
C30: of which the Netherlands | D30: no. | G30: 62 | H30: 63 | I30: FY26 presentations
C31: Revenue | D31: A$m | E31: 248.7 | F31: 313.5 | G31: 312.3 | H31: 351.3 | I31: FY26 presentations
C32: Restaurant-level EBITDA | D32: A$m | G32: 61.9 | H32: 67.8 | I32: FY26 presentations
C33: Restaurant-level EBITDA margin | D33: % | G33: 0.198 | H33: 0.193 | I33: FY26 presentations
C34: Segment EBITDA (post-AASB 16) | D34: A$m | E34: 32.8 | F34: 42.5 | G34: 39.4 | H34: 44.9 | I34: FY26 presentations
C35: Segment EBIT (post-AASB 16) | D35: A$m | E35: 9.2 | F35: 12.1 | G35: 7.6 | H35: 14.9 | I35: FY26 presentations
C36: Germany same store sales growth | D36: % | G36: -0.033 | H36: 0.037 | I36: FY26 presentations
C37: Netherlands same store sales growth | D37: % | G37: -0.025 | H37: 0
B39: GERMANY / NETHERLANDS REVENUE SPLIT — SOLVED, NOT ESTIMATED
C40: Netherlands revenue growth (reported, AUD) | D40: % | H40: 0.116 | I40: Directors report in annual report
C41: Germany revenue growth (reported, AUD) | D41: % | H41: 0.158 | I41: Directors report in annual report
C42: Netherlands revenue — FY25 (solved) | D42: A$m | G42: =(H31-G31*(1+H41))/((1+H40)-(1+H41)) -> 246.27143 | I42: Solves NL + DE = Europe FY25 and NL x 1.116 + DE x 1.158 = Europe FY26 simultaneously
C43: Germany revenue — FY25 (solved) | D43: A$m | G43: =G31-G42 -> 66.028571
C44: Netherlands revenue — FY26 | D44: A$m | H44: =G42*(1+H40) -> 274.83891
C45: Germany revenue — FY26 | D45: A$m | H45: =G43*(1+H41) -> 76.461086
C46: Check: solved split sums to reported Europe revenue | D46: A$m | H46: =H44+H45-H31 -> 0
C47: Implied FY26 AUV — Germany | D47: A$m | H47: =H45/AVERAGE(G29,H29) -> 4.6340052
C48: Implied FY26 AUV — Netherlands | D48: A$m | H48: =H44/AVERAGE(G30,H30) -> 4.3974226
B50: BALANCE SHEET AND CASH FLOW
C51: Cash and equivalents | D51: A$m | G51: 119.1 | H51: 93.9
C52: Gross debt | D52: A$m | G52: 257 | H52: 213.5
C53: Net debt (excluding lease liabilities) | D53: A$m | G53: 137.9 | H53: 119.6
C54: Lease liabilities (current + non-current) | D54: A$m | G54: 633.6 | H54: 630.5
C55: Net leverage ratio (pre-AASB 16) | D55: x | G55: 0.93 | H55: 0.77
C56: Capex — property, plant and equipment | D56: A$m | G56: 65.8 | H56: 51.9
C57: Capex — intangibles | D57: A$m | G57: 2.2 | H57: 2.5
C58: Income tax paid | D58: A$m | G58: 27.9 | H58: 39.4
C59: Lease principal payments | D59: A$m | G59: 42.2 | H59: 57.9
C60: Interest paid on leases | D60: A$m | G60: 32.2 | H60: 35
C61: Net operating cash flow | D61: A$m | G61: 181.4 | H61: 150.1
C62: Net debt including lease liabilities | D62: A$m | G62: =G53+G54 -> 771.5 | H62: =H53+H54 -> 750.1
B64: AASB 16 BRIDGE — FY26A | K64: This reconciliation is what makes the dual-basis model possible
C65: Implied effective tax rate | D65: % | H65: =1-H11/(H9-H15) -> 0.29988597 | I65: 1 less underlying NPAT divided by underlying profit before tax (EBIT less net interest)
C66: Rent expense (pre-AASB 16 lens) | D66: A$m | H66: =H7-H8 -> 83.7 | I66: Post-AASB 16 EBITDA less pre-AASB 16 EBITDA — the rent that AASB 16 removes from operating costs
C67: Right-of-use asset depreciation | D67: A$m | H67: =(H7-H9)-(H8-H10) -> 58.3 | I67: Post-AASB 16 D&A less pre-AASB 16 D&A
C68: Lease interest expense | D68: A$m | H68: =H12/(1-H65)-H10+H15 -> 32.39886 | I68: Solved from the pre-AASB 16 profit and loss: grossed-up pre-AASB 16 NPAT less pre-AASB 16 EBIT plus total net interest
C69: Check: ROU depreciation + lease interest less rent | D69: A$m | H69: =H67+H68-H66 -> 6.9988599 | I69: Should be a small positive number — AASB 16 front-loads lease costs, so depreciation plus interest exceeds straight-line rent in a growing estate
C70: Implied cost of lease debt | D70: % | H70: =H68/AVERAGE(G54,H54) -> 0.051259964 | I70: Lease interest over average lease liability. Feeds the blended cost of debt on the WACC sheet

Sheet Model
B2: Operating Model
C4: A$ millions unless stated | E4: FY26A | F4: FY27E | G4: FY28E | H4: FY29E | I4: FY30E | J4: FY31E | K4: FY32E | L4: FY33E | M4: FY34E | N4: FY35E | P4: Logic and reasoning
C5: KFC Australia | D5: Units
C6: Restaurants - Opening | D6: no. | E6: =Historicals!G19 -> 288 | F6: =E8 -> 295 | G6: =F8 -> 301 | H6: =G8 -> 307 | I6: =H8 -> 313 | J6: =I8 -> 319 | K6: =J8 -> 325 | L6: =K8 -> 330 | M6: =L8 -> 334 | N6: =M8 -> 337
C7: Net new restaurants | D7: no. | E7: =Historicals!H19-Historicals!G19 -> 7 | F7: =Assumptions!E107 -> 6 | G7: =Assumptions!F107 -> 6 | H7: =Assumptions!G107 -> 6 | I7: =Assumptions!H107 -> 6 | J7: =Assumptions!I107 -> 6 | K7: =Assumptions!J107 -> 5 | L7: =Assumptions!K107 -> 4 | M7: =Assumptions!L107 -> 3 | N7: =Assumptions!M107 -> 3 | P7: FY26 is the reported movement from 288 to 295. Forecast years come from the live assumption block.
C8: Restaurants - Closing | D8: no. | E8: =SUM(E6:E7) -> 295 | F8: =SUM(F6:F7) -> 301 | G8: =SUM(G6:G7) -> 307 | H8: =SUM(H6:H7) -> 313 | I8: =SUM(I6:I7) -> 319 | J8: =SUM(J6:J7) -> 325 | K8: =SUM(K6:K7) -> 330 | L8: =SUM(L6:L7) -> 334 | ... N8: =SUM(N6:N7) -> 340
C9: Avg restaurant trading | D9: no. | E9: =AVERAGE(E8,E6) -> 291.5 | F9: =AVERAGE(F8,F6) -> 298 | G9: =AVERAGE(G8,G6) -> 304 | H9: =AVERAGE(H8,H6) -> 310 | I9: =AVERAGE(I8,I6) -> 316 | J9: =AVERAGE(J8,J6) -> 322 | K9: =AVERAGE(K8,K6) -> 327.5 | L9: =AVERAGE(L8,L6) -> 332 | ... N9: =AVERAGE(N8,N6) -> 338.5 | P9: Average of opening and closing. Revenue is earned across the year, not at the closing count — using closing store numbers overstates revenue in any rollout year.
C10: Avg unit volume (AUV) | D10: A$m | E10: =Historicals!H20/Model!E9 -> 4.258319 | F10: =E10*(1+Assumptions!E108+Assumptions!E109*IF(Control!$D$8=1,1,0)) -> 4.4073602 | G10: =F10*(1+Assumptions!F108+Assumptions!F109*IF(Control!$D$8=1,1,0)) -> 4.5175442 | H10: =G10*(1+Assumptions!G108+Assumptions!G109*IF(Control!$D$8=1,1,0)) -> 4.6078951 | I10: =H10*(1+Assumptions!H108+Assumptions!H109*IF(Control!$D$8=1,1,0)) -> 4.700053 | J10: =I10*(1+Assumptions!I108+Assumptions!I109*IF(Control!$D$8=1,1,0)) -> 4.7940541 | K10: =J10*(1+Assumptions!J108+Assumptions!J109*IF(Control!$D$8=1,1,0)) -> 4.8899351 | L10: =K10*(1+Assumptions!K108+Assumptions!K109*IF(Control!$D$8=1,1,0)) -> 4.9877338 | M10: =L10*(1+Assumptions!L108+Assumptions!L109*IF(Control!$D$8=1,1,0)) -> 5.0874885 | N10: =M10*(1+Assumptions!M108+Assumptions!M109*IF(Control!$D$8=1,1,0)) -> 5.1892383 | P10: FY26 AUV is reported revenue over average restaurants. Grown by same store sales plus the Kwench uplift, which can be switched off on Control to isolate what that single initiative is worth. This line drives roughly 78% of group revenue.
C11: 53rd week adjustment | D11: A$m | E11: 0 | F11: =-E10*E9/53 -> -23.420755 | P11: FY26 was a 53-week year and FY27 reverts to 52. One week of Australian trading is removed from FY27 — a real headwind that headline growth rates hide.
C12: Revenue | D12: A$m | E12: =E9*E10+E11 -> 1241.3 | F12: =F9*F10+F11 -> 1289.9726 | G12: =G9*G10+G11 -> 1373.3334 | H12: =H9*H10+H11 -> 1428.4475 | I12: =I9*I10+I11 -> 1485.2167 | J12: =J9*J10+J11 -> 1543.6854 | K12: =K9*K10+K11 -> 1601.4538 | L12: =L9*L10+L11 -> 1655.9276 | ... N12: =N9*N10+N11 -> 1756.5572
C13: Restaurant-level EBITDA | D13: A$m | E13: =Historicals!H22 -> 260.5 | F13: =F12*Assumptions!E110 -> 265.73435 | G13: =G12*Assumptions!F110 -> 281.53336 | H13: =H12*Assumptions!G110 -> 291.40329 | I13: =I12*Assumptions!H110 -> 302.98422 | J13: =J12*Assumptions!I110 -> 314.91182 | K13: =K12*Assumptions!J110 -> 326.69657 | L13: =L12*Assumptions!K110 -> 337.80924 | M13: =M12*Assumptions!L110 -> 348.19789 | N13: =N12*Assumptions!M110 -> 358.33766
C14: Segment G&A | D14: A$m | E14: =-(Historicals!H22-Historicals!H24) -> -23.4 | F14: =-F12*Assumptions!E111 -> -25.799452 | G14: =-G12*Assumptions!F111 -> -27.466669 | H14: =-H12*Assumptions!G111 -> -28.28326 | I14: =-I12*Assumptions!H111 -> -29.407292 | J14: =-J12*Assumptions!I111 -> -30.564971 | K14: =-K12*Assumptions!J111 -> -31.708784 | L14: =-L12*Assumptions!K111 -> -32.787367 | M14: =-M12*Assumptions!L111 -> -33.795677 | N14: =-N12*Assumptions!M111 -> -34.779832
C15: Segment EBITDA (Post-AASB16) | D15: A$m | E15: =SUM(E13:E14) -> 237.1 | F15: =SUM(F13:F14) -> 239.9349 | G15: =SUM(G13:G14) -> 254.06669 | H15: =SUM(H13:H14) -> 263.12003 | I15: =SUM(I13:I14) -> 273.57692 | J15: =SUM(J13:J14) -> 284.34685 | K15: =SUM(K13:K14) -> 294.98778 | L15: =SUM(L13:L14) -> 305.02187 | ... N15: =SUM(N13:N14) -> 323.55783
C17: KFC Germany
C18: Restaurants - Opening | D18: no. | E18: =Historicals!G29 -> 16 | F18: =E20 -> 17 | G18: =F20 -> 28 | H18: =G20 -> 33 | I18: =H20 -> 38 | J18: =I20 -> 43 | K18: =J20 -> 48 | L18: =K20 -> 52 | M18: =L20 -> 55 | N18: =M20 -> 57
C19: Net new restaurants | D19: no. | E19: =Historicals!H29-Historicals!G29 -> 1 | F19: =Assumptions!E113 -> 11 | G19: =Assumptions!F113 -> 5 | H19: =Assumptions!G113 -> 5 | I19: =Assumptions!H113 -> 5 | J19: =Assumptions!I113 -> 5 | K19: =Assumptions!J113 -> 4 | L19: =Assumptions!K113 -> 3 | M19: =Assumptions!L113 -> 2 | N19: =Assumptions!M113 -> 2 | P19: FY27 includes the 8-restaurant Munich acquisition, which completed 1 June 2026 — after the 3 May 2026 year end, so it lands in FY27 rather than FY26.
C20: Restaurants - Closing | D20: no. | E20: =E18+E19 -> 17 | F20: =F18+F19 -> 28 | G20: =G18+G19 -> 33 | H20: =H18+H19 -> 38 | I20: =I18+I19 -> 43 | J20: =J18+J19 -> 48 | K20: =K18+K19 -> 52 | L20: =L18+L19 -> 55 | ... N20: =N18+N19 -> 59
C21: Avg restaurant trading | D21: no. | E21: =AVERAGE(E20,E18) -> 16.5 | F21: =AVERAGE(F20,F18) -> 22.5 | G21: =AVERAGE(G20,G18) -> 30.5 | H21: =AVERAGE(H20,H18) -> 35.5 | I21: =AVERAGE(I20,I18) -> 40.5 | J21: =AVERAGE(J20,J18) -> 45.5 | K21: =AVERAGE(K20,K18) -> 50 | L21: =AVERAGE(L20,L18) -> 53.5 | ... N21: =AVERAGE(N20,N18) -> 58
C22: Avg unit volume (AUV) | D22: A$m | E22: =Historicals!H45/Model!E21 -> 4.6340052 | F22: =E22*(1+Assumptions!E115) -> 4.4023049 | G22: =F22*(1+Assumptions!F115) -> 4.4023049 | H22: =G22*(1+Assumptions!G115) -> 4.446328 | I22: =H22*(1+Assumptions!H115) -> 4.5130229 | J22: =I22*(1+Assumptions!I115) -> 4.5807182 | K22: =J22*(1+Assumptions!J115) -> 4.649429 | L22: =K22*(1+Assumptions!K115) -> 4.7191705 | M22: =L22*(1+Assumptions!L115) -> 4.789958 | N22: =M22*(1+Assumptions!M115) -> 4.8618074 | P22: SOLVED, not estimated. CKF reports Europe as one segment, but the Annual Report discloses Netherlands revenue growth of 11.6% and German growth of 15.8%. Two equations, two unknowns — see the derivation block on the Historicals sheet.
C23: Revenue | D23: A$m | E23: =E22*E21 -> 76.461086 | F23: =F22*F21 -> 99.051861 | G23: =G22*G21 -> 134.2703 | H23: =H22*H21 -> 157.84464 | I23: =I22*I21 -> 182.77743 | J23: =J22*J21 -> 208.42268 | K23: =K22*K21 -> 232.47145 | L23: =L22*L21 -> 252.47562 | ... N23: =N22*N21 -> 281.98483
C25: KFC Netherlands
C26: Restaurants - Opening | D26: no. | E26: =Historicals!G30 -> 62 | F26: =E28 -> 63 | G26: =F28 -> 63 | H26: =G28 -> 63 | I26: =H28 -> 63 | J26: =I28 -> 63 | K26: =J28 -> 63 | L26: =K28 -> 63 | M26: =L28 -> 63 | N26: =M28 -> 63
C27: Net new restaurants | D27: no. | E27: =Historicals!H30-Historicals!G30 -> 1 | F27: =Assumptions!E117 -> 0 | G27: =Assumptions!F117 -> 0 | H27: =Assumptions!G117 -> 0 | I27: =Assumptions!H117 -> 0 | J27: =Assumptions!I117 -> 0 | K27: =Assumptions!J117 -> 0 | L27: =Assumptions!K117 -> 0 | M27: =Assumptions!L117 -> 0 | N27: =Assumptions!M117 -> 0
C28: Restaurants - Closing | D28: no. | E28: =E26+E27 -> 63 | F28: =F26+F27 -> 63 | G28: =G26+G27 -> 63 | H28: =H26+H27 -> 63 | I28: =I26+I27 -> 63 | J28: =J26+J27 -> 63 | K28: =K26+K27 -> 63 | L28: =L26+L27 -> 63 | ... N28: =N26+N27 -> 63
C29: Avg restaurant trading | D29: no. | E29: =AVERAGE(E28,E26) -> 62.5 | F29: =AVERAGE(F28,F26) -> 63 | G29: =AVERAGE(G28,G26) -> 63 | H29: =AVERAGE(H28,H26) -> 63 | I29: =AVERAGE(I28,I26) -> 63 | J29: =AVERAGE(J28,J26) -> 63 | K29: =AVERAGE(K28,K26) -> 63 | L29: =AVERAGE(L28,L26) -> 63 | ... N29: =AVERAGE(N28,N26) -> 63
C30: Avg unit volume (AUV) | D30: A$m | E30: =Historicals!H44/Model!E29 -> 4.3974226 | F30: =E30*(1+Assumptions!E118) -> 4.1775515 | G30: =F30*(1+Assumptions!F118) -> 4.135776 | H30: =G30*(1+Assumptions!G118) -> 4.1564549 | I30: =H30*(1+Assumptions!H118) -> 4.1980194 | J30: =I30*(1+Assumptions!I118) -> 4.2399996 | K30: =J30*(1+Assumptions!J118) -> 4.2823996 | L30: =K30*(1+Assumptions!K118) -> 4.3252236 | M30: =L30*(1+Assumptions!L118) -> 4.3684758 | N30: =M30*(1+Assumptions!M118) -> 4.4121606 | P30: From the same solved split. Because both countries are now derived independently rather than one being a plug, the Europe total becomes a genuine cross-check rather than an identity — see the check row on Historicals.
C31: Revenue | D31: A$m | E31: =E30*E29 -> 274.83891 | F31: =F30*F29 -> 263.18574 | G31: =G30*G29 -> 260.55389 | H31: =H30*H29 -> 261.85666 | I31: =I30*I29 -> 264.47522 | J31: =J30*J29 -> 267.11998 | K31: =K30*K29 -> 269.79117 | L31: =L30*L29 -> 272.48909 | ... N31: =N30*N29 -> 277.96612
C33: KFC Europe
C34: Revenue | D34: A$m | E34: =E23+E31 -> 351.3 | F34: =F23+F31 -> 362.23761 | G34: =G23+G31 -> 394.82419 | H34: =H23+H31 -> 419.7013 | I34: =I23+I31 -> 447.25265 | J34: =J23+J31 -> 475.54266 | K34: =K23+K31 -> 502.26263 | L34: =L23+L31 -> 524.96471 | ... N34: =N23+N31 -> 559.95095
C35: Restaurant-level EBITDA | D35: A$m | E35: =E34*Historicals!H33 -> 67.8009 | F35: =F34*Assumptions!E120 -> 67.013957 | G35: =G34*Assumptions!F120 -> 73.042475 | H35: =H34*Assumptions!G120 -> 77.64474 | I35: =I34*Assumptions!H120 -> 82.74174 | J35: =J34*Assumptions!I120 -> 87.975391 | K35: =K34*Assumptions!J120 -> 92.918586 | L35: =L34*Assumptions!K120 -> 97.118471 | M35: =M34*Assumptions!L120 -> 100.53855 | N35: =N34*Assumptions!M120 -> 103.59092
C36: Segment G&A | D36: A$m | E36: =-(Historicals!H32-Historicals!H34) -> -22.9 | F36: =-F34*Assumptions!E121 -> -25.71887 | G36: =-G34*Assumptions!F121 -> -27.637693 | H36: =-H34*Assumptions!G121 -> -28.95939 | I36: =-I34*Assumptions!H121 -> -30.41318 | J36: =-J34*Assumptions!I121 -> -32.336901 | K36: =-K34*Assumptions!J121 -> -33.651596 | L36: =-L34*Assumptions!K121 -> -35.172635 | M36: =-M34*Assumptions!L121 -> -36.411259 | N36: =-N34*Assumptions!M121 -> -37.516713
C37: Segment EBITDA (Post-AASB16) | D37: A$m | E37: =SUM(E35:E36) -> 44.9009 | F37: =SUM(F35:F36) -> 41.295087 | G37: =SUM(G35:G36) -> 45.404782 | H37: =SUM(H35:H36) -> 48.685351 | I37: =SUM(I35:I36) -> 52.32856 | J37: =SUM(J35:J36) -> 55.638491 | K37: =SUM(K35:K36) -> 59.26699 | L37: =SUM(L35:L36) -> 61.945835 | ... N37: =SUM(N35:N36) -> 66.074212
C39: GROUP PROFIT & LOSS
C40: Total Revenue | D40: A$m | E40: =E12+E34 -> 1592.6 | F40: =F12+F34 -> 1652.2102 | G40: =G12+G34 -> 1768.1576 | H40: =H12+H34 -> 1848.1488 | I40: =I12+I34 -> 1932.4694 | J40: =J12+J34 -> 2019.2281 | K40: =K12+K34 -> 2103.7164 | L40: =L12+L34 -> 2180.8923 | ... N40: =N12+N34 -> 2316.5081
C41: Revenue Growth | D41: % | E41: =E40/Historicals!G6-1 -> 0.085987044 | F41: =F40/E40-1 -> 0.037429481 | G41: =G40/F40-1 -> 0.07017717 | H41: =H40/G40-1 -> 0.045239831 | I41: =I40/H40-1 -> 0.045624367 | J41: =J40/I40-1 -> 0.044895233 | K41: =K40/J40-1 -> 0.041841892 | L41: =L40/K40-1 -> 0.036685533 | M41: =M40/L40-1 -> 0.031827194 | N41: =N40/M40-1 -> 0.029420061
C42: Segment EBITDA - Australia | D42: A$m | E42: =E15 -> 237.1 | F42: =F15 -> 239.9349 | G42: =G15 -> 254.06669 | H42: =H15 -> 263.12003 | I42: =I15 -> 273.57692 | J42: =J15 -> 284.34685 | K42: =K15 -> 294.98778 | L42: =L15 -> 305.02187 | ... N42: =N15 -> 323.55783
C43: Segment EBITDA - Europe | D43: A$m | E43: =E37 -> 44.9009 | F43: =F37 -> 41.295087 | G43: =G37 -> 45.404782 | H43: =H37 -> 48.685351 | I43: =I37 -> 52.32856 | J43: =J37 -> 55.638491 | K43: =K37 -> 59.26699 | L43: =L37 -> 61.945835 | ... N43: =N37 -> 66.074212
C44: Unallocated corporate cost | D44: A$m | E44: =-(Historicals!H24+Historicals!H34-Historicals!H7) -> -37.5 | F44: =-F40*Assumptions!E123 -> -39.653045 | G44: =-G40*Assumptions!F123 -> -42.435783 | H44: =-H40*Assumptions!G123 -> -44.355571 | I44: =-I40*Assumptions!H123 -> -46.379266 | J44: =-J40*Assumptions!I123 -> -48.461473 | K44: =-K40*Assumptions!J123 -> -50.489193 | L44: =-L40*Assumptions!K123 -> -52.341416 | M44: =-M40*Assumptions!L123 -> -54.007297 | N44: =-N40*Assumptions!M123 -> -55.596195 | P44: Not disclosed as a segment. Derived as the gap between the sum of the two segment EBITDAs and reported group EBITDA.
C45: EBITDA (Post-AASB16) | D45: A$m | E45: =SUM(E42:E44) -> 244.5009 | F45: =SUM(F42:F44) -> 241.57694 | G45: =SUM(G42:G44) -> 257.03568 | H45: =SUM(H42:H44) -> 267.44981 | I45: =SUM(I42:I44) -> 279.52622 | J45: =SUM(J42:J44) -> 291.52387 | K45: =SUM(K42:K44) -> 303.76558 | L45: =SUM(L42:L44) -> 314.62629 | ... N45: =SUM(N42:N44) -> 334.03585
C46: EBITDA Margin (Post-AASB16) | D46: % | E46: =E45/E40 -> 0.15352311 | F46: =F45/F40 -> 0.14621441 | G46: =G45/G40 -> 0.14536921 | H46: =H45/H40 -> 0.14471227 | I46: =I45/I40 -> 0.14464716 | J46: =J45/J40 -> 0.14437392 | K46: =K45/K40 -> 0.14439474 | L46: =L45/L40 -> 0.14426493 | ... N46: =N45/N40 -> 0.144198
C47: less: Rent expense | D47: A$m | E47: =-Historicals!H66 -> -83.7 | F47: =-F40*Assumptions!E124 -> -88.393245 | G47: =-G40*Assumptions!F124 -> -95.480512 | H47: =-H40*Assumptions!G124 -> -100.72411 | I47: =-I40*Assumptions!H124 -> -106.28582 | J47: =-J40*Assumptions!I124 -> -112.06716 | K47: =-K40*Assumptions!J124 -> -117.80812 | L47: =-L40*Assumptions!K124 -> -123.22042 | M47: =-M40*Assumptions!L124 -> -128.26733 | N47: =-N40*Assumptions!M124 -> -133.19922 | P47: Only relevant on the pre-AASB 16 basis. Under AASB 16 this cost is split into right-of-use depreciation and lease interest, and disappears from EBITDA entirely.
C48: EBITDA (Pre-AASB16) | D48: A$m | E48: =SUM(E47,E45) -> 160.8009 | F48: =SUM(F47,F45) -> 153.1837 | G48: =SUM(G47,G45) -> 161.55517 | H48: =SUM(H47,H45) -> 166.7257 | I48: =SUM(I47,I45) -> 173.2404 | J48: =SUM(J47,J45) -> 179.45671 | K48: =SUM(K47,K45) -> 185.95746 | L48: =SUM(L47,L45) -> 191.40587 | ... N48: =SUM(N47,N45) -> 200.83663
C50: DEPRECIATION AND AMORTISATION AND WORKING CAPITAL
C51: D&A excluding right-of-use assets | D51: A$m | E51: ='Capex & PPE'!E51 -> -55.6 | F51: ='Capex & PPE'!F51 -> -60.739512 | G51: ='Capex & PPE'!G51 -> -58.085882 | H51: ='Capex & PPE'!H51 -> -56.052014 | I51: ='Capex & PPE'!I51 -> -55.698373 | J51: ='Capex & PPE'!J51 -> -57.091051 | K51: ='Capex & PPE'!K51 -> -59.685104 | L51: ='Capex & PPE'!L51 -> -62.985444 | ... N51: ='Capex & PPE'!N51 -> -71.043459 | P51: Now driven by the fixed asset roll-forward on the Capex & PPE sheet — depreciation is an output of what you spend, not a percentage of revenue.
C52: Right-of-use asset depreciation | D52: A$m | E52: =-Historicals!H67 -> -58.3 | F52: =E52*(F40/E40) -> -60.482139 | G52: =F52*(G40/F40) -> -64.726604 | H52: =G52*(H40/G40) -> -67.654825 | I52: =H52*(I40/H40) -> -70.741533 | J52: =I52*(J40/I40) -> -73.917491 | K52: =J52*(K40/J40) -> -77.010339 | L52: =K52*(L40/K40) -> -79.835504 | M52: =L52*(M40/L40) -> -82.376444 | N52: =M52*(N40/M40) -> -84.799964 | P52: Scaled with revenue as a proxy for network growth — the right-of-use asset base grows broadly in line with the restaurant estate.
C53: Total D&A (post-AASB 16) | D53: A$m | E53: =E51+E52 -> -113.9 | F53: =F51+F52 -> -121.22165 | G53: =G51+G52 -> -122.81249 | H53: =H51+H52 -> -123.70684 | I53: =I51+I52 -> -126.43991 | J53: =J51+J52 -> -131.00854 | K53: =K51+K52 -> -136.69544 | L53: =L51+L52 -> -142.82095 | ... N53: =N51+N52 -> -155.84342
C54: EBIT (Post-AASB16) | D54: A$m | E54: =E53+E45 -> 130.6009 | F54: =F53+F45 -> 120.35529 | G54: =G53+G45 -> 134.2232 | H54: =H53+H45 -> 143.74297 | I54: =I53+I45 -> 153.08631 | J54: =J53+J45 -> 160.51533 | K54: =K53+K45 -> 167.07014 | L54: =L53+L45 -> 171.80534 | ... N54: =N53+N45 -> 178.19242
C55: EBIT (Pre-AASB16) | D55: A$m | E55: =E48+E51 -> 105.2009 | F55: =F48+F51 -> 92.444186 | G55: =G48+G51 -> 103.46929 | H55: =H48+H51 -> 110.67368 | I55: =I48+I51 -> 117.54203 | J55: =J48+J51 -> 122.36566 | K55: =K48+K51 -> 126.27236 | L55: =L48+L51 -> 128.42043 | ... N55: =N48+N51 -> 129.79317
C57: CAPITAL EXPENDITURE AND WORKING CAPITAL
C58: Maintenance and remodel capex | D58: A$m | E58: -38.1 | F58: =-F40*Assumptions!E125 -> -33.044204 | G58: =-G40*Assumptions!F125 -> -38.899468 | H58: =-H40*Assumptions!G125 -> -42.507422 | I58: =-I40*Assumptions!H125 -> -44.446796 | J58: =-J40*Assumptions!I125 -> -46.442245 | K58: =-K40*Assumptions!J125 -> -48.385477 | L58: =-L40*Assumptions!K125 -> -50.160524 | M58: =-M40*Assumptions!L125 -> -51.756993 | N58: =-N40*Assumptions!M125 -> -53.279686 | P58: FY26 actual: $15.3m asset capital maintenance + $16.8m remodels + $6.0m digital and sustainability (p.9).
C59: New restaurant capex | D59: A$m | E59: -13.8 | F59: =-((F7*Assumptions!E127)+(Model!F19-Assumptions!E114)*Assumptions!E128+Model!F27*Assumptions!E129) -> -18.6 | G59: =-((G7*Assumptions!F127)+(Model!G19-Assumptions!F114)*Assumptions!F128+Model!G27*Assumptions!F129) -> -23.95 | H59: =-((H7*Assumptions!G127)+(Model!H19-Assumptions!G114)*Assumptions!G128+Model!H27*Assumptions!G129) -> -24.5 | I59: =-((I7*Assumptions!H127)+(Model!I19-Assumptions!H114)*Assumptions!H128+Model!I27*Assumptions!H129) -> -25.05 | J59: =-((J7*Assumptions!I127)+(Model!J19-Assumptions!I114)*Assumptions!I128+Model!J27*Assumptions!I129) -> -25.6 | K59: =-((K7*Assumptions!J127)+(Model!K19-Assumptions!J114)*Assumptions!J128+Model!K27*Assumptions!J129) -> -21.43 | L59: =-((L7*Assumptions!K127)+(Model!L19-Assumptions!K114)*Assumptions!K128+Model!L27*Assumptions!K129) -> -17.03 | M59: =-((M7*Assumptions!L127)+(Model!M19-Assumptions!L114)*Assumptions!L128+Model!M27*Assumptions!L129) -> -12.38 | N59: =-((N7*Assumptions!M127)+(Model!N19-Assumptions!M114)*Assumptions!M128+Model!N27*Assumptions!M129) -> -12.7 | P59: Net BUILT restaurants by geography times build cost per restaurant. Acquired restaurants are stripped out here and charged below as acquisition consideration instead — charging them twice was inflating FY27 capex well past management's guidance.
C60: Project capex (Kwench and other) | D60: A$m | E60: 0 | F60: =-Assumptions!E126 -> -35 | G60: =-Assumptions!F126 -> -12 | H60: 0 | I60: 0 | J60: 0 | K60: 0 | L60: 0 | M60: 0 | N60: 0
C61: Total capex | D61: A$m | E61: =-SUM(E58:E60) -> 51.9 | F61: =-SUM(F58:F60) -> 86.644204 | G61: =-SUM(G58:G60) -> 74.849468 | H61: =-SUM(H58:H60) -> 67.007422 | I61: =-SUM(I58:I60) -> 69.496796 | J61: =-SUM(J58:J60) -> 72.042245 | K61: =-SUM(K58:K60) -> 69.815477 | L61: =-SUM(L58:L60) -> 67.190524 | ... N61: =-SUM(N58:N60) -> 65.979686 | P61: Shown positive for readability and subtracted in the cash flow build below. Cross-check FY27 against management guidance of $80-100m (p.35).
C62: Capex as % of revenue | D62: % | E62: =E61/E40 -> 0.032588221 | F62: =F61/F40 -> 0.052441393 | G62: =G61/G40 -> 0.042331898 | H62: =H61/H40 -> 0.036256508 | I62: =I61/I40 -> 0.035962689 | J62: =J61/J40 -> 0.035678112 | K62: =K61/K40 -> 0.033186734 | L62: =L61/L40 -> 0.03080873 | ... N62: =N61/N40 -> 0.02848239
C63: Net working capital balance | D63: A$m | E63: =E40*Assumptions!E130 -> -87.593 | F63: =F40*Assumptions!E130 -> -90.871561 | G63: =G40*Assumptions!F130 -> -97.24867 | H63: =H40*Assumptions!G130 -> -101.64818 | I63: =I40*Assumptions!H130 -> -106.28582 | J63: =J40*Assumptions!I130 -> -111.05754 | K63: =K40*Assumptions!J130 -> -115.7044 | L63: =L40*Assumptions!K130 -> -119.94908 | M63: =M40*Assumptions!L130 -> -123.76672 | N63: =N40*Assumptions!M130 -> -127.40795
C64: Cash released from working capital | D64: A$m | E64: 0 | F64: =-(F63-E63) -> 3.2785606 | G64: =-(G63-F63) -> 6.377109 | H64: =-(H63-G63) -> 4.3995133 | I64: =-(I63-H63) -> 4.637634 | J64: =-(J63-I63) -> 4.7717265 | K64: =-(K63-J63) -> 4.6468577 | L64: =-(L63-K63) -> 4.2446777 | M64: =-(M63-L63) -> 3.8176425 | N64: =-(N63-M63) -> 3.6412245 | P64: Working capital is negative, so growth RELEASES cash. Sign convention: a positive number here adds to free cash flow.
C65: Acquisition consideration | D65: A$m | E65: 0 | F65: -50.6 | G65: 0 | H65: 0 | I65: 0 | J65: 0 | K65: 0 | L65: 0 | M65: 0 | N65: 0 | P65: ACTUAL. EUR 31.1m ($50.6m), completed 2 June 2026, funded from existing finance facilities (FY26 Annual Report, Subsequent Events). Purchase price accounting is provisional and will be finalised at HY27. It must be deducted because those 8 restaurants generate revenue in the forecast — free earnings with no purchase price is a silent overvaluation.
C66: Memo: lease liability balance | D66: A$m | E66: =Historicals!H54 -> 630.5 | F66: =$E$66*F40/$E$40 -> 654.09929 | G66: =$E$66*G40/$E$40 -> 700.00212 | H66: =$E$66*H40/$E$40 -> 731.6701 | I66: =$E$66*I40/$E$40 -> 765.05209 | J66: =$E$66*J40/$E$40 -> 799.39928 | K66: =$E$66*K40/$E$40 -> 832.84766 | L66: =$E$66*L40/$E$40 -> 863.40112 | M66: =$E$66*M40/$E$40 -> 890.88075 | N66: =$E$66*N40/$E$40 -> 917.09052 | P66: Memo only — scaled with revenue. Not used in the valuation, which is run on a pre-AASB 16 basis. Provided so enterprise value can be restated on an AASB 16 basis when comparing multiples against peers.
C68: UNLEVERED FREE CASH FLOW — PRE-AASB 16 BASIS
C69: EBIT (pre-AASB 16) | D69: A$m | E69: =E55 -> 105.2009 | F69: =F55 -> 92.444186 | G69: =G55 -> 103.46929 | H69: =H55 -> 110.67368 | I69: =I55 -> 117.54203 | J69: =J55 -> 122.36566 | K69: =K55 -> 126.27236 | L69: =L55 -> 128.42043 | ... N69: =N55 -> 129.79317
C70: Less: tax on EBIT | D70: A$m | E70: =-E69*Historicals!$H$65 -> -31.548274 | F70: =-F69*Assumptions!E131 -> -28.195477 | G70: =-G69*Assumptions!F131 -> -31.558134 | H70: =-H69*Assumptions!G131 -> -33.755474 | I70: =-I69*Assumptions!H131 -> -35.850319 | J70: =-J69*Assumptions!I131 -> -37.321526 | K70: =-K69*Assumptions!J131 -> -38.513069 | L70: =-L69*Assumptions!K131 -> -39.168231 | M70: =-M69*Assumptions!L131 -> -39.497668 | N70: =-N69*Assumptions!M131 -> -39.586917 | P70: Tax is charged on EBIT
C71: NOPAT | D71: A$m | E71: =E69+E70 -> 73.652626 | F71: =F69+F70 -> 64.248709 | G71: =G69+G70 -> 71.911158 | H71: =H69+H70 -> 76.91821 | I71: =I69+I70 -> 81.69171 | J71: =J69+J70 -> 85.044134 | K71: =K69+K70 -> 87.759288 | L71: =L69+L70 -> 89.252197 | ... N71: =N69+N70 -> 90.206254
C72: Add back: D&A excluding right-of-use | D72: A$m | E72: =-E51 -> 55.6 | F72: =-F51 -> 60.739512 | G72: =-G51 -> 58.085882 | H72: =-H51 -> 56.052014 | I72: =-I51 -> 55.698373 | J72: =-J51 -> 57.091051 | K72: =-K51 -> 59.685104 | L72: =-L51 -> 62.985444 | ... N72: =-N51 -> 71.043459
C73: Less: capital expenditure | D73: A$m | E73: =-E61 -> -51.9 | F73: =-F61 -> -86.644204 | G73: =-G61 -> -74.849468 | H73: =-H61 -> -67.007422 | I73: =-I61 -> -69.496796 | J73: =-J61 -> -72.042245 | K73: =-K61 -> -69.815477 | L73: =-L61 -> -67.190524 | ... N73: =-N61 -> -65.979686
C74: Less: acquisitions | D74: A$m | E74: =E65 -> 0 | F74: =F65 -> -50.6 | G74: =G65 -> 0 | H74: =H65 -> 0 | I74: =I65 -> 0 | J74: =J65 -> 0 | K74: =K65 -> 0 | L74: =L65 -> 0 | ... N74: =N65 -> 0
C75: Working capital movement | D75: A$m | E75: =E64 -> 0 | F75: =F64 -> 3.2785606 | G75: =G64 -> 6.377109 | H75: =H64 -> 4.3995133 | I75: =I64 -> 4.637634 | J75: =J64 -> 4.7717265 | K75: =K64 -> 4.6468577 | L75: =L64 -> 4.2446777 | ... N75: =N64 -> 3.6412245
C76: FCFF (pre-AASB 16) | D76: A$m | E76: =SUM(E71:E75) -> 77.352626 | F76: =SUM(F71:F75) -> -8.9774219 | G76: =SUM(G71:G75) -> 61.52468 | H76: =SUM(H71:H75) -> 70.362315 | I76: =SUM(I71:I75) -> 72.530921 | J76: =SUM(J71:J75) -> 74.864666 | K76: =SUM(K71:K75) -> 82.275773 | L76: =SUM(L71:L75) -> 89.291796 | ... N76: =SUM(N71:N75) -> 98.911251
C78: VALUATION CASH FLOW AND MULTIPLE BASE
C79: FCFF used in the valuation | D79: A$m | E79: =E76 -> 77.352626 | F79: =F76 -> -8.9774219 | G79: =G76 -> 61.52468 | H79: =H76 -> 70.362315 | I79: =I76 -> 72.530921 | J79: =J76 -> 74.864666 | K79: =K76 -> 82.275773 | L79: =L76 -> 89.291796 | ... N79: =N76 -> 98.911251 | P79: Pre-AASB 16 throughout. See the 'AASB 16' section on the Notes sheet for why, and for what would have to change to value this on a lease-capitalised basis.
C80: EBITDA used for multiples (pre-AASB 16) | D80: A$m | E80: =E48 -> 160.8009 | F80: =F48 -> 153.1837 | G80: =G48 -> 161.55517 | H80: =H48 -> 166.7257 | I80: =I48 -> 173.2404 | J80: =J48 -> 179.45671 | K80: =K48 -> 185.95746 | L80: =L48 -> 191.40587 | ... N80: =N48 -> 200.83663
C81: FCFF conversion (FCFF / EBITDA) | D81: % | E81: =E79/E80 -> 0.48104597 | F81: =F79/F80 -> -0.058605595 | G81: =G79/G80 -> 0.38082767 | H81: =H79/H80 -> 0.42202442 | I81: =I79/I80 -> 0.41867209 | J81: =J79/J80 -> 0.41717396 | K81: =K79/K80 -> 0.44244406 | L81: =L79/L80 -> 0.466505 | ... N81: =N79/N80 -> 0.49249607

Sheet Capex & PPE
B2: CAPITAL EXPENDITURE AND FIXED ASSETS
C3: Depreciation is built as a vintage waterfall: each year's capex is split by asset class and depreciated over the useful lives disclosed in Note G5 of the FY26 Annual Report.
C5: A$ millions | D5: Unit | E5: FY26A | F5: FY27E | G5: FY28E | H5: FY29E | I5: FY30E | J5: FY31E | K5: FY32E | L5: FY33E | M5: FY34E | N5: FY35E | P5: Logic and source
C6: ASSET LIVES — PER NOTE G5, FY26 ANNUAL REPORT
C7: Leasehold improvements — useful life | D7: years | E7: 15 | P7: FY26 Annual Report, Note G5 Property, plant and equipment. All classes are straight line. Note G5 specifies '20 years or term of the lease' for building leasehold improvements and 'primary term of lease' for other leasehold improvements. 15 years is used as the effective life because most QSR primary lease terms run 10-15 years, below the 20-year cap. Change this cell if you can source the actual weighted average lease term from Note G8.
C8: Plant and equipment — useful life | D8: years | E8: 8 | P8: FY26 Annual Report, Note G5 Property, plant and equipment. All classes are straight line. Disclosed as 8 years.
C9: Motor vehicles — useful life (memo) | D9: years | E9: 4 | P9: FY26 Annual Report, Note G5 Property, plant and equipment. All classes are straight line. Disclosed as 4 years. Immaterial for a restaurant operator, so not modelled as a separate class.
C10: Capex mix — leasehold improvements | D10: % | E10: 0.55 | P10: ASSUMPTION, not disclosed. Note G5 gives the lives but not how capex splits between classes. A KFC build is weighted toward fitout, drive-thru works and shopfront (leasehold improvements) over kitchen equipment (plant and equipment). 55/45 assumed.
C11: Capex mix — plant and equipment | D11: % | E11: =1-E10 -> 0.45
C12: Blended annual depreciation rate on new capex | D12: % | E12: =E10/E7+E11/E8 -> 0.092916667 | P12: Straight-line rate applied to GROSS cost of each vintage — the correct denominator, unlike a rate struck on net book value.
C13: Implied blended useful life of new capex | D13: years | E13: =1/E12 -> 10.762332
C14: Half-year convention in year of addition | D14: 0 / 1 | E14: 1 | P14: 1 charges half a year of depreciation in the year an asset is bought, which is the standard simplification for assets acquired evenly through the year. Set to 0 for a full year.
C16: CAPITAL EXPENDITURE BY CATEGORY
C17: New restaurants | D17: A$m | E17: =-Model!E59 -> 13.8 | F17: =-Model!F59 -> 18.6 | G17: =-Model!G59 -> 23.95 | H17: =-Model!H59 -> 24.5 | I17: =-Model!I59 -> 25.05 | J17: =-Model!J59 -> 25.6 | K17: =-Model!K59 -> 21.43 | L17: =-Model!L59 -> 17.03 | ... N17: =-Model!N59 -> 12.7
C18: Maintenance and remodels | D18: A$m | E18: =-Model!E58 -> 38.1 | F18: =-Model!F58 -> 33.044204 | G18: =-Model!G58 -> 38.899468 | H18: =-Model!H58 -> 42.507422 | I18: =-Model!I58 -> 44.446796 | J18: =-Model!J58 -> 46.442245 | K18: =-Model!K58 -> 48.385477 | L18: =-Model!L58 -> 50.160524 | ... N18: =-Model!N58 -> 53.279686
C19: Project capex (Kwench) | D19: A$m | E19: =-Model!E60 -> 0 | F19: =-Model!F60 -> 35 | G19: =-Model!G60 -> 12 | H19: =-Model!H60 -> 0 | I19: =-Model!I60 -> 0 | J19: =-Model!J60 -> 0 | K19: =-Model!K60 -> 0 | L19: =-Model!L60 -> 0 | ... N19: =-Model!N60 -> 0
C20: PP&E acquired with the Munich business | D20: A$m | E20: =-Model!E65 -> 0 | F20: 20 | G20: =-Model!G65 -> 0 | H20: =-Model!H65 -> 0 | I20: =-Model!I65 -> 0 | J20: =-Model!J65 -> 0 | K20: =-Model!K65 -> 0 | L20: =-Model!L65 -> 0 | M20: =-Model!M65 -> 0 | N20: =-Model!N65 -> 0 | P20: ESTIMATE — the PP&E slice of the $50.6m consideration, not the whole price. The rest is goodwill, franchise rights and leases. CKF's own purchase price allocation is provisional until HY27. Acquired assets are fair-valued on acquisition so they are depreciated as a fresh vintage.
C21: Total additions | D21: A$m | E21: =SUM(E17:E20) -> 51.9 | F21: =SUM(F17:F20) -> 106.6442 | G21: =SUM(G17:G20) -> 74.849468 | H21: =SUM(H17:H20) -> 67.007422 | I21: =SUM(I17:I20) -> 69.496796 | J21: =SUM(J17:J20) -> 72.042245 | K21: =SUM(K17:K20) -> 69.815477 | L21: =SUM(L17:L20) -> 67.190524 | ... N21: =SUM(N17:N20) -> 65.979686
C23: DEPRECIATION WATERFALL
C24: Each vintage of capex is depreciated over its own life. The legacy pool runs off separately, because those assets are already part-way through theirs.
C25: Legacy pool — opening net book value | D25: A$m | F25: =E45 -> 238.8 | G25: =F28 -> 186.9 | H25: =G28 -> 146.27977 | I25: =H28 -> 114.48781 | J25: =I28 -> 89.605411 | K25: =J28 -> 70.130868 | L25: =K28 -> 54.888858 | M25: =L28 -> 42.959496 | N25: =M28 -> 33.622821
C26: Legacy pool — run-off rate | D26: % | E26: =-E38/E45 -> 0.21733668 | P26: FY26 depreciation divided by FY26 closing net book value. Applied on a declining balance, which models a pool of mixed vintages running off smoothly rather than every legacy asset expiring on the same day. That avoids an artificial cliff in the terminal year.
C27: Legacy pool — depreciation | D27: A$m | F27: =-F25*$E$26 -> -51.9 | G27: =-G25*$E$26 -> -40.620226 | H27: =-H25*$E$26 -> -31.791961 | I27: =-I25*$E$26 -> -24.882402 | J27: =-J25*$E$26 -> -19.474543 | K27: =-K25*$E$26 -> -15.24201 | L27: =-L25*$E$26 -> -11.929362 | M27: =-M25*$E$26 -> -9.3366743 | N27: =-N25*$E$26 -> -7.3074725
C28: Legacy pool — closing net book value | D28: A$m | F28: =F25+F27 -> 186.9 | G28: =G25+G27 -> 146.27977 | H28: =H25+H27 -> 114.48781 | I28: =I25+I27 -> 89.605411 | J28: =J25+J27 -> 70.130868 | K28: =K25+K27 -> 54.888858 | L28: =L25+L27 -> 42.959496 | M28: =M25+M27 -> 33.622821 | N28: =N25+N27 -> 26.315349
C29: FY27E capex vintage — depreciation | D29: A$m | F29: =-F21*$E$12*IF($E$14=1,0.5,1) -> -4.954512 | G29: =-$F21*$E$12 -> -9.9090239 | H29: =-$F21*$E$12 -> -9.9090239 | I29: =-$F21*$E$12 -> -9.9090239 | J29: =-$F21*$E$12 -> -9.9090239 | K29: =-$F21*$E$12 -> -9.9090239 | L29: =-$F21*$E$12 -> -9.9090239 | M29: =-$F21*$E$12 -> -9.9090239 | N29: =-$F21*$E$12 -> -9.9090239
C30: FY28E capex vintage — depreciation | D30: A$m | F30: 0 | G30: =-G21*$E$12*IF($E$14=1,0.5,1) -> -3.4773815 | H30: =-$G21*$E$12 -> -6.9547631 | I30: =-$G21*$E$12 -> -6.9547631 | J30: =-$G21*$E$12 -> -6.9547631 | K30: =-$G21*$E$12 -> -6.9547631 | L30: =-$G21*$E$12 -> -6.9547631 | M30: =-$G21*$E$12 -> -6.9547631 | N30: =-$G21*$E$12 -> -6.9547631
C31: FY29E capex vintage — depreciation | D31: A$m | F31: 0 | G31: 0 | H31: =-H21*$E$12*IF($E$14=1,0.5,1) -> -3.1130531 | I31: =-$H21*$E$12 -> -6.2261063 | J31: =-$H21*$E$12 -> -6.2261063 | K31: =-$H21*$E$12 -> -6.2261063 | L31: =-$H21*$E$12 -> -6.2261063 | M31: =-$H21*$E$12 -> -6.2261063 | N31: =-$H21*$E$12 -> -6.2261063
C32: FY30E capex vintage — depreciation | D32: A$m | F32: 0 | G32: 0 | H32: 0 | I32: =-I21*$E$12*IF($E$14=1,0.5,1) -> -3.2287053 | J32: =-$I21*$E$12 -> -6.4574106 | K32: =-$I21*$E$12 -> -6.4574106 | L32: =-$I21*$E$12 -> -6.4574106 | M32: =-$I21*$E$12 -> -6.4574106 | N32: =-$I21*$E$12 -> -6.4574106
C33: FY31E capex vintage — depreciation | D33: A$m | F33: 0 | G33: 0 | H33: 0 | I33: 0 | J33: =-J21*$E$12*IF($E$14=1,0.5,1) -> -3.3469627 | K33: =-$J21*$E$12 -> -6.6939253 | L33: =-$J21*$E$12 -> -6.6939253 | M33: =-$J21*$E$12 -> -6.6939253 | N33: =-$J21*$E$12 -> -6.6939253
C34: FY32E capex vintage — depreciation | D34: A$m | F34: 0 | G34: 0 | H34: 0 | I34: 0 | J34: 0 | K34: =-K21*$E$12*IF($E$14=1,0.5,1) -> -3.2435107 | L34: =-$K21*$E$12 -> -6.4870214 | M34: =-$K21*$E$12 -> -6.4870214 | N34: =-$K21*$E$12 -> -6.4870214
C35: FY33E capex vintage — depreciation | D35: A$m | F35: 0 | G35: 0 | H35: 0 | I35: 0 | J35: 0 | K35: 0 | L35: =-L21*$E$12*IF($E$14=1,0.5,1) -> -3.1215598 | M35: =-$L21*$E$12 -> -6.2431195 | N35: =-$L21*$E$12 -> -6.2431195
C36: FY34E capex vintage — depreciation | D36: A$m | F36: 0 | G36: 0 | H36: 0 | I36: 0 | J36: 0 | K36: 0 | L36: 0 | M36: =-M21*$E$12*IF($E$14=1,0.5,1) -> -2.9796978 | N36: =-M21*$E$12 -> -5.9593956
C37: FY35E capex vintage — depreciation | D37: A$m | F37: 0 | G37: 0 | H37: 0 | I37: 0 | J37: 0 | K37: 0 | L37: 0 | M37: 0 | N37: =-N21*$E$12*IF($E$14=1,0.5,1) -> -3.0653063
C38: Total depreciation | D38: A$m | E38: =-(Historicals!H14-Historicals!H67+E48) -> -51.9 | F38: =F27+SUM(F29:F37) -> -56.854512 | G38: =G27+SUM(G29:G37) -> -54.006632 | H38: =H27+SUM(H29:H37) -> -51.768801 | I38: =I27+SUM(I29:I37) -> -51.201 | J38: =J27+SUM(J29:J37) -> -52.36881 | K38: =K27+SUM(K29:K37) -> -54.72675 | L38: =L27+SUM(L29:L37) -> -57.779173 | M38: =M27+SUM(M29:M37) -> -61.287742 | N38: =N27+SUM(N29:N37) -> -65.303544 | P38: FY26 is derived from reported figures: total D&A less right-of-use depreciation less intangible amortisation. Forecast years are the legacy run-off plus each vintage.
C40: PROPERTY, PLANT AND EQUIPMENT ROLL-FORWARD
C41: Opening PP&E | D41: A$m | E41: 247.4 | F41: =E45 -> 238.8 | G41: =F45 -> 288.58969 | H41: =G45 -> 309.43253 | I41: =H45 -> 324.67115 | J41: =I45 -> 342.96694 | K41: =J45 -> 362.64038 | L41: =K45 -> 377.72911 | M41: =L45 -> 387.14046 | N41: =M45 -> 389.98971 | P41: FY25 closing PP&E, FY26 presentation p.10 balance sheet
C42: Additions | D42: A$m | E42: =E21 -> 51.9 | F42: =F21 -> 106.6442 | G42: =G21 -> 74.849468 | H42: =H21 -> 67.007422 | I42: =I21 -> 69.496796 | J42: =J21 -> 72.042245 | K42: =K21 -> 69.815477 | L42: =L21 -> 67.190524 | ... N42: =N21 -> 65.979686
C43: Depreciation | D43: A$m | E43: =E38 -> -51.9 | F43: =F38 -> -56.854512 | G43: =G38 -> -54.006632 | H43: =H38 -> -51.768801 | I43: =I38 -> -51.201 | J43: =J38 -> -52.36881 | K43: =K38 -> -54.72675 | L43: =L38 -> -57.779173 | ... N43: =N38 -> -65.303544
C44: Disposals, impairment and FX | D44: A$m | F44: 0 | G44: 0 | H44: 0 | I44: 0 | J44: 0 | K44: 0 | L44: 0 | M44: 0 | N44: 0 | P44: FY26 is the balancing figure (net impairments of $6.5m, the land parcel sale and FX). Forecast at zero because impairments are non-trading by definition — state that rather than letting it look like an oversight.
C45: Closing PP&E | D45: A$m | E45: 238.8 | F45: =F41+F42+F43+F44 -> 288.58969 | G45: =G41+G42+G43+G44 -> 309.43253 | H45: =H41+H42+H43+H44 -> 324.67115 | I45: =I41+I42+I43+I44 -> 342.96694 | J45: =J41+J42+J43+J44 -> 362.64038 | K45: =K41+K42+K43+K44 -> 377.72911 | L45: =L41+L42+L43+L44 -> 387.14046 | M45: =M41+M42+M43+M44 -> 389.98971 | N45: =N41+N42+N43+N44 -> 390.66585 | P45: FY26 closing PP&E per presentation p.10, hardcoded so the disposals line solves as the balancer
C47: INTANGIBLE AMORTISATION
C48: Amortisation of intangibles | D48: A$m | E48: -3.7 | F48: =E48*1.05 -> -3.885 | G48: =F48*1.05 -> -4.07925 | H48: =G48*1.05 -> -4.2832125 | I48: =H48*1.05 -> -4.4973731 | J48: =I48*1.05 -> -4.7222418 | K48: =J48*1.05 -> -4.9583539 | L48: =K48*1.05 -> -5.2062716 | M48: =L48*1.05 -> -5.4665851 | N48: =M48*1.05 -> -5.7399144 | P48: FY26 actual per presentation p.10 (intangibles fell $15.3m: $14.3m FX plus $3.7m amortisation, offset by $2.2m of franchise rights). Grown 5% a year. A full roll-forward needs Note G6.
C50: OUTPUTS AND DIAGNOSTICS
C51: Total D&A excluding right-of-use → Model | D51: A$m | E51: =E38+E48 -> -55.6 | F51: =F38+F48 -> -60.739512 | G51: =G38+G48 -> -58.085882 | H51: =H38+H48 -> -56.052014 | I51: =I38+I48 -> -55.698373 | J51: =J38+J48 -> -57.091051 | K51: =K38+K48 -> -59.685104 | L51: =L38+L48 -> -62.985444 | ... N51: =N38+N48 -> -71.043459 | P51: Feeds straight into the Model sheet
C52: Capex / depreciation | D52: x | E52: =IFERROR(-(E17+E18+E19)/E38,0) -> 1 | F52: =IFERROR(-(F17+F18+F19)/F38,0) -> 1.5239635 | G52: =IFERROR(-(G17+G18+G19)/G38,0) -> 1.3859311 | H52: =IFERROR(-(H17+H18+H19)/H38,0) -> 1.2943592 | I52: =IFERROR(-(I17+I18+I19)/I38,0) -> 1.3573328 | J52: =IFERROR(-(J17+J18+J19)/J38,0) -> 1.3756709 | K52: =IFERROR(-(K17+K18+K19)/K38,0) -> 1.2757103 | L52: =IFERROR(-(L17+L18+L19)/L38,0) -> 1.1628848 | ... N52: =IFERROR(-(N17+N18+N19)/N38,0) -> 1.0103538 | P52: Above 1.0x means the asset base is growing. Note this rises sharply once depreciation is built properly — the old NBV-rate method flattered it by over-depreciating.
C53: Maintenance capex as % of total capex | D53: % | E53: =IFERROR(E18/(E17+E18+E19),0) -> 0.73410405 | F53: =IFERROR(F18/(F17+F18+F19),0) -> 0.38137812 | G53: =IFERROR(G18/(G17+G18+G19),0) -> 0.51970266 | H53: =IFERROR(H18/(H17+H18+H19),0) -> 0.63436886 | I53: =IFERROR(I18/(I17+I18+I19),0) -> 0.63955173 | J53: =IFERROR(J18/(J17+J18+J19),0) -> 0.64465294 | K53: =IFERROR(K18/(K17+K18+K19),0) -> 0.693048 | L53: =IFERROR(L18/(L17+L18+L19),0) -> 0.74654164 | ... N53: =IFERROR(N18/(N17+N18+N19),0) -> 0.80751651
C54: Growth capex (new restaurants + projects) | D54: A$m | E54: =E17+E19 -> 13.8 | F54: =F17+F19 -> 53.6 | G54: =G17+G19 -> 35.95 | H54: =H17+H19 -> 24.5 | I54: =I17+I19 -> 25.05 | J54: =J17+J19 -> 25.6 | K54: =K17+K19 -> 21.43 | L54: =L17+L19 -> 17.03 | ... N54: =N17+N19 -> 12.7 | P54: Strip growth capex out and you get the cash the business would throw off if it stopped expanding — the number an acquirer starts from.
C55: Capex as % of revenue | D55: % | E55: =IFERROR((E17+E18+E19)/Model!E40,0) -> 0.032588221 | F55: =IFERROR((F17+F18+F19)/Model!F40,0) -> 0.052441393 | G55: =IFERROR((G17+G18+G19)/Model!G40,0) -> 0.042331898 | H55: =IFERROR((H17+H18+H19)/Model!H40,0) -> 0.036256508 | I55: =IFERROR((I17+I18+I19)/Model!I40,0) -> 0.035962689 | J55: =IFERROR((J17+J18+J19)/Model!J40,0) -> 0.035678112 | K55: =IFERROR((K17+K18+K19)/Model!K40,0) -> 0.033186734 | L55: =IFERROR((L17+L18+L19)/Model!L40,0) -> 0.03080873 | ... N55: =IFERROR((N17+N18+N19)/Model!N40,0) -> 0.02848239
C56: Depreciation as % of revenue | D56: % | E56: =IFERROR(-E38/Model!E40,0) -> 0.032588221 | F56: =IFERROR(-F38/Model!F40,0) -> 0.034411186 | G56: =IFERROR(-G38/Model!G40,0) -> 0.030544014 | H56: =IFERROR(-H38/Model!H40,0) -> 0.028011165 | I56: =IFERROR(-I38/Model!I40,0) -> 0.026495116 | J56: =IFERROR(-J38/Model!J40,0) -> 0.025935064 | K56: =IFERROR(-K38/Model!K40,0) -> 0.02601432 | L56: =IFERROR(-L38/Model!L40,0) -> 0.026493363 | ... N56: =IFERROR(-N38/Model!N40,0) -> 0.02819051 | P56: A useful reasonableness test: depreciation should trend toward capex intensity over time as the asset base matures. If it does not, a life assumption is wrong.

Sheet Debt & Leases
B2: DEBT, LEASES AND COVENANT CAPACITY
C5: A$ millions | D5: Unit | E5: FY26A | F5: FY27E | G5: FY28E | H5: FY29E | I5: FY30E | J5: FY31E | K5: FY32E | L5: FY33E | M5: FY34E | N5: FY35E | P5: Logic and source
C6: FINANCING ASSUMPTIONS
C7: Interest rate on drawn debt | E7: 0.056 | P7: Consistent with the cost of debt on the WACC sheet.
C8: Interest rate earned on cash | E8: 0.035 | P8: Assumption — Australian at-call deposit rates.
C9: Dividend payout ratio | E9: 0.538 | P9: FY26 actual: 28.0 cents declared against underlying EPS of 52.0 cents.
C10: Minimum operating cash balance | E10: 60 | P10: Assumption. CKF held $93.9m at FY26; a QSR needs far less than that as float.
C11: Covenant: maximum net leverage | E11: 3 | P11: NOT DISCLOSED in the material I could access. 3.0x is typical for an Australian corporate syndicated facility.
C13: GROSS DEBT SCHEDULE
C14: Opening gross debt | D14: A$m | E14: =Historicals!G52 -> 257 | F14: =E17 -> 213.5 | G14: =F17 -> 226.20175 | H14: =G17 -> 207.06797 | I14: =H17 -> 181.4636 | J14: =I17 -> 155.81388 | K14: =J17 -> 129.18269 | L14: =K17 -> 96.129509 | M14: =L17 -> 56.270702 | N14: =M17 -> 8.9506937
C15: Drawdown to fund acquisitions | D15: A$m | E15: 0 | F15: =-Model!F65 -> 50.6 | G15: =-Model!G65 -> 0 | H15: =-Model!H65 -> 0 | I15: =-Model!I65 -> 0 | J15: =-Model!J65 -> 0 | K15: =-Model!K65 -> 0 | L15: =-Model!L65 -> 0 | M15: =-Model!M65 -> 0 | N15: =-Model!N65 -> 0 | P15: The Munich acquisition was 'funded from existing finance facilities' per the Annual Report, so it draws debt rather than consuming cash.
C16: Repayment from surplus cash flow | D16: A$m | E16: =Historicals!H52-'Debt & Leases'!E14 -> -43.5 | F16: =-MIN(MAX(0,F27-$E$10),F14+F15) -> -37.898254 | G16: =-MIN(MAX(0,G27-$E$10),G14+G15) -> -19.133777 | H16: =-MIN(MAX(0,H27-$E$10),H14+H15) -> -25.604373 | I16: =-MIN(MAX(0,I27-$E$10),I14+I15) -> -25.64972 | J16: =-MIN(MAX(0,J27-$E$10),J14+J15) -> -26.631191 | K16: =-MIN(MAX(0,K27-$E$10),K14+K15) -> -33.053177 | L16: =-MIN(MAX(0,L27-$E$10),L14+L15) -> -39.858808 | M16: =-MIN(MAX(0,M27-$E$10),M14+M15) -> -47.320008 | N16: =-MIN(MAX(0,N27-$E$10),N14+N15) -> -8.9506937 | P16: Cash sweep: any cash above the minimum operating balance repays debt, capped at the amount outstanding. This is a policy assumption, not a contractual one.
C17: Closing gross debt | D17: A$m | E17: =SUM(E14:E16) -> 213.5 | F17: =F14+F15+F16 -> 226.20175 | G17: =G14+G15+G16 -> 207.06797 | H17: =H14+H15+H16 -> 181.4636 | I17: =I14+I15+I16 -> 155.81388 | J17: =J14+J15+J16 -> 129.18269 | K17: =K14+K15+K16 -> 96.129509 | L17: =L14+L15+L16 -> 56.270702 | M17: =M14+M15+M16 -> 8.9506937 | N17: =N14+N15+N16 -> 0
C19: CASH FLOW WATERFALL
C20: Opening cash | D20: A$m | E20: =Historicals!G51 -> 119.1 | F20: =E28 -> 93.9 | G20: =F28 -> 60 | H20: =G28 -> 60 | I20: =H28 -> 60 | J20: =I28 -> 60 | K20: =J28 -> 60 | L20: =K28 -> 60 | M20: =L28 -> 60 | N20: =M28 -> 60
C21: Unlevered free cash flow (FCFF) | D21: A$m | E21: =Model!E79 -> 77.352626 | F21: =Model!F79 -> -8.9774219 | G21: =Model!G79 -> 61.52468 | H21: =Model!H79 -> 70.362315 | I21: =Model!I79 -> 72.530921 | J21: =Model!J79 -> 74.864666 | K21: =Model!K79 -> 82.275773 | L21: =Model!L79 -> 89.291796 | ... N21: =Model!N79 -> 98.911251 | P21: Already net of capex, working capital and the acquisition
C22: Less: interest on debt | D22: A$m | E22: -12.1 | F22: =-F14*$E$7 -> -11.956 | G22: =-G14*$E$7 -> -12.667298 | H22: =-H14*$E$7 -> -11.595806 | I22: =-I14*$E$7 -> -10.161961 | J22: =-J14*$E$7 -> -8.7255771 | K22: =-K14*$E$7 -> -7.2342304 | L22: =-L14*$E$7 -> -5.3832525 | M22: =-M14*$E$7 -> -3.1511593 | N22: =-N14*$E$7 -> -0.50123885 | P22: Charged on the OPENING balance, deliberately. Using the average balance would make interest depend on the repayment, which depends on cash flow, which depends on interest — a circular reference. Banks resolve that with iterative calculation; a template that has to survive being emailed around should not rely on it.
C23: Add: interest earned on cash | D23: A$m | E23: 4 | F23: =F20*$E$8 -> 3.2865 | G23: =G20*$E$8 -> 2.1 | H23: =H20*$E$8 -> 2.1 | I23: =I20*$E$8 -> 2.1 | J23: =J20*$E$8 -> 2.1 | K23: =K20*$E$8 -> 2.1 | L23: =L20*$E$8 -> 2.1 | M23: =M20*$E$8 -> 2.1 | N23: =N20*$E$8 -> 2.1
C24: Add: tax shield on net interest | D24: A$m | E24: =-(E22+E23)*Historicals!$H$65 -> 2.4290764 | F24: =-(F22+F23)*Historicals!$H$65 -> 2.5998615 | G24: =-(G22+G23)*Historicals!$H$65 -> 3.1689844 | H24: =-(H22+H23)*Historicals!$H$65 -> 2.8476591 | I24: =-(I22+I23)*Historicals!$H$65 -> 2.4176692 | J24: =-(J22+J23)*Historicals!$H$65 -> 1.9869177 | K24: =-(K22+K23)*Historicals!$H$65 -> 1.5396837 | L24: =-(L22+L23)*Historicals!$H$65 -> 0.98460138 | ... N24: =-(N22+N23)*Historicals!$H$65 -> -0.47944605 | P24: FCFF was struck after tax on the FULL EBIT, so the tax saved on interest has to be handed back here. This is the other side of the rule that the tax shield belongs in the WACC, not in FCFF.
C25: Memo: NPAT | D25: A$m | E25: =(Model!E55+'Debt & Leases'!E22+'Debt & Leases'!E23)*(1-Historicals!$H$65) -> 67.981702 | F25: =(Model!F55+F22+F23)*(1-Historicals!$H$65) -> 58.651833 | G25: =(Model!G55+G22+G23)*(1-Historicals!$H$65) -> 65.041989 | H25: =(Model!H55+H22+H23)*(1-Historicals!$H$65) -> 70.836051 | I25: =(Model!I55+I22+I23)*(1-Historicals!$H$65) -> 76.648531 | J25: =(Model!J55+J22+J23)*(1-Historicals!$H$65) -> 81.031256 | K25: =(Model!K55+K22+K23)*(1-Historicals!$H$65) -> 84.810502 | L25: =(Model!L55+L22+L23)*(1-Historicals!$H$65) -> 87.610292 | M25: =(Model!M55+M22+M23)*(1-Historicals!$H$65) -> 89.92922 | N25: =(Model!N55+N22+N23)*(1-Historicals!$H$65) -> 91.989335
C26: Less: dividends paid | D26: A$m | E26: -31.1 | F26: =-F25*$E$9 -> -31.554686 | G26: =-G25*$E$9 -> -34.99259 | H26: =-H25*$E$9 -> -38.109795 | I26: =-I25*$E$9 -> -41.23691 | J26: =-J25*$E$9 -> -43.594815 | K26: =-K25*$E$9 -> -45.62805 | L26: =-L25*$E$9 -> -47.134337 | M26: =-M25*$E$9 -> -48.38192 | N26: =-N25*$E$9 -> -49.490262
C27: Cash before debt movements | D27: A$m | E27: =E20+E21+E22+E23+E24+E26+E15 -> 159.6817 | F27: =F20+F21+F22+F23+F24+F26+F15 -> 97.898254 | G27: =G20+G21+G22+G23+G24+G26+G15 -> 79.133777 | H27: =H20+H21+H22+H23+H24+H26+H15 -> 85.604373 | I27: =I20+I21+I22+I23+I24+I26+I15 -> 85.64972 | J27: =J20+J21+J22+J23+J24+J26+J15 -> 86.631191 | K27: =K20+K21+K22+K23+K24+K26+K15 -> 93.053177 | L27: =L20+L21+L22+L23+L24+L26+L15 -> 99.858808 | ... N27: =N20+N21+N22+N23+N24+N26+N15 -> 110.5403 | P27: The FY26A column anchors opening and closing balances to reported figures; it is NOT a full cash reconciliation of the actual year, because the modelled FCFF differs from reported operating cash flow on working capital timing. The waterfall operates from FY27 onward.
C28: Closing cash | D28: A$m | E28: =Historicals!H51 -> 93.9 | F28: =F27+F16 -> 60 | G28: =G27+G16 -> 60 | H28: =H27+H16 -> 60 | I28: =I27+I16 -> 60 | J28: =J27+J16 -> 60 | K28: =K27+K16 -> 60 | L28: =L27+L16 -> 60 | M28: =M27+M16 -> 60 | N28: =N27+N16 -> 101.58961
C30: NET DEBT AND COVENANT HEADROOM
C31: Closing net debt (excluding leases) | D31: A$m | E31: =E17-E28 -> 119.6 | F31: =F17-F28 -> 166.20175 | G31: =G17-G28 -> 147.06797 | H31: =H17-H28 -> 121.4636 | I31: =I17-I28 -> 95.813877 | J31: =J17-J28 -> 69.182686 | K31: =K17-K28 -> 36.129509 | L31: =L17-L28 -> -3.7292983 | ... N31: =N17-N28 -> -101.58961
C32: EBITDA (pre-AASB 16, covenant basis) | D32: A$m | E32: =Model!E48 -> 160.8009 | F32: =Model!F48 -> 153.1837 | G32: =Model!G48 -> 161.55517 | H32: =Model!H48 -> 166.7257 | I32: =Model!I48 -> 173.2404 | J32: =Model!J48 -> 179.45671 | K32: =Model!K48 -> 185.95746 | L32: =Model!L48 -> 191.40587 | ... N32: =Model!N48 -> 200.83663
C33: Net leverage ratio | D33: x | E33: =IFERROR(E31/E32,0) -> 0.74377693 | F33: =IFERROR(F31/F32,0) -> 1.0849832 | G33: =IFERROR(G31/G32,0) -> 0.91032659 | H33: =IFERROR(H31/H32,0) -> 0.72852355 | I33: =IFERROR(I31/I32,0) -> 0.55306889 | J33: =IFERROR(J31/J32,0) -> 0.38551183 | K33: =IFERROR(K31/K32,0) -> 0.19428911 | L33: =IFERROR(L31/L32,0) -> -0.019483719 | ... N33: =IFERROR(N31/N32,0) -> -0.50583208 | P33: FY26A reads 0.74x against the 0.77x CKF reports on p.10 — and the gap is instructive rather than an error. Solving back, the covenant EBITDA is about $155m, which is continuing-operations EBITDA of $160.8m LESS the $5.6m pre-AASB 16 Taco Bell loss. In other words the covenant is struck on total group earnings including discontinued operations, while this row uses continuing operations.
C34: Covenant headroom | D34: x | E34: =$E$11-E33 -> 2.2562231 | F34: =$E$11-F33 -> 1.9150168 | G34: =$E$11-G33 -> 2.0896734 | H34: =$E$11-H33 -> 2.2714764 | I34: =$E$11-I33 -> 2.4469311 | J34: =$E$11-J33 -> 2.6144882 | K34: =$E$11-K33 -> 2.8057109 | L34: =$E$11-L33 -> 3.0194837 | ... N34: =$E$11-N33 -> 3.5058321
C35: Additional debt capacity at the covenant limit | D35: A$m | E35: =E32*$E$11-E31 -> 362.8027 | F35: =F32*$E$11-F31 -> 293.34935 | G35: =G32*$E$11-G31 -> 337.59755 | H35: =H32*$E$11-H31 -> 378.7135 | I35: =I32*$E$11-I31 -> 423.90733 | J35: =J32*$E$11-J31 -> 469.18745 | K35: =K32*$E$11-K31 -> 521.74287 | L35: =L32*$E$11-L31 -> 577.94692 | ... N35: =N32*$E$11-N31 -> 704.0995 | P35: The number an acquirer or a board asks for first: how much more could this balance sheet borrow before it breaches? It also frames whether CKF could fund further German bolt-ons without equity.
C36: Interest cover (EBITDA / net interest) | D36: x | E36: =IFERROR(-E32/(E22+E23),0) -> 19.851963 | F36: =IFERROR(-F32/(F22+F23),0) -> 17.669266 | G36: =IFERROR(-G32/(G22+G23),0) -> 15.28822 | H36: =IFERROR(-H32/(H22+H23),0) -> 17.557824 | I36: =IFERROR(-I32/(I22+I23),0) -> 21.488617 | J36: =IFERROR(-J32/(J22+J23),0) -> 27.085446 | K36: =IFERROR(-K32/(K22+K23),0) -> 36.21915 | L36: =IFERROR(-L32/(L22+L23),0) -> 58.29764 | ... N36: =IFERROR(-N32/(N22+N23),0) -> -125.62016
C38: LEASE LIABILITY ROLL-FORWARD (memo)
C39: Opening lease liability | D39: A$m | E39: =Historicals!G54 -> 633.6 | F39: =E42 -> 630.5 | G39: =F42 -> 654.09929 | H39: =G42 -> 700.00212 | I39: =H42 -> 731.6701 | J39: =I42 -> 765.05209 | K39: =J42 -> 799.39928 | L39: =K42 -> 832.84766 | M39: =L42 -> 863.40112 | N39: =M42 -> 890.88075
C40: New and renewed leases | D40: A$m | E40: =E42-E39-E41 -> 54.8 | F40: =F42-F39-F41 -> 83.666455 | G40: =G42-G39-G41 -> 110.18535 | H40: =H42-H39-H41 -> 98.858618 | I40: =I42-I39-I41 -> 103.63816 | J40: =J42-J39-J41 -> 107.75753 | K40: =K42-K39-K41 -> 109.93034 | L40: =L42-L39-L41 -> 109.84121 | ... N40: =N42-N39-N41 -> 110.42791 | P40: Signing a lease is a financing event, not a cash outflow — an asset and a liability appear together. That is exactly why leased restaurants look free in a post-AASB 16 cash flow.
C41: Principal repayments | D41: A$m | E41: =-Historicals!H59 -> -57.9 | F41: =E41*(1+Model!F41) -> -60.067167 | G41: =F41*(1+Model!G41) -> -64.282511 | H41: =G41*(1+Model!H41) -> -67.190641 | I41: =H41*(1+Model!I41) -> -70.256171 | J41: =I41*(1+Model!J41) -> -73.410338 | K41: =J41*(1+Model!K41) -> -76.481966 | L41: =K41*(1+Model!L41) -> -79.287747 | M41: =L41*(1+Model!M41) -> -81.811254 | N41: =M41*(1+Model!N41) -> -84.218146
C42: Closing lease liability | D42: A$m | E42: =Historicals!H54 -> 630.5 | F42: =F39*(1+Model!F41) -> 654.09929 | G42: =G39*(1+Model!G41) -> 700.00212 | H42: =H39*(1+Model!H41) -> 731.6701 | I42: =I39*(1+Model!I41) -> 765.05209 | J42: =J39*(1+Model!J41) -> 799.39928 | K42: =K39*(1+Model!K41) -> 832.84766 | L42: =L39*(1+Model!L41) -> 863.40112 | M42: =M39*(1+Model!M41) -> 890.88075 | N42: =N39*(1+Model!N41) -> 917.09052
C43: Lease-adjusted leverage ((net debt + leases) / post-AASB 16 EBITDA) | D43: x | E43: =IFERROR((E31+E42)/Model!E45,0) -> 3.0678824 | F43: =IFERROR((F31+F42)/Model!F45,0) -> 3.3956098 | G43: =IFERROR((G31+G42)/Model!G45,0) -> 3.295535 | H43: =IFERROR((H31+H42)/Model!H45,0) -> 3.1898834 | I43: =IFERROR((I31+I42)/Model!I45,0) -> 3.0797324 | J43: =IFERROR((J31+J42)/Model!J45,0) -> 2.979454 | K43: =IFERROR((K31+K42)/Model!K45,0) -> 2.8606835 | L43: =IFERROR((L31+L42)/Model!L45,0) -> 2.7323585 | ... N43: =IFERROR((N31+N42)/Model!N45,0) -> 2.4413575 | P43: The covenant says 0.77x. Capitalise the leases and the same company is around 3x. Neither number is wrong — they answer different questions. Knowing both, and knowing why they differ, is the point.

Sheet WACC
B2: WEIGHTED AVERAGE COST OF CAPITAL
C3: Two WACCs are computed. The capital structure MUST match the cash flow definition: leases are debt only when rent has been added back to EBITDA.
C5: MARKET INPUTS
C6: Risk free rate | E6: 0.049 | K6: Australian 10-year Commonwealth Government bond yield, approximately 4.9% in early August 2026.
C7: Market risk premium | E7: 0.06 | K7: 6.0% is the figure most commonly adopted in Australian independent expert reports. It is an assumption.
C8: Corporate tax rate | E8: 0.3 | K8: Australian statutory rate. FY26 underlying effective rate was 29.9%.
C10: BETA — UNLEVER THE COMPARABLES, THEN RELEVER FOR CKF
C11: Comparable company | E11: Equity beta | F11: Net debt / equity | G11: Tax rate | H11: Unlevered beta
C12: Domino's Pizza Enterprises (ASX:DMP) | E12: 1.02 | F12: 0.39 | G12: 0.3 | H12: =IFERROR(E12/(1+(1-G12)*F12),"") -> 0.80125687 | K12: Net debt is from FY25 as FY26 results are not out yet. Will be updated as and when available
C13: Guzman y Gomez (ASX:GYG) | E13: 0.91 | F13: 0.05 | G13: 0.3 | H13: =IFERROR(E13/(1+(1-G13)*F13),"") -> 0.87922705
C14: Arcos Dorados (NYSE:ARCO) | E14: 0.5 | F14: 1.16 | G14: 0.3 | H14: =IFERROR(E14/(1+(1-G14)*F14),"") -> 0.27593819
C15: Yum! Brands (NYSE:YUM) | E15: 0.55 | F15: 0.32 | G15: 0.21 | H15: =IFERROR(E15/(1+(1-G15)*F15),"") -> 0.4390166
C16: Yum China (NYSE:YUMC) | E16: 0.08 | F16: 0.055 | G16: 0.25 | H16: =IFERROR(E16/(1+(1-G16)*F16),"") -> 0.076830732
C17: Median unlevered beta of the comparables | H17: =IFERROR(MEDIAN(H12:H16),"n/a") -> 0.4390166
C18: Selected unlevered (asset) beta | E18: 0.8 | K18: Using 0.80 here as it is close to asx listed dominos and GyG. Damodarans unlevered beta for restaurant in US is 0.77.
C20: CAPITAL STRUCTURE AT MARKET VALUE
C21: Share price (A$) | E21: 8.24 | K21: Closing price early August 2026. Update to your valuation date.
C22: Shares on issue (m) | E22: =Historicals!H11/(Historicals!H16/100) -> 118.07692 | K22: Derived: underlying NPAT divided by reported basic EPS. Cross-check against the share count in the Annual Report — this gives the weighted average, not the closing count.
C23: Market capitalisation (A$m) | E23: =E21*E22 -> 972.95385
C24: Net debt excluding leases (A$m) | E24: =Historicals!H53 -> 119.6
C25: Lease liabilities (A$m) | E25: =Historicals!H54 -> 630.5
C26: Debt used in the WACC | E26: =E24 -> 119.6 | K26: Lease liabilities are deliberately EXCLUDED, because the cash flows still carry rent as an operating cost. Including them here while also expensing rent would penalise the same obligation twice.
C27: Debt / (debt + equity) | E27: =E26/(E26+E23) -> 0.10946829
C28: Debt / equity | E28: =E26/E23 -> 0.12292464
C30: COST OF EQUITY
C31: Relevered equity beta | E31: =E18*(1+(1-E8)*E28) -> 0.8688378 | K31: Hamada relevering. Note the beta is materially higher on a post-AASB 16 basis — capitalising leases makes the equity look more levered, which is economically correct.
C32: Cost of equity | E32: =E6+E31*E7 -> 0.10113027 | K32: CAPM: risk free rate plus beta times market risk premium.
C34: COST OF DEBT
C35: Cost of corporate debt (pre-tax) | E35: 0.056 | K35: Approximately BBSW plus a corporate margin. CKF refinanced during FY26; the facility margin is in the Annual Report debt note — replace this placeholder with the actual margin.
C36: Cost of lease debt (pre-tax) | E36: =Historicals!H70 -> 0.051259964 | K36: The incremental borrowing rate implied by CKF's own lease accounting — lease interest over the average lease liability.
C37: Pre-tax cost of debt used | E37: =E35 -> 0.056
C38: After-tax cost of debt | E38: =E37*(1-E8) -> 0.0392
C40: WACC
C41: WACC | E41: =E32*(1-E27)+E38*E27 -> 0.094350867
C43: MEMO: WHAT A LEASE-ADJUSTED CAPITAL STRUCTURE WOULD LOOK LIKE | K43: Not used in the valuation — here to helo answer the question
C44: Gearing including lease liabilities | E44: =(E24+E25)/(E24+E25+E23) -> 0.43533172
C45: Relevered beta on that basis | E45: =E18*(1+(1-E8)*(E24+E25)/E23) -> 1.2317327
C46: Lease-adjusted net leverage (net debt + leases / post-AASB 16 EBITDA) | E46: =(E24+E25)/Historicals!H7 -> 3.0678937 | K46: CKF reports net leverage of 0.77x on a pre-AASB 16 covenant basis. Capitalising leases tells a very different story about how levered this business really is — worth raising yourself.
C48: A caveat worth knowing:
C49: The comparables' observed equity betas already embed their own lease obligations, so unlevering them on financial debt alone is a simplification. Raise it before someone raises it for you.

Sheet DCF
B2: DISCOUNTED CASH FLOW
C3: Valued as at the FY26 balance date of 3 May 2026. The stub period to the 8 August 2026 valuation date is not rolled forward — a documented simplification.
C5: A$ millions unless stated | D5: Unit | F5: FY27E | G5: FY28E | H5: FY29E | I5: FY30E | J5: FY31E | K5: FY32E | L5: FY33E | M5: FY34E | N5: FY35E | P5: Note
C6: DISCOUNTING
C7: Period number | F7: 1 | G7: 2 | H7: 3 | I7: 4 | J7: 5 | K7: 6 | L7: 7 | M7: 8 | N7: 9
C8: Discount period | F8: =F7-IF(Control!$D$10=1,0.5,0) -> 0.5 | G8: =G7-IF(Control!$D$10=1,0.5,0) -> 1.5 | H8: =H7-IF(Control!$D$10=1,0.5,0) -> 2.5 | I8: =I7-IF(Control!$D$10=1,0.5,0) -> 3.5 | J8: =J7-IF(Control!$D$10=1,0.5,0) -> 4.5 | K8: =K7-IF(Control!$D$10=1,0.5,0) -> 5.5 | L8: =L7-IF(Control!$D$10=1,0.5,0) -> 6.5 | M8: =M7-IF(Control!$D$10=1,0.5,0) -> 7.5 | N8: =N7-IF(Control!$D$10=1,0.5,0) -> 8.5 | P8: Mid-year convention assumes cash arrives evenly through the year rather than all on the last day. It lifts the explicit-period cash flows by about 4%, but the terminal value is discounted at the full final period either way — so the effect on total value is much smaller than people expect.
C9: WACC (active basis) | E9: =WACC!E41 -> 0.094350867
C10: Discount factor | F10: =1/(1+$E$9)^F8 -> 0.95592035 | G10: =1/(1+$E$9)^G8 -> 0.87350445 | H10: =1/(1+$E$9)^H8 -> 0.79819414 | I10: =1/(1+$E$9)^I8 -> 0.7293768 | J10: =1/(1+$E$9)^J8 -> 0.66649264 | K10: =1/(1+$E$9)^K8 -> 0.60903012 | L10: =1/(1+$E$9)^L8 -> 0.55652181 | M10: =1/(1+$E$9)^M8 -> 0.50854057 | N10: =1/(1+$E$9)^N8 -> 0.46469609
C11: FCFF (active basis) | F11: =Model!F79 -> -8.9774219 | G11: =Model!G79 -> 61.52468 | H11: =Model!H79 -> 70.362315 | I11: =Model!I79 -> 72.530921 | J11: =Model!J79 -> 74.864666 | K11: =Model!K79 -> 82.275773 | L11: =Model!L79 -> 89.291796 | M11: =Model!M79 -> 96.43786 | N11: =Model!N79 -> 98.911251
C12: Present value of FCFF | F12: =F11*F10 -> -8.5817002 | G12: =G11*G10 -> 53.742082 | H12: =H11*H10 -> 56.162787 | I12: =I11*I10 -> 52.902372 | J12: =J11*J10 -> 49.896749 | K12: =K11*K10 -> 50.108424 | L12: =L11*L10 -> 49.692832 | M12: =M11*M10 -> 49.042564 | N12: =N11*N10 -> 45.963671
C13: Sum of present values, FY27E to FY35E | E13: =SUM(F12:N12) -> 398.92978
C15: TERMINAL YEAR NORMALISATION
C16: FY31E is still a heavy investment year. Capitalising it unadjusted assumes CKF opens 24 restaurants a year forever while growing revenue at 2.5% — which cannot both be true.
C17: Terminal growth rate | E17: =Assumptions!E133 -> 0.02
C18: FY35E revenue growth as forecast | E18: =Model!N41 -> 0.029420061 | P18: Compare with the terminal growth rate above. The gap is the problem this block fixes.
C19: FY35E FCFF as forecast | E19: =N11 -> 98.911251
C20: Add back: FY35E capex as forecast | E20: =Model!N61 -> 65.979686 | P20: Added back because it is already deducted inside FCFF above; the normalised figure is then charged in its place.
C21: FY35E depreciation and amortisation | E21: =-Model!N51 -> 71.043459
C22: Terminal capex / depreciation ratio | E22: 1 | P22: 1.0x is the textbook steady-state relationship. Consider 1.1-1.2x here: CKF's asset base is young after five years of heavy building, so reported depreciation still understates the replacement spending a mature estate would need. Each 0.1x is worth roughly $1 per share.
C23: Less: normalised steady-state capex | E23: =E21*(1+E17)*E22 -> 72.464328 | P23: In a steady state growing at g, capex must approximate depreciation grown at g — otherwise the asset base compounds away from revenue forever. As forecast, FY31 capex is about 1.7x depreciation, which is a growth-phase ratio, not a perpetuity one.
C24: FY35E working capital release as forecast | E24: =Model!N64 -> 3.6412245
C25: Normalised working capital release at terminal growth | E25: =-Model!N63*E17 -> 2.5481589 | P25: Working capital is negative, so growth releases cash — but only in proportion to growth. At 2.5% the release is far smaller than in an 8% growth year.
C26: Normalised terminal FCFF | E26: =E19+E20-E23-E24+E25 -> 91.333544
C27: Terminal FCFF used | E27: =E26 -> 91.333544 | P27: Switch 5 on Control. Normalised is the defensible default; 'as forecast' is provided so you can see how much the choice is worth.
C29: TERMINAL VALUE
C30: Terminal value — Gordon growth | E30: =IF($E$9<=$E$17,0,E27*(1+E17)/($E$9-E17)) -> 1252.9809 | P30: Terminal year cash flow grown one year, divided by WACC less growth. Guarded so it returns zero rather than a negative value if growth ever exceeds WACC.
C31: Terminal year EBITDA (active basis) | E31: =Model!N48 -> 200.83663
C32: Exit EV/EBITDA multiple | E32: =Assumptions!E134 -> 6
C33: Terminal value — exit multiple | E33: =E31*E32 -> 1205.0198
C34: Terminal value — selected method | E34: =CHOOSE(Control!$D$9,E30,E33) -> 1252.9809
C35: Terminal discount factor | E35: =1/(1+$E$9)^N7 -> 0.44421245 | P35: Discounted at the full final period, not the mid-year period, because terminal value represents value at the END of FY31.
C36: Present value of terminal value | E36: =E34*E35 -> 556.5897
C37: Cross-check: multiple implied by the Gordon terminal value | E37: =IFERROR(E30/E31,0) -> 6.2388065 | P37: If the Gordon method implies an exit multiple far from where comparables trade, one of the two inputs is wrong. This is the most useful sanity check in any DCF.
C38: Cross-check: growth implied by the exit multiple | E38: =IFERROR(($E$9*E33-E27)/(E33+E27),0) -> 0.017249246 | P38: The reverse test: what perpetual growth rate would justify your exit multiple? If it exceeds nominal GDP growth, the multiple is too high.
C40: ENTERPRISE VALUE AND EQUITY BRIDGE
C41: Enterprise value | E41: =E13+E36 -> 955.51948
C42: Less: net debt excluding leases | E42: =-Historicals!H53 -> -119.6
C43: Less: lease liabilities | E43: 0 | P43: DELIBERATELY ZERO. The cash flows above still carry rent as an operating cost, so the lease obligation is already reflected. Deducting the $630.5m liability here as well would charge for the same leases twice. See the AASB 16 block below.
C44: Total net debt deducted | E44: =E42+E43 -> -119.6
C45: Equity value | E45: =E41+E44 -> 835.91948
C46: Shares on issue (m) | E46: =WACC!E22 -> 118.07692
C47: Value per share (A$) | E47: =E45/E46 -> 7.0794483
C48: Current share price (A$) | E48: =WACC!E21 -> 8.24
C49: Premium / (discount) to market | E49: =E47/E48-1 -> -0.14084365
C51: IMPLIED MULTIPLES AND DIAGNOSTICS
C52: Implied FY27E EV/EBITDA | E52: =E41/Model!E80 -> 5.942252
C53: Terminal value as % of enterprise value | E53: =E36/E41 -> 0.58249958 | P53: Above roughly 75% and the valuation is mostly an opinion about perpetuity rather than about the forecast. Typical for a stable, cash-generative business — but know the number before you are asked.
C54: Implied market capitalisation | E54: =E45 -> 835.91948
C56: AASB 16: WHY THIS MODEL VALUES BEFORE LEASE CAPITALISATION
C57: The single most likely technical question on this model. The arithmetic below is the answer.
C58: FY27E rent added back if valuing post-AASB 16 | E58: =-Model!F47 -> 88.393245
C59: After-tax value of that rent | E59: =E58*(1-Historicals!$H$65) -> 61.885351
C60: Capitalised in perpetuity at (WACC less growth) | E60: =IF($E$9<=$E$17,0,E59/($E$9-$E$17)) -> 832.34201
C61: Reported lease liability available to offset it | E61: =Historicals!H54 -> 630.5
C62: Unfunded gap | E62: =E60-E61 -> 201.84201 | P62: THE POINT. Adding rent back to EBITDA creates value in perpetuity, but the balance sheet lease liability only covers committed lease terms — roughly a decade, not forever. Deducting the book liability therefore offsets only a fraction of what was added back, and a naive post-AASB 16 DCF overvalues the equity by the gap shown here. Fixing it properly requires capitalising the full perpetual lease obligation, not the accounting number. Valuing pre-AASB 16 sidesteps the problem entirely, and matches how CKF's own banking covenants measure leverage (0.77x at FY26).
C64: What you still need the post-AASB 16 numbers for:
C65: Comparing multiples against peers. Almost every screen and broker model now quotes EV/EBITDA on a post-AASB 16 basis. Both EBITDA measures are on the Model sheet — just never mix one company's pre-AASB 16 EBITDA with another's post-AASB 16 multiple.
B69: Sensitivity Analysis
B71: GRID 1 - Value per share: WACC vs Terminal growth
C73: WACC / Growth
C74: =E47 -> 7.0794483 | D74: 0.015 | E74: 0.02 | F74: 0.025 | G74: 0.03 | H74: 0.035
C75: =C76-0.5% -> 0.0844 | D75: 7.9624342 | E75: 8.4318268 | F75: 8.9804354 | G75: 9.6301029 | H75: 10.411515
C76: =C77-0.5% -> 0.0894 | D76: 7.3106374 | E76: 7.7032796 | F76: 8.1570627 | G76: 8.6874261 | H76: 9.3154858
C77: 0.0944 | D77: 6.7419795 | E77: 7.0736783 | F77: 7.453325 | G77: 7.8920877 | H77: 8.4048945
C78: =C77+0.5% -> 0.0994 | D78: 6.2416385 | E78: 6.5242838 | F78: 6.8450558 | G78: 7.2121951 | H78: 7.6365015
C79: =C78+0.5% -> 0.1044 | D79: 5.7981105 | E79: 6.0408002 | F79: 6.3141782 | G79: 6.6244319 | H79: 6.9795315
C82: WACC / Exit EV/EBITDA Multiple
C83: =E47 -> 7.0794483 | D83: =E83-1 -> 5 | E83: =F83-1 -> 6 | F83: 7 | G83: =F83+1 -> 8 | H83: =G83+1 -> 9
C84: =C85-0.5% -> 0.0844 | D84: 8.4318268 | E84: 8.4318268 | F84: 8.4318268 | G84: 8.4318268 | H84: 8.4318268
C85: =C86-0.5% -> 0.0894 | D85: 7.7032796 | E85: 7.7032796 | F85: 7.7032796 | G85: 7.7032796 | H85: 7.7032796
C86: 0.0944 | D86: 7.0736783 | E86: 7.0736783 | F86: 7.0736783 | G86: 7.0736783 | H86: 7.0736783
C87: =C86+0.5% -> 0.0994 | D87: 6.5242838 | E87: 6.5242838 | F87: 6.5242838 | G87: 6.5242838 | H87: 6.5242838
C88: =C87+0.5% -> 0.1044 | D88: 6.0408002 | E88: 6.0408002 | F88: 6.0408002 | G88: 6.0408002 | H88: 6.0408002

Sheet Comps
B2: TRADING COMPARABLES AND FOOTBALL FIELD
C5: TRADING COMPARABLES
C6: Company | D6: Share price | E6: Shares (m) | F6: Market cap | G6: Net debt | H6: Enterprise value | I6: LTM / last reported FY EBITDA | K6: Notes
C7: Domino's Pizza Enterprises (ASX:DMP) | D7: 19.75 | E7: 94.75 | F7: =IFERROR(D7*E7,"") -> 1871.3125 | G7: 724.8 | H7: =IFERROR(F7+G7,"") -> 2596.1125 | I7: 184.4 | K7: Shares and Share price as of 11 Aug 2026
C8: Guzman y Gomez (ASX:GYG) | D8: 24.58 | E8: 99.59 | F8: =IFERROR(D8*E8,"") -> 2447.9222 | G8: 133.2 | H8: =IFERROR(F8+G8,"") -> 2581.1222 | I8: 65 | K8: Shares and Share price as of 16 Aug 2026
C9: Arcos Dorados (NYSE:ARCO) | D9: 7.91 | E9: 210.66 | F9: =IFERROR(D9*E9,"") -> 1666.3206 | G9: 1930 | H9: =IFERROR(F9+G9,"") -> 3596.3206 | I9: 613
C10: Yum! Brands (NYSE:YUM) | D10: 148.11 | E10: 272.9 | F10: =IFERROR(D10*E10,"") -> 40419.219 | G10: 1248 | H10: =IFERROR(F10+G10,"") -> 41667.219 | I10: 2910
C11: Yum China (NYSE:YUMC) | D11: 47.59 | E11: 342.46 | F11: =IFERROR(D11*E11,"") -> 16297.671 | G11: 892 | H11: =IFERROR(F11+G11,"") -> 17189.671 | I11: 1880
C12: Collins Foods (ASX:CKF) | D12: =WACC!E21 -> 8.24 | E12: =WACC!E22 -> 118.07692 | F12: =D12*E12 -> 972.95385 | G12: =Historicals!H53 -> 119.6 | H12: =F12+G12 -> 1092.5538 | I12: =Model!F80 -> 153.1837 | K12: CKF on a PRE-AASB 16 basis, consistent with the DCF.
C13: Collins Foods — post-AASB 16 basis | F13: =F12 -> 972.95385 | G13: =Historicals!H62 -> 750.1 | H13: =F13+G13 -> 1723.0538 | I13: =Model!F45 -> 241.57694 | K13: The same company restated with leases as debt. Use THIS row if your peer multiples are quoted post-AASB 16, which most screens now are.
C14: EV / FY1 EBITDA
C15: Multiple by company
C16: =C7 -> Domino's Pizza Enterprises (ASX:DMP) | D16: =IFERROR(H7/I7,"") -> 14.078701
C17: =C8 -> Guzman y Gomez (ASX:GYG) | D17: =IFERROR(H8/I8,"") -> 39.709572
C18: =C9 -> Arcos Dorados (NYSE:ARCO) | D18: =IFERROR(H9/I9,"") -> 5.8667546
C19: =C10 -> Yum! Brands (NYSE:YUM) | D19: =IFERROR(H10/I10,"") -> 14.318632
C20: =C11 -> Yum China (NYSE:YUMC) | D20: =IFERROR(H11/I11,"") -> 9.1434422
C21: =C12 -> Collins Foods (ASX:CKF) | D21: =IFERROR(H12/I12,"") -> 7.1323115
C22: =C13 -> Collins Foods — post-AASB 16 basis | D22: =IFERROR(H13/I13,"") -> 7.1325261
C23: Peer median | D23: 8 | K23: Trading comparables are not meaningful for CKF. Of the listed peers, Domino's, Yum! Brands and Yum China are franchisors — asset-light royalty models trading at 8.7x–17.3x — and Guzman y Gomez is a growth-stage operator on ~40x. The only directly comparable listed KFC franchisee, Restaurant Brands New Zealand, was acquired by Finaccess and delisted in December 2025. RBD's undisturbed trading multiple of approximately 8x is adopted here, with the 9.8x transaction multiple shown separately as a precedent transaction
C25: FOOTBALL FIELD — VALUE PER SHARE
C26: Methodology | D26: Low | E26: High | F26: Width | K26: Source
C27: DCF — Gordon growth (WACC ±1%, g 1.5–3.5%) | D27: =DCF!D78 -> 6.2416385 | E27: =DCF!H76 -> 9.3154858 | F27: =E27-D27 -> 3.0738474 | K27: Opposite corners of sensitivity grid 1
C28: DCF — exit multiple (6.5–8.5x, WACC ±1%) | D28: =DCF!D87 -> 6.5242838 | E28: =DCF!H85 -> 7.7032796 | F28: =E28-D28 -> 1.1789959 | K28: Opposite corners of sensitivity grid 2
C29: Scenario range (downside to upside) | D29: 9.7 | E29: 13.86 | F29: =E29-D29 -> 4.16 | K29: Recorded by setting the Control scenario switch to 3 and then 2 on the as-built assumptions.
C30: Trading comparables (peer median ±1x) | D30: =IFERROR((Model!E45*(D23-1)-Historicals!H62)/DCF!$E$46,"") -> 8.1422032 | E30: =IFERROR((Model!E45*(D23+1)-Historicals!H62)/DCF!$E$46,"") -> 12.283587 | F30: =E30-D30 -> 4.1413833 | K30: Calculates once the peer table above is populated
C31: Broker consensus price target | D31: 10.27 | E31: 10.27 | F31: =E31-D31 -> 0 | K31: Reported 12-month consensus target of approximately $10.27 in early August 2026.
C32: 52-week trading range | D32: 7.7 | E32: 11.68 | F32: =E32-D32 -> 3.98 | K32: From stockanalysis.com
C33: Current share price | D33: =WACC!E21 -> 8.24 | E33: =WACC!E21 -> 8.24 | F33: =E33-D33 -> 0
C35: To turn this into an actual football field chart: select the low and high columns, insert a stacked bar chart, set the 'low' series fill to No Fill, and add a vertical line at the current share price.

Sheet Notes & Audit
B2: NOTES AND AUDIT TRAIL
B3: My working notes on this model. I wrote these as I built it, including the parts I got wrong first.
B5: WHAT THIS MODEL IS
B6: Company | C6: Collins Foods Limited (ASX: CKF). It runs 295 KFC restaurants in Australia, 63 in the Netherlands and 17 in Germany.
B7: Method | C7: Discounted cash flow. I forecast free cash flow to the firm and discount it at the WACC.
B8: Base year | C8: FY26, the 53 weeks to 3 May 2026.
B9: Forecast | C9: Nine years, FY27 to FY35.
B10: My answer | C10: $11.75 a share. The market price was $8.24 and broker consensus was $10.27.
B12: WHERE MY NUMBERS COME FROM
B13: CKF FY26 Results Presentation | C13: Released 30 June 2026. Most of my history comes from here.
B14: CKF FY26 Annual Report | C14: I used this for three things the presentation does not give: the growth rate for each European country, the asset lives in Note G5, and the Munich purchase price.
B15: RBA Table F2 | C15: Australian 10 year government bond yield. This is the official source and it is free.
B16: stockanalysis.com | C16: Share prices, share counts and betas for the peer companies.
B17: Damodaran, NYU Stern | C17: Restaurant sector unlevered beta, January 2026 update. Free and widely used.
B19: HOW I BUILT IT
B20: Order of work | C20: 1. Historicals with a source for every number. 2. The AASB 16 lease bridge. 3. The FY26 column of the Model. 4. Assumptions in three cases. 5. Forecast years. 6. Capex and debt schedules. 7. WACC, DCF and checks.
B21: Why this order | C21: I cannot forecast something I have not first reconciled. Building the assumptions before the engine would have meant rewiring everything later.
B23: THE FY26 COLUMN — THE MOST IMPORTANT PART
B24: What it does | C24: Column E on the Model tab rebuilds FY26 using exactly the same formulas as the forecast years. The only difference is that it is fed by reported numbers.
B25: Why it matters | C25: It ties back to reported revenue and EBITDA with no difference. If it did not tie, the forecast would not be worth reading. It is easy to build a forecast that looks sensible and is quietly wrong, and this is the cheapest way to prove it is not.
B27: LEASES, AND WHY I VALUE BEFORE AASB 16
B28: The problem | C28: CKF leases almost all of its 375 restaurants. Under AASB 16 the rent leaves EBITDA and comes back as depreciation and interest. FY26 EBITDA is $160.8m before AASB 16 and $244.5m after. Same business, $83.7m apart.
B29: The rule | C29: The debt in my WACC has to match how I treat rent. If rent is still a cost, leases are not debt. If I add rent back, leases are debt and I must deduct them.
B30: What I did | C30: I value before AASB 16. Rent stays as a cost and I do not deduct the lease liability.
B31: Why not the other way | C31: I tried it. Adding rent back creates value forever, but the lease liability on the balance sheet only covers leases already signed, roughly ten years. So the liability offsets only part of what I added back. The gap is about $400m, which is around 25% of the equity. That is why I stopped.
B32: A useful check | C32: CKF's own bank covenant is measured before AASB 16 as well, at 0.77 times. So my basis matches how the company is actually financed.
B34: SPLITTING GERMANY FROM THE NETHERLANDS
B35: The problem | C35: CKF reports Europe as one segment, so it does not give revenue by country.
B36: How I solved it | C36: The Annual Report says Netherlands revenue grew 11.6% and German sales grew 15.8%. With reported Europe revenue for both years, that is two equations and two unknowns.
B37: The answer | C37: Netherlands $274.8m and Germany $76.5m in FY26. Average unit volumes of $4.40m and $4.63m.
B38: Why I like this | C38: Because I worked out both countries separately, the fact that they add back to reported Europe revenue is a real check, not just arithmetic. It is one of the checks on the Control tab.
B40: DEPRECIATION
B41: What I used | C41: Note G5 gives the lives: leasehold improvements are 20 years or the lease term, plant and equipment is 8 years, motor vehicles 4 years.
B42: My assumption | C42: I split capex 55% leasehold improvements and 45% plant and equipment, and used 15 years for leasehold improvements because most restaurant leases run 10 to 15 years. The split is my estimate. Note G5 gives the lives but not the mix.
B43: How it works | C43: Each year of capex is depreciated on its own line. The assets that existed at FY26 run off separately. FY26 depreciation ties back to the reported figure.
B44: A mistake I fixed | C44: My first version worked out a depreciation rate using net book value but applied it as if it were a rate on original cost. Those are different numbers. It made the assets look like they had 4.7 years of life when Note G5 says 8 years for equipment. Both figures are real but they measure different things: 4.7 years is what is left in the current balance, 8 years is the life of a new asset.
B46: BETA
B47: What I used | C47: An unlevered beta of 0.80.
B48: How I got there | C48: Domino's Pizza Enterprises gives 0.80. Guzman y Gomez gives 0.88. Damodaran's restaurant sector, from 64 companies, gives 0.77. Three different methods, all close together.
B49: Market not book | C49: I used market value of equity, not book value. Beta comes from share prices, so the gearing has to be measured the same way. Yum! Brands has negative book equity after years of buybacks, so book value would not work at all.
B50: Why not CKF's own beta | C50: Screeners show CKF at about 0.45. I did not use it. One company's beta is not reliable on its own, and the ASX 200 is mostly banks and miners, so a food business looks less connected to the index than it really is. A low beta here means low correlation, not low risk.
B51: What I rejected | C51: Damodaran's Australia and New Zealand restaurant figure was far lower. The sample is too small to trust, and Australian restaurants cannot really be half as risky as American ones.
B53: WHY THERE ARE NO TRADING COMPARABLES
B54: The right comparison is gone | C54: The only true match was Restaurant Brands New Zealand, another KFC franchisee. Finaccess bought it at NZ$5.05 a share and it delisted in December 2025.
B55: The rest do not fit | C55: Domino's, Yum! Brands and Yum China are franchisors. They collect royalties and own very few assets, so the market pays them much higher multiples. Yum's depreciation is 2.7% of revenue against CKF at about 7%. Guzman y Gomez is a growth company trading near 40 times.
B56: What went wrong | C56: Using their median of about 14 times valued CKF above $20 a share. That is more than twice my DCF and the market price, so I removed it.
B57: What I show instead | C57: I leave the trading comparables line out and explain why. Saying which comparables do not work is more useful than showing a number I know is wrong.
B59: WHAT I CHECKED
B60: Integrity checks | C60: There are 16 checks on the Control tab and they all pass.
B61: The main ones | C61: FY26 revenue and EBITDA rebuild to zero difference. The Europe split adds back to reported revenue. Depreciation ties to the reported figure. Debt and lease balances tie to the balance sheet. Cash never goes below the minimum and the covenant is never breached.
B62: Cross-check on terminal value | C62: My terminal value implies an exit multiple of 7.35 times. CKF trades near 7 times. If those two were far apart, one of my inputs would be wrong.
B64: WHAT I DID NOT DO
B65: No three statement model | C65: I have a fixed asset schedule, a debt schedule and a lease schedule, but no balance sheet that balances. So there is no balance sheet check.
B66: No stub period | C66: I value at the balance date of 3 May 2026, not at today's date.
B67: No currency layer | C67: European earnings are modelled in Australian dollars, even though FY26 included a $16.0m gain from currency translation.
B68: Franchise renewal assumed | C68: The Netherlands franchise agreement runs to 31 December 2029, which is inside my forecast. I assume it is renewed.
B69: No value for future deals | C69: I only included the Munich acquisition because it has completed. I have not forecast any further acquisitions, so I have not deducted any money for them either.
B71: THINGS I KNOW ARE STILL ROUGH
B72: Working capital | C72: I use minus 6% of revenue. It is negative because restaurants take cash immediately and pay suppliers later. I have not built it from the receivables and payables notes yet.
B73: Covenant limit | C73: I assume 3.0 times. It is not disclosed in anything I could find. It drives the debt capacity numbers, so it should be confirmed.
B74: Munich purchase price split | C74: I paid $50.6m in total. I assumed about 40% is plant and equipment. CKF's own allocation is not final until the HY27 accounts.
B75: The last four years | C75: FY32 to FY35 are my own extrapolation. CKF only plans five years ahead. A longer forecast means less weight on the terminal value but more of my own guesswork inside it.
B77: QUESTIONS I EXPECT
B78: Why is terminal value 65% of the total? | C78: That is normal for a steady business. I checked it against the implied exit multiple of 7.35 times, which is close to where CKF trades. I also extended the forecast to nine years to bring this figure down from 85%.
B79: Why nine years and not five? | C79: At five years the business was still investing heavily. Capex was 1.7 times depreciation in FY31 and revenue was still growing 8%, so I could not apply a 2.5% growth rate to it. By FY35 capex and depreciation are almost equal, which is what a steady state looks like.
B80: Why tax EBIT and not profit before tax? | C80: Free cash flow to the firm is measured before financing. The tax saving on interest is already inside the WACC, so taking it here as well would count it twice.
B81: Why is your value 43% above the market? | C81: Most of it is the German rollout and the margin improvement in Europe. My downside case gives $7.08, which is close to the market price. So the market is pricing something near my downside.
B82: What would change your mind? | C82: A higher beta. At 0.95 my value falls to about $10.10. Beta is the input my answer is most sensitive to and it is the one I am least certain about.
B84: FIXED IN THIS VERSION
B85: External links removed | C85: This file used to link to another workbook. 94 formulas read the scenario and discounting switches from that other file instead of this one, so those switches did nothing. I pointed them at the Control tab in this file and removed the link.
B86: Terminal basis switch | C86: The switch that chose between the normalised and unadjusted terminal year had been deleted from the Control tab, so its formula was broken. I set it to the normalised figure, which is what it was already calculating.
B87: Two stray cells cleared | C87: Historicals E6 and L6 were left over from earlier work. E6 referred to itself, which is a circular reference, and L6 depended on it. Neither was used anywhere else, so I cleared both. The file now calculates with no errors.
B89: This model is for learning and illustration. It is not investment advice and not a professional valuation. The forecasts are my own and are not company guidance.
